Workbook

Sheet April 25
A1: April | B1: Shopify
A3: Products | B3: Total revenue | C3: Total expense | D3: Total P/L | E3: Profit % | F3: P/pcs | G3: Ad spent | H3: Total orders | I3: Shipped | J3: Product expense | K3: Delivered | L3: Shipping charges | M3: RTO | N3: In-transit | O3: RTO% | P3: Shipped% | Q3: Delivered % | R3: CPD | S3: Cancellation %
A4: V1 | B4: 584117 | C4: =G4+J4+L4 -> 186864 | D4: =B4-C4 -> 397253 | E4: =D4/B4*100 -> 68.009149 | F4: =D4/K4 -> 704.34929 | H4: 607 | I4: 588 | J4: =250*K4 -> 141000 | K4: 564 | L4: =I4*78 -> 45864 | M4: =I4-K4-N4 -> 24 | O4: =M4/I4*100 -> 4.0816327 | P4: =I4/H4*100 -> 96.869852 | Q4: =K4/I4*100 -> 95.918367 | R4: =G4/K4 -> 0 | S4: =100-P4 -> 3.1301483 | T4: =B4/B21*100 -> 9.6820739
A5: V1- P of 2 | B5: 23288 | C5: =G5+J5+L5 -> 6936 | D5: =B5-C5 -> 16352 | E5: =D5/B5*100 -> 70.21642 | F5: =D5/K5 -> 1362.6667 | H5: 13 | I5: 12 | J5: =500*K5 -> 6000 | K5: 12 | L5: =I5*78 -> 936 | M5: =I5-K5-N5 -> 0 | O5: =M5/I5*100 -> 0 | P5: =I5/H5*100 -> 92.307692 | Q5: =K5/I5*100 -> 100 | R5: =G5/K5 -> 0 | S5: =100-P5 -> 7.6923077 | T5: =B5/B21*100 -> 0.38601194
A6: V2 | B6: 849827 | C6: =G6+J6+L6 -> 297662 | D6: =B6-C6 -> 552165 | E6: =D6/B6*100 -> 64.973812 | F6: =D6/K6 -> 802.56541 | H6: 751 | I6: 729 | J6: =350*K6 -> 240800 | K6: 688 | L6: =I6*78 -> 56862 | M6: =I6-K6-N6 -> 41 | O6: =M6/I6*100 -> 5.6241427 | P6: =I6/H6*100 -> 97.070573 | Q6: =K6/I6*100 -> 94.375857 | R6: =G6/K6 -> 0 | S6: =100-P6 -> 2.9294274 | T6: =B6/B21*100 -> 14.086369
A7: V2- P of 2 | B7: 44780 | C7: =G7+J7+L7 -> 14860 | D7: =B7-C7 -> 29920 | E7: =D7/B7*100 -> 66.815543 | F7: =D7/K7 -> 1574.7368 | H7: 20 | I7: 20 | J7: =700*K7 -> 13300 | K7: 19 | L7: =I7*78 -> 1560 | M7: =I7-K7-N7 -> 1 | O7: =M7/I7*100 -> 5 | P7: =I7/H7*100 -> 100 | Q7: =K7/I7*100 -> 95 | R7: =G7/K7 -> 0 | S7: =100-P7 -> 0 | T7: =B7/B21*100 -> 0.74225415
A8: V3 | B8: 201900 | C8: =G8+J8+L8 -> 88770 | D8: =B8-C8 -> 113130 | E8: =D8/B8*100 -> 56.032689 | F8: =D8/K8 -> 992.36842 | H8: 122 | I8: 115 | J8: =700*K8 -> 79800 | K8: 114 | L8: =I8*78 -> 8970 | M8: =I8-K8-N8 -> 1 | O8: =M8/I8*100 -> 0.86956522 | P8: =I8/H8*100 -> 94.262295 | Q8: =K8/I8*100 -> 99.130435 | R8: =G8/K8 -> 0 | S8: =100-P8 -> 5.7377049 | T8: =B8/B21*100 -> 3.3466082
A9: V4 | B9: 131285 | C9: =G9+J9+L9 -> 83024 | D9: =B9-C9 -> 48261 | E9: =D9/B9*100 -> 36.760483 | F9: =D9/K9 -> 163.59661 | H9: 322 | I9: 308 | J9: =200*K9 -> 59000 | K9: 295 | L9: =I9*78 -> 24024 | M9: =I9-K9-N9 -> 13 | O9: =M9/I9*100 -> 4.2207792 | P9: =I9/H9*100 -> 95.652174 | Q9: =K9/I9*100 -> 95.779221 | R9: =G9/K9 -> 0 | S9: =100-P9 -> 4.3478261 | T9: =B9/B21*100 -> 2.1761241
A10: V4- P of 2 | B10: 51303 | C10: =G10+J10+L10 -> 29236 | D10: =B10-C10 -> 22067 | E10: =D10/B10*100 -> 43.013079 | F10: =D10/K10 -> 361.7541 | H10: 66 | I10: 62 | J10: =400*K10 -> 24400 | K10: 61 | L10: =I10*78 -> 4836 | M10: =I10-K10-N10 -> 1 | O10: =M10/I10*100 -> 1.6129032 | P10: =I10/H10*100 -> 93.939394 | Q10: =K10/I10*100 -> 98.387097 | R10: =G10/K10 -> 0 | S10: =100-P10 -> 6.0606061 | T10: =B10/B21*100 -> 0.85037661
A11: V5 | B11: 74759 | C11: =G11+J11+L11 -> 24506 | D11: =B11-C11 -> 50253 | E11: =D11/B11*100 -> 67.22 | F11: =D11/K11 -> 679.09459 | H11: 83 | I11: 77 | J11: =250*K11 -> 18500 | K11: 74 | L11: =I11*78 -> 6006 | M11: =I11-K11-N11 -> 3 | O11: =M11/I11*100 -> 3.8961039 | P11: =I11/H11*100 -> 92.771084 | Q11: =K11/I11*100 -> 96.103896 | R11: =G11/K11 -> 0 | S11: =100-P11 -> 7.2289157 | T11: =B11/B21*100 -> 1.2391732
A12: V6 | B12: 908265 | C12: =G12+J12+L12 -> 343618 | D12: =B12-C12 -> 564647 | E12: =D12/B12*100 -> 62.167649 | F12: =D12/K12 -> 713.83944 | H12: 882 | I12: 856 | J12: =350*K12 -> 276850 | K12: 791 | L12: =I12*78 -> 66768 | M12: =I12-K12-N12 -> 65 | O12: =M12/I12*100 -> 7.5934579 | P12: =I12/H12*100 -> 97.052154 | Q12: =K12/I12*100 -> 92.406542 | R12: =G12/K12 -> 0 | S12: =100-P12 -> 2.9478458 | T12: =B12/B21*100 -> 15.055013
A13: V6- P of 2 | B13: 40608 | C13: =G13+J13+L13 -> 14782 | D13: =B13-C13 -> 25826 | E13: =D13/B13*100 -> 63.598306 | F13: =D13/K13 -> 1359.2632 | H13: 20 | I13: 19 | J13: =700*K13 -> 13300 | K13: 19 | L13: =I13*78 -> 1482 | M13: =I13-K13-N13 -> 0 | O13: =M13/I13*100 -> 0 | P13: =I13/H13*100 -> 95 | Q13: =K13/I13*100 -> 100 | R13: =G13/K13 -> 0 | S13: =100-P13 -> 5 | T13: =B13/B21*100 -> 0.67310086
A14: V7 | B14: 113826 | C14: =G14+J14+L14 -> 56612 | D14: =B14-C14 -> 57214 | E14: =D14/B14*100 -> 50.264439 | F14: =D14/K14 -> 589.83505 | H14: 110 | I14: 104 | J14: =500*K14 -> 48500 | K14: 97 | L14: =I14*78 -> 8112 | M14: =I14-K14-N14 -> 7 | O14: =M14/I14*100 -> 6.7307692 | P14: =I14/H14*100 -> 94.545455 | Q14: =K14/I14*100 -> 93.269231 | R14: =G14/K14 -> 0 | S14: =100-P14 -> 5.4545455 | T14: =B14/B21*100 -> 1.8867312
A15: V8 | B15: 145054 | C15: =G15+J15+L15 -> 64264 | D15: =B15-C15 -> 80790 | E15: =D15/B15*100 -> 55.696499 | F15: =D15/K15 -> 985.2439 | H15: 102 | I15: 88 | J15: =700*K15 -> 57400 | K15: 82 | L15: =I15*78 -> 6864 | M15: =I15-K15-N15 -> 6 | O15: =M15/I15*100 -> 6.8181818 | P15: =I15/H15*100 -> 86.27451 | Q15: =K15/I15*100 -> 93.181818 | R15: =G15/K15 -> 0 | S15: =100-P15 -> 13.72549 | T15: =B15/B21*100 -> 2.4043531
A16: V9 | B16: 2414163 | C16: =G16+J16+L16 -> 1123392 | D16: =B16-C16 -> 1290771 | E16: =D16/B16*100 -> 53.466605 | F16: =D16/K16 -> 1129.2835 | H16: 1277 | I16: 1214 | J16: =900*K16 -> 1028700 | K16: 1143 | L16: =I16*78 -> 94692 | M16: =I16-K16-N16 -> 71 | O16: =M16/I16*100 -> 5.8484349 | P16: =I16/H16*100 -> 95.066562 | Q16: =K16/I16*100 -> 94.151565 | R16: =G16/K16 -> 0 | S16: =100-P16 -> 4.9334377 | T16: =B16/B21*100 -> 40.016135
A17: V9 P of 2 | B17: 147995 | C17: =G17+J17+L17 -> 73476 | D17: =B17-C17 -> 74519 | E17: =D17/B17*100 -> 50.352377 | F17: =D17/K17 -> 1910.7436 | H17: 45 | I17: 42 | J17: =1800*K17 -> 70200 | K17: 39 | L17: =I17*78 -> 3276 | M17: =I17-K17-N17 -> 3 | O17: =M17/I17*100 -> 7.1428571 | P17: =I17/H17*100 -> 93.333333 | Q17: =K17/I17*100 -> 92.857143 | R17: =G17/K17 -> 0 | S17: =100-P17 -> 6.6666667 | T17: =B17/B21*100 -> 2.4531019
A18: V6-V2 Combo | B18: 142122 | C18: =G18+J18+L18 -> 50648 | D18: =B18-C18 -> 91474 | E18: =D18/B18*100 -> 64.363012 | F18: =D18/K18 -> 1407.2923 | H18: 71 | I18: 66 | J18: =K18*700 -> 45500 | K18: 65 | L18: =I18*78 -> 5148 | M18: =I18-K18-N18 -> 1 | O18: =M18/I18*100 -> 1.5151515 | P18: =I18/H18*100 -> 92.957746 | Q18: =K18/I18*100 -> 98.484848 | R18: =G18/K18 -> 0 | S18: =100-P18 -> 7.0422535 | T18: =B18/B21*100 -> 2.3557536
A19: V6-V4 Combo | B19: 22508 | C19: =G19+J19+L19 -> 7536 | D19: =B19-C19 -> 14972 | E19: =D19/B19*100 -> 66.518571 | F19: =D19/K19 -> 1247.6667 | H19: 13 | I19: 12 | J19: =K19*550 -> 6600 | K19: 12 | L19: =I19*78 -> 936 | M19: =I19-K19-N19 -> 0 | O19: =M19/I19*100 -> 0 | P19: =I19/H19*100 -> 92.307692 | Q19: =K19/I19*100 -> 100 | R19: =G19/K19 -> 0 | S19: =100-P19 -> 7.6923077 | T19: =B19/B21*100 -> 0.37308299
A20: Busy Book | B20: 137174 | C20: =G20+J20+L20 -> 74507 | D20: =B20-C20 -> 62667 | E20: =D20/B20*100 -> 45.684313 | F20: =D20/K20 -> 238.27757 | H20: 264 | I20: 264 | J20: =K20*205 -> 53915 | K20: 263 | L20: =I20*78 -> 20592 | M20: =I20-K20-N20 -> 1 | O20: =M20/I20*100 -> 0.37878788 | P20: =I20/H20*100 -> 100 | Q20: =K20/I20*100 -> 99.621212 | R20: =G20/K20 -> 0 | S20: =100-P20 -> 0 | T20: =B20/B21*100 -> 2.2737376
A21: Total | B21: =SUM(B4:B20) -> 6032974 | D21: =SUM(D4:D20) -> 3492281 | G21: 3500724 | H21: =SUM(H4:H20) -> 4768 | I21: =SUM(I4:I20) -> 4576 | J21: =SUM(J4:J20) -> 2183765 | K21: =SUM(K4:K20) -> 4338 | L21: =SUM(L4:L20) -> 356928 | M21: =SUM(M4:M20) -> 238 | N21: =SUM(N4:N20) -> 0 | R21: =SUM(R4:R20) -> 0
A24: Shopify | D24: Blended
A25: Total Revenue | B25: =B21 -> 6032974 | D25: COGS | E25: =B26/K21 -> 503.40364
A26: COGS | B26: =J21 -> 2183765 | C26: 0.36 | D26: CAC | E26: =B28/K21 -> 806.99032
A27: Logistics | B27: =L21 -> 356928 | C27: 0.06 | D27: Logistics | E27: =L21/K21 -> 82.279391
A28: Marketing | B28: =G21 -> 3500724 | C28: 0.58 | D28: AOV | E28: =B25/K21 -> 1390.7271
A29: P&L | B29: =B25-(B26+B27+B28) -> -8443
A30: P&L %
A33: April | B33: Amazon
B35: Total revenue | C35: Total expense | D35: Total P/L | E35: Profit % | F35: P/pcs | G35: Total orders | H35: Product expense | I35: Delivered | J35: Return | K35: Amazon expense | L35: RTO% | M35: Only Ad spend | N35: Return GMV
A36: V1 | B36: =897486+37687.24+15175.92 -> 950349.16 | C36: =K36+H36 -> 586466.44 | D36: =B36-C36 -> 363882.72 | E36: =D36/B36*100 -> 38.289371 | F36: =D36/I36 -> 378.65007 | G36: =1018+37+10 -> 1065 | H36: =250*I36 -> 240250 | I36: =909+32+20 -> 961 | J36: =G36-I36 -> 104 | K36: =330908.99+13077.61+2229.84 -> 346216.44 | L36: =J36/G36*100 -> 9.7652582 | N36: =J36*999 -> 103896 | O36: =B36/M36 -> #DIV/0! | P36: =B36/B51*100 -> 33.651225
A37: V2 | B37: =682999+28950.52 -> 711949.52 | C37: =K37+H37 -> 345782.34 | D37: =B37-C37 -> 366167.18 | E37: =D37/B37*100 -> 51.431621 | F37: =D37/I37 -> 617.4826 | G37: =608+26 -> 634 | H37: =350*I37 -> 207550 | I37: =571+22 -> 593 | J37: =G37-I37 -> 41 | K37: =128290.96 + 9941.38 -> 138232.34 | L37: =J37/G37*100 -> 6.466877 | M37: 0 | N37: =J37*1119 -> 45879 | O37: =B37/M37 -> #DIV/0! | P37: =B37/B51*100 -> 25.209654
A38: V3 | B38: =8495 -> 8495 | C38: =K38+H38 -> 5781.95 | D38: =B38-C38 -> 2713.05 | E38: =D38/B38*100 -> 31.937022 | F38: =D38/I38 -> 542.61 | G38: 5 | H38: =900*I38 -> 4500 | I38: 5 | J38: =G38-I38 -> 0 | K38: =1281.95 -> 1281.95 | L38: =J38/G38*100 -> 0 | M38: 0 | N38: =J38*1799 -> 0 | O38: =B38/M38 -> #DIV/0! | P38: =B38/B51*100 -> 0.30080224
A39: V4 | B39: =401764+7122.92 -> 408886.92 | C39: =K39+H39 -> 351973.5 | D39: =B39-C39 -> 56913.42 | E39: =D39/B39*100 -> 13.91911 | F39: =D39/I39 -> 65.872014 | G39: =914+11 -> 925 | H39: =220*I39 -> 190080 | I39: =11+853 -> 864 | J39: =G39-I39 -> 61 | K39: =160673.89 + 1219.61 -> 161893.5 | L39: =J39/G39*100 -> 6.5945946 | M39: 0 | N39: =J39*499 -> 30439 | O39: =B39/M39 -> #DIV/0! | P39: =B39/B51*100 -> 14.478411
A40: V5 | B40: =5836.96+52653 -> 58489.96 | C40: =K40+H40 -> 57243.72 | D40: =B40-C40 -> 1246.24 | E40: =D40/B40*100 -> 2.1306905 | F40: =D40/I40 -> 19.4725 | G40: =67+10 -> 77 | H40: =250*I40 -> 16000 | I40: =59+5 -> 64 | J40: =G40-I40 -> 13 | K40: =9362.66+31881.06 -> 41243.72 | L40: =J40/G40*100 -> 16.883117 | M40: 0 | N40: =J40*1049 -> 13637 | O40: =B40/M40 -> #DIV/0! | P40: =B40/B51*100 -> 2.0710902
A41: V6 | B41: =8994+224817 -> 233811 | C41: =K41+H41 -> 153158.13 | D41: =B41-C41 -> 80652.87 | E41: =D41/B41*100 -> 34.4949 | F41: =D41/I41 -> 389.62739 | G41: =245+7 -> 252 | H41: =320*I41 -> 66240 | I41: =201+6 -> 207 | J41: =G41-I41 -> 45 | K41: =2992.3+83925.83 -> 86918.13 | L41: =J41/G41*100 -> 17.857143 | M41: 0 | N41: =J41*1249 -> 56205 | O41: =B41/M41 -> #DIV/0! | P41: =B41/B51*100 -> 8.2790904
A42: V7 | B42: =10054.48+57064 -> 67118.48 | C42: =K42+H42 -> 58514.81 | D42: =B42-C42 -> 8603.67 | E42: =D42/B42*100 -> 12.818631 | F42: =D42/I42 -> 191.19267 | G42: =37+10 -> 47 | H42: =500*I42 -> 22500 | I42: =37+8 -> 45 | J42: =G42-I42 -> 2 | K42: =28226.67 + 7788.14 -> 36014.81 | L42: =J42/G42*100 -> 4.2553191 | M42: 0 | N42: =J42*1349 -> 2698 | O42: =B42/M42 -> #DIV/0! | P42: =B42/B51*100 -> 2.3766203
A43: V8 | B43: 0 | C43: =K43+H43 -> 0 | D43: =B43-C43 -> 0 | E43: =D43/B43*100 -> #DIV/0! | F43: =D43/I43 -> #DIV/0! | G43: 0 | H43: =800*I43 -> 0 | I43: 0 | J43: =G43-I43 -> 0 | K43: 0 | L43: =J43/G43*100 -> #DIV/0! | M43: 0 | N43: =J43*1899 -> 0 | O43: =B43/M43 -> #DIV/0! | P43: =B43/B51*100 -> 0
A44: V9 | B44: =173817+119322.96 -> 293139.96 | C44: =K44+H44 -> 197022.87 | D44: =B44-C44 -> 96117.09 | E44: =D44/B44*100 -> 32.788805 | F44: =D44/I44 -> 691.48986 | G44: =100+62 -> 162 | H44: =1000*I44 -> 139000 | I44: =84+55 -> 139 | J44: =G44-I44 -> 23 | K44: =33042.98+24979.89 -> 58022.87 | L44: =J44/G44*100 -> 14.197531 | M44: 0 | N44: =J44*1999 -> 45977 | O44: =B44/M44 -> #DIV/0! | P44: =B44/B51*100 -> 10.379889
A45: BB | B45: =50716 -> 50716 | C45: =K45+H45 -> 41926.86 | D45: =B45-C45 -> 8789.14 | E45: =D45/B45*100 -> 17.330113 | F45: =D45/I45 -> 101.0246 | G45: 92 | H45: =200*I45 -> 17400 | I45: 87 | J45: =G45-I45 -> 5 | K45: =24526.86 -> 24526.86 | L45: =J45/G45*100 -> 5.4347826 | M45: 0 | N45: =J45*599 -> 2995 | O45: =B45/M45 -> #DIV/0! | P45: =B45/B51*100 -> 1.7958195
A46: V1V4 | B46: 0 | C46: =K46+H46 -> 0 | D46: =B46-C46 -> 0 | E46: =D46/B46*100 -> #DIV/0! | F46: =D46/I46 -> #DIV/0! | G46: 0 | H46: =(270+220)*I46 -> 0 | I46: 0 | J46: =G46-I46 -> 0 | K46: 0 | L46: =J46/G46*100 -> #DIV/0! | M46: 0 | O46: =B46/M46 -> #DIV/0! | P46: =B46/B51*100 -> 0
A47: V1V2 | B47: =24788 -> 24788 | C47: =K47+H47 -> 11072.68 | D47: =B47-C47 -> 13715.32 | E47: =D47/B47*100 -> 55.330482 | F47: =D47/I47 -> 1142.9433 | G47: 12 | H47: =(270+350)*I47 -> 7440 | I47: 12 | J47: =G47-I47 -> 0 | K47: =3632.68 -> 3632.68 | L47: =J47/G47*100 -> 0 | M47: 0 | N47: =J47*2199 -> 0 | O47: =B47/M47 -> #DIV/0! | P47: =B47/B51*100 -> 0.87772643
A48: V1V6 | B48: =10384.29 -> 10384.29 | C48: =K48+H48 -> 5746.73 | D48: =B48-C48 -> 4637.56 | E48: =D48/B48*100 -> 44.659385 | F48: =D48/I48 -> 772.92667 | G48: 8 | H48: =(270+320)*I48 -> 3540 | I48: 6 | J48: =G48-I48 -> 2 | K48: =2206.73 -> 2206.73 | L48: =J48/G48*100 -> 25 | M48: 0 | N48: =J48*999 -> 1998 | O48: =B48/M48 -> #DIV/0! | P48: =B48/B51*100 -> 0.36770073
A49: V2V4 | B49: =5986.29 -> 5986.29 | C49: =K49+H49 -> 10052.55 | D49: =B49-C49 -> -4066.26 | E49: =D49/B49*100 -> -67.926211 | F49: =D49/I49 -> -1355.42 | G49: 6 | H49: =(350+220)*I49 -> 1710 | I49: 3 | J49: =G49-I49 -> 3 | K49: =8342.55 -> 8342.55 | L49: =J49/G49*100 -> 50 | M49: 0 | N49: =J49*1499 -> 4497 | O49: =B49/M49 -> #DIV/0! | P49: =B49/B51*100 -> 0.21197051
A50: V2V6 | B50: 0 | C50: =K50+H50 -> 0 | D50: =B50-C50 -> 0 | E50: =D50/B50*100 -> #DIV/0! | F50: =D50/I50 -> #DIV/0! | G50: 0 | H50: =(350+320)*I50 -> 0 | I50: 0 | J50: =G50-I50 -> 0 | K50: 0 | L50: =J50/G50*100 -> #DIV/0! | M50: 0 | N50: =J50*999 -> 0 | O50: =B50/M50 -> #DIV/0! | P50: =B50/B51*100 -> 0
A51: Total | B51: =SUM(B36:B50) -> 2824114.6 | C51: =SUM(C36:C50) -> 1824742.6 | D51: =B51-C51 -> 999372 | G51: =SUM(G34:G50) -> 3285 | H51: =SUM(H36:H50) -> 916210 | I51: =SUM(I34:I50) -> 2986 | K51: =SUM(K36:K50) -> 908532.58 | M51: =SUM(M34:M50) -> 0
K52: =K51-300000 -> 608532.58
K53: =K51-K52 -> 300000
A54: Total Revenue | B54: =B51 -> 2824114.6 | K54: 459232.58
A55: COGS | B55: =H51 -> 916210 | D55: Blended
A56: Amazon Cumi | B56: =K54 -> 459232.58 | D56: COGS | E56: =B55/I51 -> 306.83523 | F56: 0.39
A57: Logi | B57: 149300 | H57: =50*I51 -> 149300
A58: Marketing | B58: =K53 -> 300000 | D58: CAC | E58: =B58/I51 -> 100.46885 | F58: 0.1 | H58: =B56-H57 -> 309932.58
A59: Net P&L | B59: =B54-SUM(B55:B58) -> 999372 | D59: Commisions | E59: =B56/I51 -> 153.79524 | F59: 0.146
A60: P&L % | B60: =B59/B54*100 -> 35.387091 | D60: AOV | E60: =B54/I51 -> 945.78519
A66: April | B66: Flipkart
B68: Total revenue | C68: Total expense | D68: Total P/L | E68: Profit % | F68: P/pcs | G68: Total orders | H68: Product expense | I68: Delivered | J68: Return | K68: Flipkart expenses | L68: RTO% | M68: Only Ad spend
A69: V1 | B69: =21514+1847 -> 23361 | C69: =K69+H69 -> 13176.9 | D69: =B69-C69 -> 10184.1 | E69: =D69/B69*100 -> 43.594452 | F69: =D69/I69 -> 509.205 | G69: 34 | H69: =270*I69 -> 5400 | I69: 20 | J69: =G69-I69 -> 14 | K69: =8325.35+-548.45 -> 7776.9 | L69: =J69/G69*100 -> 41.176471 | M69: =20%*B69 -> 4672.2
A70: V2 | B70: =27928 -> 27928 | C70: =K70+H70 -> 17189.92 | D70: =B70-C70 -> 10738.08 | E70: =D70/B70*100 -> 38.449155 | F70: =D70/I70 -> 488.09455 | G70: 32 | H70: =350*I70 -> 7700 | I70: 22 | J70: =G70-I70 -> 10 | K70: =9489.92 -> 9489.92 | L70: =J70/G70*100 -> 31.25 | M70: =20%*B70 -> 5585.6
A71: V3 | B71: 0 | C71: =K71+H71 -> 362.26 | D71: =B71-C71 -> -362.26 | E71: =D71/B71*100 -> #DIV/0! | F71: =D71/I71 -> #DIV/0! | G71: 1 | H71: =980*I71 -> 0 | I71: 0 | J71: =G71-I71 -> 1 | K71: =362.26 -> 362.26 | L71: =J71/G71*100 -> 100 | M71: =20%*B71 -> 0
A72: V4 | B72: =19007+949 -> 19956 | C72: =K72+H72 -> 19088.29 | D72: =B72-C72 -> 867.71 | E72: =D72/B72*100 -> 4.3481159 | F72: =D72/I72 -> 22.248974 | G72: 56 | H72: =220*I72 -> 8580 | I72: 39 | J72: =G72-I72+2 -> 19 | K72: =10176.58+331.71 -> 10508.29 | L72: =J72/G72*100 -> 33.928571 | M72: =20%*B72 -> 3991.2
A73: V5 | B73: =6894 -> 6894 | C73: =K73+H73 -> 3862.12 | D73: =B73-C73 -> 3031.88 | E73: =D73/B73*100 -> 43.978532 | F73: =D73/I73 -> 505.31333 | G73: 8 | H73: =270*I73 -> 1620 | I73: 6 | J73: =G73-I73 -> 2 | K73: =2242.12 -> 2242.12 | L73: =J73/G73*100 -> 25 | M73: =20%*B73 -> 1378.8
A74: V6 | B74: =38205 -> 38205 | C74: =K74+H74 -> 23136.26 | D74: =B74-C74 -> 15068.74 | E74: =D74/B74*100 -> 39.441801 | F74: =D74/I74 -> 502.29133 | G74: 45 | H74: =320*I74 -> 9600 | I74: 30 | J74: =G74-I74 -> 15 | K74: =13536.26 -> 13536.26 | L74: =J74/G74*100 -> 33.333333 | M74: =20%*B74 -> 7641
A75: V7 | B75: =2798 -> 2798 | C75: =K75+H75 -> 1985.84 | D75: =B75-C75 -> 812.16 | E75: =D75/B75*100 -> 29.026447 | F75: =D75/I75 -> 406.08 | G75: 4 | H75: =470*I75 -> 940 | I75: 2 | J75: =G75-I75 -> 2 | K75: =1045.84 -> 1045.84 | L75: =J75/G75*100 -> 50 | M75: =20%*B75 -> 559.6
A76: Wooden cal | B76: =7130 -> 7130 | C76: =K76+H76 -> 4936.3 | D76: =B76-C76 -> 2193.7 | E76: =D76/B76*100 -> 30.767181 | F76: =D76/I76 -> 219.37 | G76: 12 | H76: =200*I76 -> 2000 | I76: 10 | J76: =G76-I76 -> 2 | K76: =2936.3 -> 2936.3 | L76: =J76/G76*100 -> 16.666667 | M76: =20%*B76 -> 1426
A77: V9 | B77: =55353 -> 55353 | C77: =K77+H77 -> 46712.94 | D77: =B77-C77 -> 8640.06 | E77: =D77/B77*100 -> 15.609018 | F77: =D77/I77 -> 320.00222 | G77: 49 | H77: =1000*I77 -> 27000 | I77: 27 | J77: =G77-I77 -> 22 | K77: =19712.94 -> 19712.94 | L77: =J77/G77*100 -> 44.897959 | M77: 0
A78: V4V2 | B78: =4947 -> 4947 | C78: =K78+H78 -> 3174.19 | D78: =B78-C78 -> 1772.81 | E78: =D78/B78*100 -> 35.836062 | F78: =D78/I78 -> 590.93667 | G78: 3 | H78: =(220+350)*I78 -> 1710 | I78: 3 | J78: =G78-I78 -> 0 | K78: =1464.19 -> 1464.19 | L78: =J78/G78*100 -> 0 | M78: =20%*B78 -> 989.4
A79: V1V4 | B79: =10143 -> 10143 | C79: =K79+H79 -> 7030.9 | D79: =B79-C79 -> 3112.1 | E79: =D79/B79*100 -> 30.682244 | F79: =D79/I79 -> 444.58571 | G79: 12 | H79: =(270+220)*I79 -> 3430 | I79: 7 | J79: =G79-I79 -> 5 | K79: =3600.9 -> 3600.9 | L79: =J79/G79*100 -> 41.666667 | M79: =20%*B79 -> 2028.6
A80: V6V2 | B80: =2349 -> 2349 | C80: =K80+H80 -> 1339.61 | D80: =B80-C80 -> 1009.39 | E80: =D80/B80*100 -> 42.971052 | F80: =D80/I80 -> 1009.39 | G80: 1 | H80: =(320+350)*I80 -> 670 | I80: 1 | J80: 0 | K80: =669.61 -> 669.61 | L80: =J80/G80*100 -> 0 | M80: =20%*B80 -> 469.8
A81: V4V2 | B81: =2249 -> 2249 | C81: =K81+H81 -> 1246.59 | D81: =B81-C81 -> 1002.41 | E81: =D81/B81*100 -> 44.571365 | F81: =D81/I81 -> 1002.41 | G81: 1 | H81: =(270+350)*I81 -> 620 | I81: 1 | J81: 0 | K81: =626.59 -> 626.59 | L81: =J81/G81*100 -> 0 | M81: =20%*B81 -> 449.8
B82: =SUM(B69:B81) -> 201313 | C82: =SUM(C69:C81) -> 143242.12 | D82: =SUM(D69:D81) -> 58070.88 | G82: =SUM(G69:G81) -> 258 | H82: =SUM(H69:H81) -> 69270 | I82: =SUM(I69:I81) -> 168 | J82: =SUM(J69:J81) -> 92 | K82: =SUM(K69:K81) -> 73972.12 | M82: =SUM(M69:M81) -> 29192
A85: Total Revenue | B85: =B82 -> 201313
A86: COGS | B86: =H82 -> 69270 | D86: Blended
A87: Flipkart Ex | B87: =K82-B88 -> 44780.12 | D87: COGS | E87: =B86/I82 -> 412.32143
A88: Marketing | B88: =M82 -> 29192 | D88: CAC | E88: =B88/I82 -> 173.7619
A89: Net P&L | B89: =B85-SUM(B86:B88) -> 58070.88 | D89: Commisions | E89: =B87/I82 -> 266.54833
A90: P&L % | B90: =B89/B85*100 -> 28.846066 | D90: AOV | E90: =B85/I82 -> 1198.2917
A95: April | B95: Blinkit
B97: Total revenue | C97: Total expense | D97: Total P/L | E97: Profit % | F97: P/pcs | G97: Product exp | H97: Total orders | I97: Blinkit exp | J97: Ads | K97: Logistics
A98: V1 | B98: =689*H98 -> 97149 | C98: =J98+G98+I98+K98 -> 71750.1 | D98: =B98-C98 -> 25398.9 | E98: =D98/B98*100 -> 26.144273 | F98: =D98/H98 -> 180.13404 | G98: =270*H98 -> 38070 | H98: 141 | I98: 0 | J98: =L98%*M98 -> 30860.1 | K98: =20*H98 -> 2820 | L98: 85 | M98: 36306
A99: V4 | B99: =359*H99 -> 31951 | C99: =J99+G99+I99+K99 -> 26805.9 | D99: =B99-C99 -> 5145.1 | E99: =D99/B99*100 -> 16.103095 | F99: =D99/H99 -> 57.810112 | G99: =220*H99 -> 19580 | H99: 89 | I99: 0 | J99: =L99%*M98 -> 5445.9 | K99: =20*H99 -> 1780 | L99: =100-L98 -> 15
A100: V2 | B100: =781*H100 -> 57013 | C100: =J100+G100+I100+K100 -> 27010 | D100: =B100-C100 -> 30003 | E100: =D100/B100*100 -> 52.62484 | F100: =D100/H100 -> 411 | G100: =350*H100 -> 25550 | H100: 73 | I100: 0 | J100: =L100%*M100 -> 0 | K100: =20*H100 -> 1460
A101: V6 | B101: =843*H101 -> 55638 | C101: =J101+G101+I101+K101 -> 24420 | D101: =B101-C101 -> 31218 | E101: =D101/B101*100 -> 56.109134 | F101: =D101/H101 -> 473 | G101: =350*H101 -> 23100 | H101: 66 | I101: 0 | J101: =L101%*M101 -> 0 | K101: =20*H101 -> 1320
B102: =SUM(B98:B101) -> 241751 | C102: =SUM(C98:C101) -> 149986 | D102: =SUM(D98:D101) -> 91765 | E102: =SUM(E98:E101) -> 150.98134 | F102: =SUM(F98:F101) -> 1121.9442 | G102: =SUM(G98:G101) -> 106300 | H102: =SUM(H98:H101) -> 369 | I102: =SUM(I98:I101) -> 0 | ... K102: =SUM(K98:K101) -> 7380
A105: Total Revenue | B105: =B102 -> 241751 | D105: Blended
A106: COGS | B106: =G102 -> 106300 | D106: COGS | E106: =B106/H102 -> 288.07588
A107: Logitics | B107: =K102 -> 7380 | D107: CAC | E107: =B108/H102 -> 98.390244
A108: Ad Spent | B108: =I102+J102 -> 36306 | D108: Logistics | E108: =K102/H102 -> 20
A109: Net P&L | B109: =B105-SUM(B106:B108) -> 91765 | D109: AOV | E109: =B105/H102 -> 655.15176
A110: P&L % | B110: =B109/B105*100 -> 37.958478
A116: April | B116: Instamart
B118: Total revenue | C118: Total expense | D118: Total P/L | E118: Profit % | F118: P/pcs | G118: Product exp | H118: Total orders | I118: Exp | J118: Ads | K118: Logistics
A119: V1 | B119: =727*H119 -> 73427 | C119: =J119+G119+I119+K119 -> 29290 | D119: =B119-C119 -> 44137 | E119: =D119/B119*100 -> 60.110041 | F119: =D119/H119 -> 437 | G119: =270*H119 -> 27270 | H119: 101 | I119: 0 | J119: 0 | K119: =20*H119 -> 2020
A120: V4 | B120: =385*H120 -> 11550 | C120: =J120+G120+I120+K120 -> 7200 | D120: =B120-C120 -> 4350 | E120: =D120/B120*100 -> 37.662338 | F120: =D120/H120 -> 145 | G120: =220*H120 -> 6600 | H120: 30 | I120: 0 | J120: 0 | K120: =20*H120 -> 600
A121: V2 | B121: =801*H121 -> 53667 | C121: =J121+G121+I121+K121 -> 24790 | D121: =B121-C121 -> 28877 | E121: =D121/B121*100 -> 53.80774 | F121: =D121/H121 -> 431 | G121: =350*H121 -> 23450 | H121: 67 | I121: 0 | J121: 0 | K121: =20*H121 -> 1340
B122: =SUM(B119:B121) -> 138644 | C122: =SUM(C119:C121) -> 61280 | D122: =B122-C122 -> 77364 | G122: =SUM(G119:G121) -> 57320 | H122: =SUM(H119:H121) -> 198 | K122: =SUM(K119:K121) -> 3960
A124: Total Revenue | B124: =B122 -> 138644 | D124: Blended
A125: COGS | B125: =G122 -> 57320 | D125: COGS | E125: =B125/H122 -> 289.49495
A126: Logitics | B126: =K122 -> 3960 | D126: CAC | E126: =B127 -> 0
A127: Ad Spent | B127: =I121+J121 -> 0 | D127: Logistics | E127: =B126/H122 -> 20
A128: Net P&L | B128: =B124-SUM(B125:B127) -> 77364 | D128: AOV | E128: =B124/H122 -> 700.22222
...

Sheet May 25
A1: May | B1: Shopify
A3: Products | B3: Total revenue | C3: Total expense | D3: Total P/L | E3: Profit % | F3: P/pcs | G3: Ad spent | H3: Total orders | I3: Shipped | J3: Product expense | K3: Delivered | L3: Shipping charges | M3: RTO | N3: In-transit | O3: RTO% | P3: Shipped% | Q3: Delivered % | R3: CPD | S3: Cancellation %
A4: V1 | B4: 549323 | C4: =G4+J4+L4 -> 189912 | D4: =B4-C4 -> 359411 | E4: =D4/B4*100 -> 65.42799 | F4: =D4/K4 -> 660.68199 | H4: 594 | I4: 586 | J4: =250*K4 -> 136000 | K4: 544 | L4: =I4*92 -> 53912 | M4: =I4-K4-N4 -> 42 | O4: =M4/I4*100 -> 7.1672355 | P4: =I4/H4*100 -> 98.653199 | Q4: =K4/I4*100 -> 92.832765 | R4: =G4/K4 -> 0 | S4: =100-P4 -> 1.3468013
A5: V1- P of 2 | B5: 11752 | C5: =G5+J5+L5 -> 3552 | D5: =B5-C5 -> 8200 | E5: =D5/B5*100 -> 69.775357 | F5: =D5/K5 -> 1366.6667 | H5: 6 | I5: 6 | J5: =500*K5 -> 3000 | K5: 6 | L5: =I5*92 -> 552 | M5: =I5-K5-N5 -> 0 | O5: =M5/I5*100 -> 0 | P5: =I5/H5*100 -> 100 | Q5: =K5/I5*100 -> 100 | R5: =G5/K5 -> 0 | S5: =100-P5 -> 0
A6: V2 | B6: 460600 | C6: =G6+J6+L6 -> 173096 | D6: =B6-C6 -> 287504 | E6: =D6/B6*100 -> 62.419453 | F6: =D6/K6 -> 744.82902 | H6: 419 | I6: 413 | J6: =350*K6 -> 135100 | K6: 386 | L6: =I6*92 -> 37996 | M6: =I6-K6-N6 -> 27 | O6: =M6/I6*100 -> 6.5375303 | P6: =I6/H6*100 -> 98.568019 | Q6: =K6/I6*100 -> 93.46247 | R6: =G6/K6 -> 0 | S6: =100-P6 -> 1.4319809
A7: V2- P of 2 | B7: 8758 | C7: =G7+J7+L7 -> 3168 | D7: =B7-C7 -> 5590 | E7: =D7/B7*100 -> 63.827358 | F7: =D7/K7 -> 1397.5 | H7: 5 | I7: 4 | J7: =700*K7 -> 2800 | K7: 4 | L7: =I7*92 -> 368 | M7: =I7-K7-N7 -> 0 | O7: =M7/I7*100 -> 0 | P7: =I7/H7*100 -> 80 | Q7: =K7/I7*100 -> 100 | R7: =G7/K7 -> 0 | S7: =100-P7 -> 20
A8: V3 | B8: 33818 | C8: =G8+J8+L8 -> 16632 | D8: =B8-C8 -> 17186 | E8: =D8/B8*100 -> 50.81909 | F8: =D8/K8 -> 818.38095 | H8: 22 | I8: 21 | J8: =700*K8 -> 14700 | K8: 21 | L8: =I8*92 -> 1932 | M8: =I8-K8-N8 -> 0 | O8: =M8/I8*100 -> 0 | P8: =I8/H8*100 -> 95.454545 | Q8: =K8/I8*100 -> 100 | R8: =G8/K8 -> 0 | S8: =100-P8 -> 4.5454545
A9: V4 | B9: 170818 | C9: =G9+J9+L9 -> 124804 | D9: =B9-C9 -> 46014 | E9: =D9/B9*100 -> 26.937442 | F9: =D9/K9 -> 108.78014 | H9: 439 | I9: 437 | J9: =200*K9 -> 84600 | K9: 423 | L9: =I9*92 -> 40204 | M9: =I9-K9-N9 -> 14 | O9: =M9/I9*100 -> 3.2036613 | P9: =I9/H9*100 -> 99.544419 | Q9: =K9/I9*100 -> 96.796339 | R9: =G9/K9 -> 0 | S9: =100-P9 -> 0.45558087
A10: V4- P of 2 | B10: 41284 | C10: =G10+J10+L10 -> 25092 | D10: =B10-C10 -> 16192 | E10: =D10/B10*100 -> 39.221006 | F10: =D10/K10 -> 317.4902 | H10: 52 | I10: 51 | J10: =400*K10 -> 20400 | K10: 51 | L10: =I10*92 -> 4692 | M10: =I10-K10-N10 -> 0 | O10: =M10/I10*100 -> 0 | P10: =I10/H10*100 -> 98.076923 | Q10: =K10/I10*100 -> 100 | R10: =G10/K10 -> 0 | S10: =100-P10 -> 1.9230769
A11: V5 | B11: 64141 | C11: =G11+J11+L11 -> 22520 | D11: =B11-C11 -> 41621 | E11: =D11/B11*100 -> 64.889852 | F11: =D11/K11 -> 586.21127 | H11: 91 | I11: 75 | J11: =220*K11 -> 15620 | K11: 71 | L11: =I11*92 -> 6900 | M11: =I11-K11-N11 -> 4 | O11: =M11/I11*100 -> 5.3333333 | P11: =I11/H11*100 -> 82.417582 | Q11: =K11/I11*100 -> 94.666667 | R11: =G11/K11 -> 0 | S11: =100-P11 -> 17.582418
A12: V6 | B12: 852560 | C12: =G12+J12+L12 -> 327316 | D12: =B12-C12 -> 525244 | E12: =D12/B12*100 -> 61.607863 | F12: =D12/K12 -> 717.54645 | H12: 802 | I12: 773 | J12: =350*K12 -> 256200 | K12: 732 | L12: =I12*92 -> 71116 | M12: =I12-K12-N12 -> 41 | O12: =M12/I12*100 -> 5.3040103 | P12: =I12/H12*100 -> 96.38404 | Q12: =K12/I12*100 -> 94.69599 | R12: =G12/K12 -> 0 | S12: =100-P12 -> 3.6159601
A13: V6- P of 2 | B13: 22186 | C13: =G13+J13+L13 -> 7920 | D13: =B13-C13 -> 14266 | E13: =D13/B13*100 -> 64.301812 | F13: =D13/K13 -> 1426.6 | H13: 10 | I13: 10 | J13: =700*K13 -> 7000 | K13: 10 | L13: =I13*92 -> 920 | M13: =I13-K13-N13 -> 0 | O13: =M13/I13*100 -> 0 | P13: =I13/H13*100 -> 100 | Q13: =K13/I13*100 -> 100 | R13: =G13/K13 -> 0 | S13: =100-P13 -> 0
A14: V7 | B14: 111760 | C14: =G14+J14+L14 -> 64304 | D14: =B14-C14 -> 47456 | E14: =D14/B14*100 -> 42.462419 | F14: =D14/K14 -> 439.40741 | H14: 113 | I14: 112 | J14: =500*K14 -> 54000 | K14: 108 | L14: =I14*92 -> 10304 | M14: =I14-K14-N14 -> 4 | O14: =M14/I14*100 -> 3.5714286 | P14: =I14/H14*100 -> 99.115044 | Q14: =K14/I14*100 -> 96.428571 | R14: =G14/K14 -> 0 | S14: =100-P14 -> 0.88495575
A15: V8 | B15: 25724 | C15: =G15+J15+L15 -> 11880 | D15: =B15-C15 -> 13844 | E15: =D15/B15*100 -> 53.817447 | F15: =D15/K15 -> 922.93333 | H15: 16 | I15: 15 | J15: =700*K15 -> 10500 | K15: 15 | L15: =I15*92 -> 1380 | M15: =I15-K15-N15 -> 0 | O15: =M15/I15*100 -> 0 | P15: =I15/H15*100 -> 93.75 | Q15: =K15/I15*100 -> 100 | R15: =G15/K15 -> 0 | S15: =100-P15 -> 6.25
A16: V9 | B16: 1250257 | C16: =G16+J16+L16 -> 665312 | D16: =B16-C16 -> 584945 | E16: =D16/B16*100 -> 46.785981 | F16: =D16/K16 -> 880.94127 | H16: 752 | I16: 736 | J16: =900*K16 -> 597600 | K16: 664 | L16: =I16*92 -> 67712 | M16: =I16-K16-N16 -> 72 | O16: =M16/I16*100 -> 9.7826087 | P16: =I16/H16*100 -> 97.87234 | Q16: =K16/I16*100 -> 90.217391 | R16: =G16/K16 -> 0 | S16: =100-P16 -> 2.1276596
A17: V9 P of 2 | B17: =46937+4211 -> 51148 | C17: =G17+J17+L17 -> 28380 | D17: =B17-C17 -> 22768 | E17: =D17/B17*100 -> 44.513959 | F17: =D17/K17 -> 1517.8667 | H17: 15 | I17: 15 | J17: =1800*K17 -> 27000 | K17: 15 | L17: =I17*92 -> 1380 | M17: =I17-K17-N17 -> 0 | O17: =M17/I17*100 -> 0 | P17: =I17/H17*100 -> 100 | Q17: =K17/I17*100 -> 100 | R17: =G17/K17 -> 0 | S17: =100-P17 -> 0
A18: V6-V2 Combo | B18: 134699 | C18: =G18+J18+L18 -> 50688 | D18: =B18-C18 -> 84011 | E18: =D18/B18*100 -> 62.369431 | F18: =D18/K18 -> 1312.6719 | H18: 65 | I18: 64 | J18: =K18*700 -> 44800 | K18: 64 | L18: =I18*92 -> 5888 | M18: =I18-K18-N18 -> 0 | O18: =M18/I18*100 -> 0 | P18: =I18/H18*100 -> 98.461538 | Q18: =K18/I18*100 -> 100 | R18: =G18/K18 -> 0 | S18: =100-P18 -> 1.5384615
A19: V6-V4 Combo | B19: 27054 | C19: =G19+J19+L19 -> 9738 | D19: =B19-C19 -> 17316 | E19: =D19/B19*100 -> 64.005323 | F19: =D19/K19 -> 1332 | H19: 15 | I19: 14 | J19: =K19*650 -> 8450 | K19: 13 | L19: =I19*92 -> 1288 | M19: =I19-K19-N19 -> 1 | O19: =M19/I19*100 -> 7.1428571 | P19: =I19/H19*100 -> 93.333333 | Q19: =K19/I19*100 -> 92.857143 | R19: =G19/K19 -> 0 | S19: =100-P19 -> 6.6666667
A20: Busy Book | B20: 162000 | C20: =G20+J20+L20 -> 102680 | D20: =B20-C20 -> 59320 | E20: =D20/B20*100 -> 36.617284 | F20: =D20/K20 -> 227.27969 | H20: 265 | I20: 265 | J20: =K20*300 -> 78300 | K20: 261 | L20: =I20*92 -> 24380 | M20: =I20-K20-N20 -> 4 | O20: =M20/I20*100 -> 1.509434 | P20: =I20/H20*100 -> 100 | Q20: =K20/I20*100 -> 98.490566 | R20: =G20/K20 -> 0 | S20: =100-P20 -> 0
A21: Total | B21: =SUM(B4:B20) -> 3977882 | D21: =SUM(D4:D20) -> 2150888 | G21: 2036423 | H21: =SUM(H4:H20) -> 3681 | I21: =SUM(I4:I20) -> 3597 | J21: =SUM(J4:J20) -> 1496070 | K21: =SUM(K4:K20) -> 3388 | L21: =SUM(L4:L20) -> 330924 | M21: =SUM(M4:M20) -> 209 | N21: =SUM(N4:N20) -> 0 | R21: =SUM(R4:R20) -> 0
D24: Blended | I24: Unit Economics | J24: 1 | K24: 1174
A25: Total Revenue | B25: =B21 -> 3977882 | D25: COGS | E25: =B27/K21 -> 441.5791 | I25: COGS | J25: 0.37 | K25: =K24*37% -> 434.38
A26: Total Units Sold | B26: =K21 -> 3388 | G26: =B27/B25*100 -> 37.609713 | I26: Logitics & Packing | J26: 0.09 | K26: =K24*J26 -> 105.66
A27: COGS | B27: =J21 -> 1496070 | D27: CAC | E27: =B29/K21 -> 601.06936 | G27: =B28/B25*100 -> 8.3191005 | I27: Marketing | J27: 0.51 | K27: =K24*J27 -> 598.74
A28: Logistics | B28: =L21 -> 330924 | D28: Logistics | E28: 92 | G28: =B29/B25*100 -> 51.19365 | I28: Profit | J28: 0.03 | K28: 38
A29: Marketing | B29: =G21 -> 2036423 | D29: AOV | E29: =B25/K21 -> 1174.1092
A30: P&L | B30: =B25-(B27+B28+B29) -> 114465
A31: P&L % | B31: 0.03
A34: May | B34: Amazon
B36: Total revenue | C36: Total expense | D36: Total P/L | E36: Profit % | F36: P/pcs | G36: Total orders | H36: Product expense | I36: Delivered | J36: Return | K36: Amazon expense | L36: RTO% | M36: Only Ad spend | N36: Return GMV
A37: V1 | B37: =737727+35043.52+16470.88 -> 789241.4 | C37: =K37+H37 -> 488123.7 | D37: =B37-C37 -> 301117.7 | E37: =D37/B37*100 -> 38.152801 | F37: =D37/I37 -> 371.29186 | G37: =823+29+8 -> 860 | H37: =250*I37 -> 202750 | I37: =776+27+8 -> 811 | J37: =G37-I37 -> 49 | K37: =16164.28+266484.18 +2725.24 -> 285373.7 | L37: =J37/G37*100 -> 5.6976744 | M37: =152094.75 +28728.79+ 1254.68 -> 182078.22 | N37: =J37*999 -> 48951
A38: V2 | B38: =66559.67+475798+2898 -> 545255.67 | C38: =K38+H38 -> 287411.48 | D38: =B38-C38 -> 257844.19 | E38: =D38/B38*100 -> 47.288677 | F38: =D38/I38 -> 538.29685 | G38: =467+52 -> 519 | H38: =350*I38 -> 167650 | I38: =430+47+2 -> 479 | J38: =G38-I38 -> 40 | K38: =23980.81+95224.67 +556 -> 119761.48 | L38: =J38/G38*100 -> 7.7071291 | M38: =11950.9 + 125741.64 + 13734 -> 151426.54 | N38: =J38*1119 -> 44760
A39: V3 | B39: =5097 -> 5097 | C39: =K39+H39 -> 3514.17 | D39: =B39-C39 -> 1582.83 | E39: =D39/B39*100 -> 31.05415 | F39: =D39/I39 -> 527.61 | G39: 3 | H39: =900*I39 -> 2700 | I39: 3 | J39: =G39-I39 -> 0 | K39: =814.17 -> 814.17 | L39: =J39/G39*100 -> 0 | M39: 0 | N39: =J39*1799 -> 0
A40: V4 | B40: =418231+10374.16+4992.32+5202.65 -> 438800.13 | C40: =K40+H40 -> 408206.65 | D40: =B40-C40 -> 30593.48 | E40: =D40/B40*100 -> 6.9720763 | F40: =D40/I40 -> 31.313695 | G40: =997+18+4+5 -> 1024 | H40: =220*I40 -> 214940 | I40: =938+17+12+10 -> 977 | J40: =G40-I40+5+8 -> 60 | K40: =190465.26+2801.39 -> 193266.65 | L40: =J40/G40*100 -> 5.859375 | M40: =115847.24 + 3622.79 -> 119470.03 | N40: =J40*499 -> 29940
A41: V5 | B41: 0 | C41: =K41+H41 -> 0 | D41: =B41-C41 -> 0 | E41: =D41/B41*100 -> #DIV/0! | F41: =D41/I41 -> #DIV/0! | G41: 0 | H41: =250*I41 -> 0 | I41: 0 | J41: =G41-I41 -> 0 | K41: 0 | L41: =J41/G41*100 -> #DIV/0! | M41: 0 | N41: =J41*1049 -> 0
A42: V6 | B42: =123107+66353.24 -> 189460.24 | C42: =K42+H42 -> 117888.72 | D42: =B42-C42 -> 71571.52 | E42: =D42/B42*100 -> 37.776538 | F42: =D42/I42 -> 455.86955 | G42: =111+60 -> 171 | H42: =320*I42 -> 50240 | I42: =102+55 -> 157 | J42: =G42-I42 -> 14 | K42: =22505.49 +45143.23 -> 67648.72 | L42: =J42/G42*100 -> 8.1871345 | M42: =32897.63 + 475.39 -> 33373.02 | N42: =J42*1249 -> 17486
A43: V7 | B43: =31719.47+36030 -> 67749.47 | C43: =K43+H43 -> 65516.4 | D43: =B43-C43 -> 2233.07 | E43: =D43/B43*100 -> 3.2960701 | F43: =D43/I43 -> 44.6614 | G43: =33+20 -> 53 | H43: =500*I43 -> 25000 | I43: 50 | J43: =G43-I43 -> 3 | K43: =14422.44+26093.96 -> 40516.4 | L43: =J43/G43*100 -> 5.6603774 | M43: =26375.73 + 437.34 -> 26813.07 | N43: =J43*1349 -> 4047
A44: V8 | B44: 0 | C44: =K44+H44 -> 0 | D44: =B44-C44 -> 0 | E44: =D44/B44*100 -> #DIV/0! | F44: =D44/I44 -> #DIV/0! | G44: 0 | H44: =800*I44 -> 0 | I44: 0 | J44: =G44-I44 -> 0 | K44: 0 | L44: =J44/G44*100 -> #DIV/0! | M44: 0 | N44: =J44*1899 -> 0
A45: V9 | B45: =132466+128639.12 -> 261105.12 | C45: =K45+H45 -> 196591.55 | D45: =B45-C45 -> 64513.57 | E45: =D45/B45*100 -> 24.707892 | F45: =D45/I45 -> 504.01227 | G45: =81+75 -> 156 | H45: =1000*I45 -> 128000 | I45: =71+57 -> 128 | J45: =G45-I45 -> 28 | K45: =43949.27+24642.28 -> 68591.55 | L45: =J45/G45*100 -> 17.948718 | M45: =18296.03 + 62.04 -> 18358.07 | N45: =J45*1999 -> 55972
A46: BB | B46: =28535 -> 28535 | C46: =K46+H46 -> 23126.43 | D46: =B46-C46 -> 5408.57 | E46: =D46/B46*100 -> 18.954162 | F46: =D46/I46 -> 104.01096 | G46: 55 | H46: =200*I46 -> 10400 | I46: 52 | J46: =G46-I46 -> 3 | K46: =12726.43 -> 12726.43 | L46: =J46/G46*100 -> 5.4545455 | M46: =10121.88 -> 10121.88 | N46: =J46*599 -> 1797
A47: V1V4 | B47: =1449 -> 1449 | C47: =K47+H47 -> 720.64 | D47: =B47-C47 -> 728.36 | E47: =D47/B47*100 -> 50.266391 | F47: =D47/I47 -> 728.36 | G47: 1 | H47: =(270+220)*I47 -> 490 | I47: 1 | J47: =G47-I47 -> 0 | K47: =230.64 -> 230.64 | L47: =J47/G47*100 -> 0 | M47: 0
A48: V1V2 | B48: =2199 -> 2199 | C48: =K48+H48 -> 620 | D48: =B48-C48 -> 1579 | E48: =D48/B48*100 -> 71.805366 | F48: =D48/I48 -> 1579 | G48: 1 | H48: =(270+350)*I48 -> 620 | I48: 1 | J48: =G48-I48 -> 0 | K48: 0 | L48: =J48/G48*100 -> 0 | M48: 0 | N48: =J48*2199 -> 0
A49: V1V6 | B49: =13194 -> 13194 | C49: =K49+H49 -> 5901.23 | D49: =B49-C49 -> 7292.77 | E49: =D49/B49*100 -> 55.273382 | F49: =D49/I49 -> 1215.4617 | G49: 7 | H49: =(270+320)*I49 -> 3540 | I49: 6 | J49: =G49-I49 -> 1 | K49: =2361.23 -> 2361.23 | L49: =J49/G49*100 -> 14.285714 | M49: 0 | N49: =J49*999 -> 999
A50: V2V4 | B50: =20189 -> 20189 | C50: =K50+H50 -> 19867.18 | D50: =B50-C50 -> 321.82 | E50: =D50/B50*100 -> 1.5940364 | F50: =D50/I50 -> 29.256364 | G50: 11 | H50: =(350+220)*I50 -> 6270 | I50: 11 | J50: =G50-I50 -> 0 | K50: =13597.18 -> 13597.18 | L50: =J50/G50*100 -> 0 | M50: =10405.32 + 203.25 -> 10608.57 | N50: =J50*1499 -> 0
A51: V2V6 | B51: 0 | C51: =K51+H51 -> 0 | D51: =B51-C51 -> 0 | E51: =D51/B51*100 -> #DIV/0! | F51: =D51/I51 -> #DIV/0! | G51: 0 | H51: =(350+320)*I51 -> 0 | I51: 0 | J51: =G51-I51 -> 0 | K51: 0 | L51: =J51/G51*100 -> #DIV/0! | M51: 0 | N51: =J51*999 -> 0
A52: NBB | B52: =20784+1998 -> 22782 | C52: =K52+H52 -> 10241.21 | D52: =B52-C52 -> 12540.79 | E52: =D52/B52*100 -> 55.046923 | F52: =D52/I52 -> 696.71056 | G52: 19 | H52: =(330)*I52 -> 5940 | I52: 18 | J52: =G52-I52 -> 1 | K52: =4036.89+264.32 -> 4301.21 | L52: =J52/G52*100 -> 5.2631579 | M52: 0 | N52: =J52*999 -> 999
A53: Total | B53: =SUM(B37:B51) -> 2362275 | C53: =SUM(C37:C51) -> 1617488.1 | D53: =B53-C53 -> 744786.88 | G53: =SUM(G35:G51) -> 2861 | H53: =SUM(H37:H51) -> 812600 | I53: =SUM(I35:I51) -> 2676 | K53: =SUM(K37:K51) -> 804888.15 | M53: =SUM(M35:M51) -> 552249.4
A56: Total Revenue | B56: =B53 -> 2362275
A57: COGS | B57: =H53 -> 812600 | D57: Blended
A58: Amazon cumi | B58: 133800 | D58: COGS | E58: =B57/I53 -> 303.66218
A59: Logi | B59: 118839
A60: Marketing | B60: =M53 -> 552249.4 | D60: CAC | E60: =B60/I53 -> 206.37123
A61: Net P&L | B61: =B56-SUM(B57:B60) -> 744786.63 | D61: Commisions | E61: =B58/I53 -> 50
A62: P&L % | B62: =B61/B56*100 -> 31.528362 | D62: AOV | E62: =B56/I53 -> 882.76346
A69: May | B69: Flipkart
B71: Total revenue | C71: Total expense | D71: Total P/L | E71: Profit % | F71: P/pcs | G71: Total orders | H71: Product expense | I71: Delivered | J71: Return | K71: Flipkart expenses | L71: RTO% | M71: Only Ad spend
A72: V1 | B72: =32190 -> 32190 | C72: =K72+H72 -> 19767.18 | D72: =B72-C72 -> 12422.82 | E72: =D72/B72*100 -> 38.592171 | F72: =D72/I72 -> 414.094 | G72: 47 | H72: =270*I72 -> 8100 | I72: 30 | J72: =G72-I72 -> 17 | K72: =11667.18 -> 11667.18 | L72: =J72/G72*100 -> 36.170213 | M72: =20%*B72 -> 6438
A73: V2 | B73: =38220 -> 38220 | C73: =K73+H73 -> 23073.44 | D73: =B73-C73 -> 15146.56 | E73: =D73/B73*100 -> 39.629932 | F73: =D73/I73 -> 504.88533 | G73: 36 | H73: =350*I73 -> 10500 | I73: 30 | J73: =G73-I73 -> 6 | K73: =12573.44 -> 12573.44 | L73: =J73/G73*100 -> 16.666667 | M73: =20%*B73 -> 7644
A74: V3 | B74: 0 | C74: =K74+H74 -> 0 | D74: =B74-C74 -> 0 | E74: =D74/B74*100 -> #DIV/0! | F74: =D74/I74 -> #DIV/0! | G74: 0 | H74: =980*I74 -> 0 | I74: 0 | J74: =G74-I74 -> 0 | K74: 0 | L74: =J74/G74*100 -> #DIV/0! | M74: =20%*B74 -> 0
A75: V4 | B75: =41200 -> 41200 | C75: =K75+H75 -> 35973.35 | D75: =B75-C75 -> 5226.65 | E75: =D75/B75*100 -> 12.686044 | F75: =D75/I75 -> 65.333125 | G75: 113 | H75: =220*I75 -> 17600 | I75: 80 | J75: =G75-I75 -> 33 | K75: =18373.35 -> 18373.35 | L75: =J75/G75*100 -> 29.20354 | M75: =20%*B75 -> 8240
A76: V5 | B76: =3447 -> 3447 | C76: =K76+H76 -> 2813.49 | D76: =B76-C76 -> 633.51 | E76: =D76/B76*100 -> 18.37859 | F76: =D76/I76 -> 211.17 | G76: 10 | H76: =270*I76 -> 810 | I76: 3 | J76: =G76-I76 -> 7 | K76: =2003.49 -> 2003.49 | L76: =J76/G76*100 -> 70 | M76: =20%*B76 -> 689.4
A77: V6 | B77: =22992 -> 22992 | C77: =K77+H77 -> 13960.5 | D77: =B77-C77 -> 9031.5 | E77: =D77/B77*100 -> 39.281054 | F77: =D77/I77 -> 501.75 | G77: 26 | H77: =320*I77 -> 5760 | I77: 18 | J77: =G77-I77 -> 8 | K77: =8200.5 -> 8200.5 | L77: =J77/G77*100 -> 30.769231 | M77: =20%*B77 -> 4598.4
A78: V7 | B78: =8394 -> 8394 | C78: =K78+H78 -> 5406.8 | D78: =B78-C78 -> 2987.2 | E78: =D78/B78*100 -> 35.587324 | F78: =D78/I78 -> 497.86667 | G78: 7 | H78: =470*I78 -> 2820 | I78: 6 | J78: =G78-I78 -> 1 | K78: =2586.8 -> 2586.8 | L78: =J78/G78*100 -> 14.285714 | M78: =20%*B78 -> 1678.8
A79: Wooden cal | B79: =713+1847 -> 2560 | C79: =K79+H79 -> 1165.88 | D79: =B79-C79 -> 1394.12 | E79: =D79/B79*100 -> 54.457813 | F79: =D79/I79 -> 697.06 | G79: 2 | H79: =200*I79 -> 400 | I79: 2 | J79: =G79-I79 -> 0 | K79: =259.73+506.15 -> 765.88 | L79: =J79/G79*100 -> 0 | M79: =20%*B79 -> 512
A80: V9 | B80: =20550 -> 20550 | C80: =K80+H80 -> 16601.63 | D80: =B80-C80 -> 3948.37 | E80: =D80/B80*100 -> 19.213479 | F80: =D80/I80 -> 394.837 | G80: 12 | H80: =1000*I80 -> 10000 | I80: 10 | J80: =G80-I80 -> 2 | K80: =6601.63 -> 6601.63 | L80: =J80/G80*100 -> 16.666667 | M80: 0
A81: V4V2 | B81: =8245 -> 8245 | C81: =K81+H81 -> 6110.32 | D81: =B81-C81 -> 2134.68 | E81: =D81/B81*100 -> 25.8906 | F81: =D81/I81 -> 426.936 | G81: 9 | H81: =(220+350)*I81 -> 2850 | I81: 5 | J81: =G81-I81 -> 4 | K81: =3260.32 -> 3260.32 | L81: =J81/G81*100 -> 44.444444 | M81: =20%*B81 -> 1649
A82: V1V4 | B82: =10143 -> 10143 | C82: =K82+H82 -> 6545.5 | D82: =B82-C82 -> 3597.5 | E82: =D82/B82*100 -> 35.46781 | F82: =D82/I82 -> 513.92857 | G82: 7 | H82: =(270+220)*I82 -> 3430 | I82: 7 | J82: =G82-I82 -> 0 | K82: =3115.5 -> 3115.5 | L82: =J82/G82*100 -> 0 | M82: =20%*B82 -> 2028.6
A83: V6V2 | B83: =2349 -> 2349 | C83: =K83+H83 -> 1305.95 | D83: =B83-C83 -> 1043.05 | E83: =D83/B83*100 -> 44.404002 | F83: =D83/I83 -> 1043.05 | G83: 4 | H83: =(320+350)*I83 -> 670 | I83: 1 | J83: =G83-I83 -> 3 | K83: =635.95 -> 635.95 | L83: =J83/G83*100 -> 75 | M83: =20%*B83 -> 469.8
A84: V4V2 | B84: =8245 -> 8245 | C84: =K84+H84 -> 6360.32 | D84: =B84-C84 -> 1884.68 | E84: =D84/B84*100 -> 22.85846 | F84: =D84/I84 -> 376.936 | G84: 9 | H84: =(270+350)*I84 -> 3100 | I84: 5 | J84: =G84-I84 -> 4 | K84: =3260.32 -> 3260.32 | L84: =J84/G84*100 -> 44.444444 | M84: =20%*B84 -> 1649
B85: =SUM(B72:B84) -> 198535 | C85: =SUM(C72:C84) -> 139084.36 | D85: =SUM(D72:D84) -> 59450.64 | G85: =SUM(G72:G84) -> 282 | H85: =SUM(H72:H84) -> 66040 | I85: =SUM(I72:I84) -> 197 | J85: =SUM(J72:J84) -> 85 | K85: =SUM(K72:K84) -> 73044.36 | M85: =SUM(M72:M84) -> 35597
A88: Total Revenue | B88: =B85 -> 198535
A89: COGS | B89: =H85 -> 66040
A90: Flipkart Ex | B90: =K85-B91 -> 37447.36 | D90: COGS | E90: =B89/I85 -> 335.22843
A91: Marketing | B91: =M85 -> 35597 | D91: CAC | E91: =B91/I85 -> 180.69543
A92: Net P&L | B92: =B88-SUM(B89:B91) -> 59450.64 | D92: Commisions | E92: =B90/I85 -> 190.08812
A93: P&L % | B93: =B92/B88*100 -> 29.944665 | D93: AOV | E93: =B88/I85 -> 1007.7919
A98: May | B98: Blinkit
B100: Total revenue | C100: Total expense | D100: Total P/L | E100: Profit % | F100: P/pcs | G100: Product exp | H100: Total orders | I100: Blinkit exp | J100: Ads | K100: Logistics
A101: V1 | B101: =689*H101 -> 81991 | C101: =J101+G101+I101+K101 -> 65409.05 | D101: =B101-C101 -> 16581.95 | E101: =D101/B101*100 -> 20.22411 | F101: =D101/H101 -> 139.34412 | G101: =270*H101 -> 32130 | H101: 119 | I101: =2277 -> 2277 | J101: =L101%*M101 -> 28622.05 | K101: =20*H101 -> 2380 | L101: 85 | M101: =33673 -> 33673
A102: V4 | B102: =359*H102 -> 33028 | C102: =J102+G102+I102+K102 -> 27970.95 | D102: =B102-C102 -> 5057.05 | E102: =D102/B102*100 -> 15.311402 | F102: =D102/H102 -> 54.967935 | G102: =220*H102 -> 20240 | H102: 92 | I102: =840 -> 840 | J102: =L102%*M101 -> 5050.95 | K102: =20*H102 -> 1840 | L102: =100-L101 -> 15
A103: V2 | B103: =781*H103 -> 39831 | C103: =J103+G103+I103+K103 -> 19975 | D103: =B103-C103 -> 19856 | E103: =D103/B103*100 -> 49.850619 | F103: =D103/H103 -> 389.33333 | G103: =350*H103 -> 17850 | H103: 51 | I103: =1105 -> 1105 | J103: =L103%*M103 -> 0 | K103: =20*H103 -> 1020
A104: V6 | B104: =843*H104 -> 53109 | C104: =J104+G104+I104+K104 -> 24390 | D104: =B104-C104 -> 28719 | E104: =D104/B104*100 -> 54.07558 | F104: =D104/H104 -> 455.85714 | G104: =350*H104 -> 22050 | H104: 63 | I104: 1080 | J104: =L104%*M104 -> 0 | K104: =20*H104 -> 1260
B105: =SUM(B101:B104) -> 207959 | C105: =SUM(C101:C104) -> 137745 | D105: =SUM(D101:D104) -> 70214 | E105: =SUM(E101:E104) -> 139.46171 | F105: =SUM(F101:F104) -> 1039.5025 | G105: =SUM(G101:G104) -> 92270 | H105: =SUM(H101:H104) -> 325 | I105: =SUM(I101:I104) -> 5302 | ... K105: =SUM(K101:K104) -> 6500
A108: Total Revenue | B108: =B105 -> 207959 | D108: Blended
A109: COGS | B109: =G105 -> 92270 | D109: COGS | E109: =B109/H105 -> 283.90769
A110: Logitics | B110: =K105 -> 6500 | D110: CAC | E110: =B111/H105 -> 119.92308
A111: Ad Spent | B111: =I105+J105 -> 38975 | D111: Logistics | E111: =K105/H105 -> 20
A112: Net P&L | B112: =B108-SUM(B109:B111) -> 70214 | D112: AOV | E112: =B108/H105 -> 639.87385
A113: P&L % | B113: =B112/B108*100 -> 33.763386
A119: May | B119: Instamart
B121: Total revenue | C121: Total expense | D121: Total P/L | E121: Profit % | F121: P/pcs | G121: Product exp | H121: Total orders | I121: Exp | J121: Ads | K121: Logistics
A122: V1 | B122: =727*H122 -> 16721 | C122: =J122+G122+I122+K122 -> 6670 | D122: =B122-C122 -> 10051 | E122: =D122/B122*100 -> 60.110041 | F122: =D122/H122 -> 437 | G122: =270*H122 -> 6210 | H122: 23 | I122: 0 | J122: 0 | K122: =20*H122 -> 460
A123: V4 | B123: =385*H123 -> 16940 | C123: =J123+G123+I123+K123 -> 10560 | D123: =B123-C123 -> 6380 | E123: =D123/B123*100 -> 37.662338 | F123: =D123/H123 -> 145 | G123: =220*H123 -> 9680 | H123: 44 | I123: 0 | J123: 0 | K123: =20*H123 -> 880
A124: V2 | B124: =801*H124 -> 46458 | C124: =J124+G124+I124+K124 -> 21460 | D124: =B124-C124 -> 24998 | E124: =D124/B124*100 -> 53.80774 | F124: =D124/H124 -> 431 | G124: =350*H124 -> 20300 | H124: 58 | I124: 0 | J124: 0 | K124: =20*H124 -> 1160
B125: =SUM(B122:B124) -> 80119 | C125: =SUM(C122:C124) -> 38690 | D125: =B125-C125 -> 41429 | G125: =SUM(G122:G124) -> 36190 | H125: =SUM(H122:H124) -> 125 | K125: =SUM(K122:K124) -> 2500
A127: Total Revenue | B127: =B125 -> 80119 | D127: Blended
A128: COGS | B128: =G125 -> 36190 | D128: COGS | E128: =B128/H125 -> 289.52
A129: Logitics | B129: =K125 -> 2500 | D129: CAC | E129: =B130 -> 0
A130: Ad Spent | B130: =I124+J124 -> 0 | D130: Logistics | E130: =B129/H125 -> 20
A131: Net P&L | B131: =B127-SUM(B128:B130) -> 41429 | D131: AOV | E131: =B127/H125 -> 640.952
...

Sheet June 25
A1: June | B1: Shopify
A3: Products | B3: Total Dilivered Revenue | C3: Total expense | D3: Total P/L | E3: Profit % | F3: P/pcs | G3: Ad spent | H3: Total orders | I3: Shipped | J3: Total COGS | K3: Delivered | L3: Shipping charges | M3: RTO | N3: In-transit | O3: RTO% | P3: Shipped% | Q3: Delivered % | R3: CPD | S3: Cancellation % | T3: COGS/Unit
A4: V1 | B4: 632837.04 | C4: =G4+J4+L4 -> 343480 | D4: =B4-C4 -> 289357.04 | E4: =D4/B4*100 -> 45.723784 | F4: =D4/K4 -> 263.29121 | H4: 1136 | I4: 1130 | J4: =K4*T4 -> 241780 | K4: 1099 | L4: =I4*90 -> 101700 | M4: =I4-K4-N4 -> 31 | O4: =M4/I4*100 -> 2.7433628 | P4: =I4/H4*100 -> 99.471831 | Q4: =K4/I4*100 -> 97.256637 | R4: =G4/K4 -> 0 | S4: =100-P4 -> 0.52816901 | T4: 220 | W4: Products
A5: V1- P of 2 | B5: 23546.69 | C5: =G5+J5+L5 -> 8480 | D5: =B5-C5 -> 15066.69 | E5: =D5/B5*100 -> 63.986446 | F5: =D5/K5 -> 941.66813 | H5: 16 | I5: 16 | J5: =K5*T5 -> 7040 | K5: 16 | L5: =I5*90 -> 1440 | M5: =I5-K5-N5 -> 0 | O5: =M5/I5*100 -> 0 | P5: =I5/H5*100 -> 100 | Q5: =K5/I5*100 -> 100 | R5: =G5/K5 -> 0 | S5: =100-P5 -> 0 | T5: 440 | W5: V1
A6: V2 | B6: 348400.03 | C6: =G6+J6+L6 -> 119966 | D6: =B6-C6 -> 228434.03 | E6: =D6/B6*100 -> 65.566593 | F6: =D6/K6 -> 763.99341 | H6: 328 | I6: 323 | J6: =K6*T6 -> 90896 | K6: 299 | L6: =I6*90 -> 29070 | M6: =I6-K6-N6 -> 24 | O6: =M6/I6*100 -> 7.4303406 | P6: =I6/H6*100 -> 98.47561 | Q6: =K6/I6*100 -> 92.569659 | R6: =G6/K6 -> 0 | S6: =100-P6 -> 1.5243902 | T6: 304 | W6: V2
A7: V2- P of 2 | B7: 8965.27 | C7: =G7+J7+L7 -> 2792 | D7: =B7-C7 -> 6173.27 | E7: =D7/B7*100 -> 68.857603 | F7: =D7/K7 -> 1543.3175 | H7: 5 | I7: 4 | J7: =K7*T7 -> 2432 | K7: 4 | L7: =I7*90 -> 360 | M7: =I7-K7-N7 -> 0 | O7: =M7/I7*100 -> 0 | P7: =I7/H7*100 -> 80 | Q7: =K7/I7*100 -> 100 | R7: =G7/K7 -> 0 | S7: =100-P7 -> 20 | T7: 608 | W7: V3
A8: V3 | B8: 540771.57 | C8: =G8+J8+L8 -> 297484 | D8: =B8-C8 -> 243287.57 | E8: =D8/B8*100 -> 44.988972 | F8: =D8/K8 -> 620.63156 | H8: 441 | I8: 422 | J8: =K8*T8 -> 259504 | K8: 392 | L8: =I8*90 -> 37980 | M8: =I8-K8-N8 -> 30 | O8: =M8/I8*100 -> 7.1090047 | P8: =I8/H8*100 -> 95.69161 | Q8: =K8/I8*100 -> 92.890995 | R8: =G8/K8 -> 0 | S8: =100-P8 -> 4.30839 | T8: 662 | W8: V4
A9: V4 | B9: 63290.51 | C9: =G9+J9+L9 -> 32504 | D9: =B9-C9 -> 30786.51 | E9: =D9/B9*100 -> 48.643169 | F9: =D9/K9 -> 265.40095 | H9: 126 | I9: 124 | J9: =K9*T9 -> 21344 | K9: 116 | L9: =I9*90 -> 11160 | M9: =I9-K9-N9 -> 8 | O9: =M9/I9*100 -> 6.4516129 | P9: =I9/H9*100 -> 98.412698 | Q9: =K9/I9*100 -> 93.548387 | R9: =G9/K9 -> 0 | S9: =100-P9 -> 1.5873016 | T9: 184 | W9: V5
A10: V4- P of 2 | B10: 29336.01 | C10: =G10+J10+L10 -> 14746 | D10: =B10-C10 -> 14590.01 | E10: =D10/B10*100 -> 49.734132 | F10: =D10/K10 -> 455.93781 | H10: 35 | I10: 33 | J10: =K10*T10 -> 11776 | K10: 32 | L10: =I10*90 -> 2970 | M10: =I10-K10-N10 -> 1 | O10: =M10/I10*100 -> 3.030303 | P10: =I10/H10*100 -> 94.285714 | Q10: =K10/I10*100 -> 96.969697 | R10: =G10/K10 -> 0 | S10: =100-P10 -> 5.7142857 | T10: 368 | W10: V6
A11: V5 | B11: 0 | C11: =G11+J11+L11 -> 0 | D11: =B11-C11 -> 0 | E11: =D11/B11*100 -> #DIV/0! | F11: =D11/K11 -> #DIV/0! | H11: 0 | I11: 0 | J11: =K11*T11 -> 0 | K11: 0 | L11: =I11*90 -> 0 | M11: =I11-K11-N11 -> 0 | T11: 206 | W11: V7
A12: V6 | B12: 167997.29 | C12: =G12+J12+L12 -> 57994 | D12: =B12-C12 -> 110003.29 | E12: =D12/B12*100 -> 65.479205 | F12: =D12/K12 -> 769.25378 | H12: 158 | I12: 155 | J12: =K12*T12 -> 44044 | K12: 143 | L12: =I12*90 -> 13950 | M12: =I12-K12-N12 -> 11 | N12: 1 | O12: =M12/I12*100 -> 7.0967742 | P12: =I12/H12*100 -> 98.101266 | Q12: =K12/I12*100 -> 92.258065 | R12: =G12/K12 -> 0 | S12: =100-P12 -> 1.8987342 | T12: 308 | W12: V8
A13: V6- P of 2 | B13: 8766.1 | C13: =G13+J13+L13 -> 2914 | D13: =B13-C13 -> 5852.1 | E13: =D13/B13*100 -> 66.758308 | F13: =D13/K13 -> 1463.025 | H13: 5 | I13: 5 | J13: =K13*T13 -> 2464 | K13: 4 | L13: =I13*90 -> 450 | M13: =I13-K13-N13 -> 1 | O13: =M13/I13*100 -> 20 | P13: =I13/H13*100 -> 100 | Q13: =K13/I13*100 -> 80 | R13: =G13/K13 -> 0 | S13: =100-P13 -> 0 | T13: 616 | W13: V9
A14: V7 | B14: 78617.16 | C14: =G14+J14+L14 -> 40515 | D14: =B14-C14 -> 38102.16 | E14: =D14/B14*100 -> 48.46545 | F14: =D14/K14 -> 494.83325 | H14: 82 | I14: 78 | J14: =K14*T14 -> 33495 | K14: 77 | L14: =I14*90 -> 7020 | M14: =I14-K14-N14 -> 1 | O14: =M14/I14*100 -> 1.2820513 | P14: =I14/H14*100 -> 95.121951 | Q14: =K14/I14*100 -> 98.717949 | R14: =G14/K14 -> 0 | S14: =100-P14 -> 4.8780488 | T14: 435 | W14: V10
A15: V8 | B15: 0 | C15: =G15+J15+L15 -> 0 | D15: =B15-C15 -> 0 | E15: =D15/B15*100 -> #DIV/0! | F15: =D15/K15 -> #DIV/0! | H15: 0 | I15: 0 | J15: =K15*T15 -> 0 | K15: 0 | L15: =I15*90 -> 0 | M15: =I15-K15-N15 -> 0 | T15: 699
A16: V9 | B16: 1333289.1 | C16: =G16+J16+L16 -> 634218 | D16: =B16-C16 -> 699071.05 | E16: =D16/B16*100 -> 52.43207 | F16: =D16/K16 -> 962.90778 | H16: 788 | I16: 771 | J16: =K16*T16 -> 564828 | K16: 726 | L16: =I16*90 -> 69390 | M16: =I16-K16-N16 -> 45 | O16: =M16/I16*100 -> 5.8365759 | P16: =I16/H16*100 -> 97.84264 | Q16: =K16/I16*100 -> 94.163424 | R16: =G16/K16 -> 0 | S16: =100-P16 -> 2.1573604 | T16: 778
A17: V9 P of 2 | B17: 31338.48 | C17: =G17+J17+L17 -> 16460 | D17: =B17-C17 -> 14878.48 | E17: =D17/B17*100 -> 47.476712 | F17: =D17/K17 -> 1487.848 | H17: 12 | I17: 10 | J17: =K17*T17 -> 15560 | K17: 10 | L17: =I17*90 -> 900 | M17: =I17-K17-N17 -> 0 | O17: =M17/I17*100 -> 0 | P17: =I17/H17*100 -> 83.333333 | Q17: =K17/I17*100 -> 100 | R17: =G17/K17 -> 0 | S17: =100-P17 -> 16.666667 | T17: 1556
A18: V10 | B18: 589604.84 | C18: =G18+J18+L18 -> 364541 | D18: =B18-C18 -> 225063.84 | E18: =D18/B18*100 -> 38.17198 | F18: =D18/K18 -> 684.08462 | H18: 389 | I18: 362 | J18: =K18*T18 -> 331961 | K18: 329 | L18: =I18*90 -> 32580 | M18: =I18-K18-N18 -> 32 | N18: 1 | O18: =M18/I18*100 -> 8.839779 | P18: =I18/H18*100 -> 93.059126 | Q18: =K18/I18*100 -> 90.883978 | R18: =G18/K18 -> 0 | S18: =100-P18 -> 6.940874 | T18: 1009
A19: Busy Book | B19: 73782.27 | C19: =G19+J19+L19 -> 57480 | D19: =B19-C19 -> 16302.27 | E19: =D19/B19*100 -> 22.095105 | F19: =D19/K19 -> 97.037321 | H19: 186 | I19: 172 | J19: =K19*T19 -> 42000 | K19: 168 | L19: =I19*90 -> 15480 | M19: =I19-K19-N19 -> 4 | O19: =M19/I19*100 -> 2.3255814 | P19: =I19/H19*100 -> 92.473118 | Q19: =K19/I19*100 -> 97.674419 | R19: =G19/K19 -> 0 | S19: =100-P19 -> 7.5268817 | T19: 250
A20: Busy Book Pink | B20: 58295.38 | C20: =G20+J20+L20 -> 25740 | D20: =B20-C20 -> 32555.38 | E20: =D20/B20*100 -> 55.845558 | F20: =D20/K20 -> 493.26333 | H20: 111 | I20: 66 | J20: =K20*T20 -> 19800 | K20: 66 | L20: =I20*90 -> 5940 | M20: =I20-K20-N20 -> 0 | O20: =M20/I20*100 -> 0 | P20: =I20/H20*100 -> 59.459459 | Q20: =K20/I20*100 -> 100 | R20: =G20/K20 -> 0 | S20: =100-P20 -> 40.540541 | T20: 300
A21: Human Book | B21: 44191.69 | C21: =G21+J21+L21 -> 23880 | D21: =B21-C21 -> 20311.69 | E21: =D21/B21*100 -> 45.962691 | F21: =D21/K21 -> 332.97852 | H21: 72 | I21: 62 | J21: =K21*T21 -> 18300 | K21: 61 | L21: =I21*90 -> 5580 | M21: =I21-K21-N21 -> 0 | N21: 1 | O21: =M21/I21*100 -> 0 | P21: =I21/H21*100 -> 86.111111 | Q21: =K21/I21*100 -> 98.387097 | R21: =G21/K21 -> 0 | S21: =100-P21 -> 13.888889 | T21: 300
A22: V9-V3 Combo | B22: 215784.73 | C22: =G22+J22+L22 -> 127260 | D22: =B22-C22 -> 88524.73 | E22: =D22/B22*100 -> 41.024557 | F22: =D22/K22 -> 1066.563 | H22: 89 | I22: 86 | J22: =K22*T22 -> 119520 | K22: 83 | L22: =I22*90 -> 7740 | M22: =I22-K22-N22 -> 3 | O22: =M22/I22*100 -> 3.4883721 | P22: =I22/H22*100 -> 96.629213 | Q22: =K22/I22*100 -> 96.511628 | R22: =G22/K22 -> 0 | S22: =100-P22 -> 3.3707865 | T22: 1440
A23: V9-V10 Combo | B23: 112465.89 | C23: =G23+J23+L23 -> 80891 | D23: =B23-C23 -> 31574.89 | E23: =D23/B23*100 -> 28.075081 | F23: =D23/K23 -> 734.29977 | H23: 46 | I23: 45 | J23: =K23*T23 -> 76841 | K23: 43 | L23: =I23*90 -> 4050 | M23: =I23-K23-N23 -> 2 | O23: =M23/I23*100 -> 4.4444444 | P23: =I23/H23*100 -> 97.826087 | Q23: =K23/I23*100 -> 95.555556 | R23: =G23/K23 -> 0 | S23: =100-P23 -> 2.173913 | T23: 1787
A24: V7-V4 Combo | B24: 13958.41 | C24: =G24+J24+L24 -> 5852 | D24: =B24-C24 -> 8106.41 | E24: =D24/B24*100 -> 58.075454 | F24: =D24/K24 -> 1013.3012 | H24: 12 | I24: 10 | J24: =K24*T24 -> 4952 | K24: 8 | L24: =I24*90 -> 900 | M24: =I24-K24-N24 -> 2 | O24: =M24/I24*100 -> 20 | P24: =I24/H24*100 -> 83.333333 | Q24: =K24/I24*100 -> 80 | R24: =G24/K24 -> 0 | S24: =100-P24 -> 16.666667 | T24: 619
A25: V1-V4 Combo | B25: 76710.99 | C25: =G25+J25+L25 -> 31976 | D25: =B25-C25 -> 44734.99 | E25: =D25/B25*100 -> 58.316273 | F25: =D25/K25 -> 698.98422 | H25: 68 | I25: 68 | J25: =K25*T25 -> 25856 | K25: 64 | L25: =I25*90 -> 6120 | M25: =I25-K25-N25 -> 4 | O25: =M25/I25*100 -> 5.8823529 | P25: =I25/H25*100 -> 100 | Q25: =K25/I25*100 -> 94.117647 | R25: =G25/K25 -> 0 | S25: =100-P25 -> 0 | T25: 404
A26: V1-V7 Combo | B26: 33500.28 | C26: =G26+J26+L26 -> 14245 | D26: =B26-C26 -> 19255.28 | E26: =D26/B26*100 -> 57.477967 | F26: =D26/K26 -> 1013.4358 | H26: 20 | I26: 20 | J26: =K26*T26 -> 12445 | K26: 19 | L26: =I26*90 -> 1800 | M26: =I26-K26-N26 -> 1 | O26: =M26/I26*100 -> 5 | P26: =I26/H26*100 -> 100 | Q26: =K26/I26*100 -> 95 | R26: =G26/K26 -> 0 | S26: =100-P26 -> 0 | T26: 655
A27: V6-V2 Combo | B27: 42657.4 | C27: =G27+J27+L27 -> 14922 | D27: =B27-C27 -> 27735.4 | E27: =D27/B27*100 -> 65.018965 | F27: =D27/K27 -> 1320.7333 | H27: 26 | I27: 23 | J27: =K27*T27 -> 12852 | K27: 21 | L27: =I27*90 -> 2070 | M27: =I27-K27-N27 -> 2 | O27: =M27/I27*100 -> 8.6956522 | P27: =I27/H27*100 -> 88.461538 | Q27: =K27/I27*100 -> 91.304348 | R27: =G27/K27 -> 0 | S27: =100-P27 -> 11.538462 | T27: 612
A28: V6-V7 Combo | B28: 38376.76 | C28: =G28+J28+L28 -> 17493 | D28: =B28-C28 -> 20883.76 | E28: =D28/B28*100 -> 54.417726 | F28: =D28/K28 -> 994.46476 | H28: 21 | I28: 21 | J28: =K28*T28 -> 15603 | K28: 21 | L28: =I28*90 -> 1890 | M28: =I28-K28-N28 -> 0 | O28: =M28/I28*100 -> 0 | P28: =I28/H28*100 -> 100 | Q28: =K28/I28*100 -> 100 | R28: =G28/K28 -> 0 | S28: =100-P28 -> 0 | T28: 743
A29: V2-V7 Combo | B29: 35758.4 | C29: =G29+J29+L29 -> 17409 | D29: =B29-C29 -> 18349.4 | E29: =D29/B29*100 -> 51.314936 | F29: =D29/K29 -> 873.78095 | H29: 21 | I29: 21 | J29: =K29*T29 -> 15519 | K29: 21 | L29: =I29*90 -> 1890 | M29: =I29-K29-N29 -> 0 | O29: =M29/I29*100 -> 0 | P29: =I29/H29*100 -> 100 | Q29: =K29/I29*100 -> 100 | R29: =G29/K29 -> 0 | S29: =100-P29 -> 0 | T29: 739
A30: V1-V2 Combo | B30: 25700.81 | C30: =G30+J30+L30 -> 8866 | D30: =B30-C30 -> 16834.81 | E30: =D30/B30*100 -> 65.503033 | F30: =D30/K30 -> 1202.4864 | H30: 18 | I30: 17 | J30: =K30*T30 -> 7336 | K30: 14 | L30: =I30*90 -> 1530 | M30: =I30-K30-N30 -> 2 | N30: 1 | O30: =M30/I30*100 -> 11.764706 | P30: =I30/H30*100 -> 94.444444 | Q30: =K30/I30*100 -> 82.352941 | R30: =G30/K30 -> 0 | S30: =100-P30 -> 5.5555556 | T30: 524
A31: V6-V4 Combo | B31: 14372.6 | C31: =G31+J31+L31 -> 4746 | D31: =B31-C31 -> 9626.6 | E31: =D31/B31*100 -> 66.978835 | F31: =D31/K31 -> 1203.325 | H31: 9 | I31: 9 | J31: =K31*T31 -> 3936 | K31: 8 | L31: =I31*90 -> 810 | M31: =I31-K31-N31 -> 1 | O31: =M31/I31*100 -> 11.111111 | P31: =I31/H31*100 -> 100 | Q31: =K31/I31*100 -> 88.888889 | R31: =G31/K31 -> 0 | S31: =100-P31 -> 0 | T31: 492
A32: V2-V4 Combo | B32: 9084.1 | C32: =G32+J32+L32 -> 3468 | D32: =B32-C32 -> 5616.1 | E32: =D32/B32*100 -> 61.823406 | F32: =D32/K32 -> 936.01667 | H32: 7 | I32: 6 | J32: =K32*T32 -> 2928 | K32: 6 | L32: =I32*90 -> 540 | M32: =I32-K32-N32 -> 0 | O32: =M32/I32*100 -> 0 | P32: =I32/H32*100 -> 85.714286 | Q32: =K32/I32*100 -> 100 | R32: =G32/K32 -> 0 | S32: =100-P32 -> 14.285714 | T32: 488
A33: Total | B33: 4707817 | D33: =SUM(D4:D32) -> 2281077.8 | G33: 2001000 | H33: =SUM(H4:H32) -> 4227 | I33: =SUM(I4:I32) -> 4059 | J33: =SUM(J4:J32) -> 2005012 | K33: =SUM(K4:K32) -> 3850 | L33: =SUM(L4:L32) -> 365310 | M33: =SUM(M4:M32) -> 205 | N33: =SUM(N4:N32) -> 4 | O33: =AVERAGE(O4:O32) -> 5.2789639 | P33: =AVERAGE(P4:P32) -> 93.268458 | Q33: =AVERAGE(Q4:Q32) -> 94.409308 | R33: =SUM(R4:R32) -> 0 | S33: =AVERAGE(S4:S32) -> 6.7315418
D36: Blended
A37: Total Units Sold | B37: =K33 -> 3850
A38: Total Revenue | B38: =B33 -> 4707817 | D38: COGS | E38: =B39/B37 -> 520.78234
A39: COGS | B39: =J33 -> 2005012 | D39: CAC | E39: 674
A40: Logistics | B40: =L33 -> 365310 | D40: Logistics | E40: =B40/B37 -> 94.885714
A41: Marketing | B41: =G33 -> 2001000 | D41: AOV | E41: =B38/B37 -> 1222.8096
A42: P&L | B42: =B38-(B39+B40+B41) -> 336495
A43: P&L % | B43: =B42/B38 -> 0.071475803
A46: June | B46: Amazon
B48: Total revenue | C48: Total expense | D48: Total P/L | E48: Profit % | F48: P/pcs | G48: Total orders | H48: Product expense | I48: Delivered | J48: Return | K48: Amazon expense | L48: RTO% | M48: Only Ad spend | N48: Return GMV
A49: V1 | B49: =542543+7446+2549 -> 552538 | C49: =K49+H49 -> 341223.62 | D49: =B49-C49 -> 211314.38 | E49: =D49/B49*100 -> 38.244316 | F49: =D49/I49 -> 356.34803 | G49: =631+6 -> 637 | H49: =220*I49 -> 130460 | I49: =580+3+10 -> 593 | J49: =G49-I49 -> 44 | K49: =208415.6 +770.57+357.14+1220.31 -> 210763.62 | L49: =J49/G49*100 -> 6.9073783 | M49: 0 | N49: =J49*999 -> 43956 | O49: =B49/M49 -> #DIV/0! | P49: =B49/B66*100 -> 28.768029
A50: V2 | B50: =311048 -> 311048 | C50: =K50+H50 -> 147522.48 | D50: =B50-C50 -> 163525.52 | E50: =D50/B50*100 -> 52.572439 | F50: =D50/I50 -> 612.45513 | G50: =287 -> 287 | H50: =304*I50 -> 81168 | I50: =267 -> 267 | J50: =G50-I50 -> 20 | K50: =844.75+65509.73 -> 66354.48 | L50: =J50/G50*100 -> 6.9686411 | M50: 0 | N50: =J50*1119 -> 22380 | O50: =B50/M50 -> #DIV/0! | P50: =B50/B66*100 -> 16.194792
A51: V3 | B51: =3388.9+15964.23+15992+1999 -> 37344.13 | C51: =K51+H51 -> 23638.64 | D51: =B51-C51 -> 13705.49 | E51: =D51/B51*100 -> 36.70052 | F51: =D51/I51 -> 622.97682 | G51: =1+8+10+5 -> 24 | H51: =662*I51 -> 14564 | I51: 22 | J51: =G51-I51 -> 2 | K51: =1287.79 +2811.23+4645.73+329.89 -> 9074.64 | L51: =J51/G51*100 -> 8.3333333 | M51: 0 | N51: =J51*1799 -> 3598 | O51: =B51/M51 -> #DIV/0! | P51: =B51/B66*100 -> 1.9443315
A52: V4 | B52: =293626+1349+3593.32 -> 298568.32 | C52: =K52+H52 -> 276163.93 | D52: =B52-C52 -> 22404.39 | E52: =D52/B52*100 -> 7.5039408 | F52: =D52/I52 -> 33.290327 | G52: =708+1+4 -> 713 | H52: =184*I52 -> 123832 | I52: =662+3+8 -> 673 | J52: =G52-I52 -> 40 | K52: =774.92+150771.6+255.14 +530.27 -> 152331.93 | L52: =J52/G52*100 -> 5.6100982 | M52: 0 | N52: =J52*499 -> 19960 | O52: =B52/M52 -> #DIV/0! | P52: =B52/B66*100 -> 15.545034
A53: V5 | B53: 0 | C53: =K53+H53 -> 0 | D53: =B53-C53 -> 0 | E53: =D53/B53*100 -> #DIV/0! | F53: =D53/I53 -> #DIV/0! | G53: 0 | H53: =250*I53 -> 0 | I53: 0 | J53: =G53-I53 -> 0 | K53: 0 | L53: =J53/G53*100 -> #DIV/0! | M53: 0 | N53: =J53*1049 -> 0 | O53: =B53/M53 -> #DIV/0! | P53: =B53/B66*100 -> 0
A54: V6 | B54: =174667 -> 174667 | C54: =K54+H54 -> 135829.25 | D54: =B54-C54 -> 38837.75 | E54: =D54/B54*100 -> 22.235311 | F54: =D54/I54 -> 248.95994 | G54: 176 | H54: =308*I54 -> 48048 | I54: 156 | J54: =G54-I54 -> 20 | K54: =87781.25 -> 87781.25 | L54: =J54/G54*100 -> 11.363636 | M54: 0 | N54: =J54*1249 -> 24980 | O54: =B54/M54 -> #DIV/0! | P54: =B54/B66*100 -> 9.0940811
A55: V7 | B55: =50157.89 -> 50157.89 | C55: =K55+H55 -> 44177.47 | D55: =B55-C55 -> 5980.42 | E55: =D55/B55*100 -> 11.923189 | F55: =D55/I55 -> 149.5105 | G55: 42 | H55: =435*I55 -> 17400 | I55: 40 | J55: =G55-I55 -> 2 | K55: =26777.47 -> 26777.47 | L55: =J55/G55*100 -> 4.7619048 | M55: 0 | N55: =J55*1349 -> 2698 | O55: =B55/M55 -> #DIV/0! | P55: =B55/B66*100 -> 2.6114831
A56: V8 | B56: 0 | C56: =K56+H56 -> 0 | D56: =B56-C56 -> 0 | E56: =D56/B56*100 -> #DIV/0! | F56: =D56/I56 -> #DIV/0! | G56: 0 | H56: =800*I56 -> 0 | I56: 0 | J56: =G56-I56 -> 0 | K56: 0 | L56: =J56/G56*100 -> #DIV/0! | M56: 0 | N56: =J56*1899 -> 0 | O56: =B56/M56 -> #DIV/0! | P56: =B56/B66*100 -> 0
A57: V9 | B57: =415403+2299 -> 417702 | C57: =K57+H57 -> 269250.24 | D57: =B57-C57 -> 148451.76 | E57: =D57/B57*100 -> 35.540112 | F57: =D57/I57 -> 645.44243 | G57: 283 | H57: =778*I57 -> 178940 | I57: 230 | J57: =G57-I57 -> 53 | K57: =87893.64+2416.6 -> 90310.24 | L57: =J57/G57*100 -> 18.727915 | M57: 0 | N57: =J57*1999 -> 105947 | O57: =B57/M57 -> #DIV/0! | P57: =B57/B66*100 -> 21.747759
A58: BB | B58: =42028 -> 42028 | C58: =K58+H58 -> 64316.57 | D58: =B58-C58 -> -22288.57 | E58: =D58/B58*100 -> -53.032669 | F58: =D58/I58 -> -305.32288 | G58: 80 | H58: =200*I58 -> 14600 | I58: 73 | J58: =G58-I58 -> 7 | K58: =49716.57 -> 49716.57 | L58: =J58/G58*100 -> 8.75 | M58: 0 | N58: =J58*599 -> 4193 | O58: =B58/M58 -> #DIV/0! | P58: =B58/B66*100 -> 2.1881984
A59: V1V4 | B59: =4097 -> 4097 | C59: =K59+H59 -> 2205.17 | D59: =B59-C59 -> 1891.83 | E59: =D59/B59*100 -> 46.175982 | F59: =D59/I59 -> 630.61 | G59: 3 | H59: =(270+220)*I59 -> 1470 | I59: 3 | J59: =G59-I59 -> 0 | K59: =735.17 -> 735.17 | L59: =J59/G59*100 -> 0 | M59: 0 | O59: =B59/M59 -> #DIV/0! | P59: =B59/B66*100 -> 0.21331133
A60: V1V2 | B60: =4374.34 -> 4374.34 | C60: =K60+H60 -> 1920.38 | D60: =B60-C60 -> 2453.96 | E60: =D60/B60*100 -> 56.098977 | F60: =D60/I60 -> 1226.98 | G60: 2 | H60: =(270+350)*I60 -> 1240 | I60: 2 | J60: =G60-I60 -> 0 | K60: =680.38 -> 680.38 | L60: =J60/G60*100 -> 0 | M60: 0 | N60: =J60*2199 -> 0 | O60: =B60/M60 -> #DIV/0! | P60: =B60/B66*100 -> 0.22775111
A61: V1V6 | B61: =2187.15 -> 2187.15 | C61: =K61+H61 -> 930.16 | D61: =B61-C61 -> 1256.99 | E61: =D61/B61*100 -> 57.471595 | F61: =D61/I61 -> 1256.99 | G61: 1 | H61: =(270+320)*I61 -> 590 | I61: 1 | J61: =G61-I61 -> 0 | K61: =340.16 -> 340.16 | L61: =J61/G61*100 -> 0 | M61: 0 | N61: =J61*999 -> 0 | O61: =B61/M61 -> #DIV/0! | P61: =B61/B66*100 -> 0.11387451
A62: V2V4 | B62: =21587 -> 21587 | C62: =K62+H62 -> 21307.6 | D62: =B62-C62 -> 279.4 | E62: =D62/B62*100 -> 1.2942975 | F62: =D62/I62 -> 21.492308 | G62: 15 | H62: =(350+220)*I62 -> 7410 | I62: 13 | J62: =G62-I62 -> 2 | K62: =13897.6 -> 13897.6 | L62: =J62/G62*100 -> 13.333333 | M62: 0 | N62: =J62*1499 -> 2998 | O62: =B62/M62 -> #DIV/0! | P62: =B62/B66*100 -> 1.1239326
A63: V2V6 | B63: =4368 -> 4368 | C63: =K63+H63 -> 12797.78 | D63: =B63-C63 -> -8429.78 | E63: =D63/B63*100 -> -192.98947 | F63: =D63/I63 -> -4214.89 | G63: 2 | H63: =(350+320)*I63 -> 1340 | I63: 2 | J63: =G63-I63 -> 0 | K63: =11457.78 -> 11457.78 | L63: =J63/G63*100 -> 0 | M63: 0 | N63: =J63*999 -> 0 | O63: =B63/M63 -> #DIV/0! | P63: =B63/B66*100 -> 0.22742102
A64: NBB | B64: =19980+103297 -> 123277 | C64: =K64+H64 -> 71654.69 | D64: =B64-C64 -> 51622.31 | E64: =D64/B64*100 -> 41.875054 | F64: =D64/I64 -> 419.69358 | G64: 128 | H64: =(330)*I64 -> 40590 | I64: 123 | J64: =G64-I64 -> 5 | K64: =26583.01+4481.68 -> 31064.69 | L64: =J64/G64*100 -> 3.90625 | M64: 0 | N64: =J64*999 -> 4995 | O64: =B64/M64 -> #DIV/0! | P64: =B64/B66*100 -> 6.4184479
A65: V10 | B65: =25940.95 -> 25940.95 | C65: =K65+H65 -> 17816.02 | D65: =B65-C65 -> 8124.93 | E65: =D65/B65*100 -> 31.320865 | F65: =D65/I65 -> 624.99462 | G65: 14 | H65: =(1009)*I65 -> 13117 | I65: 13 | J65: =G65-I65 -> 1 | K65: =4699.02 -> 4699.02 | L65: =J65/G65*100 -> 7.1428571
A66: Total | B66: =SUM(B49:B63) -> 1920666.8 | C66: =SUM(C49:C63) -> 1341283.3 | D66: =B66-C66 -> 579383.54 | G66: =SUM(G47:G63) -> 2265 | H66: =SUM(H49:H63) -> 621062 | I66: =SUM(I47:I63) -> 2075 | K66: =SUM(K49:K65) -> 755985 | M66: =SUM(M47:M63) -> 0
A69: Total Revenue | B69: =B66 -> 1920666.8
A70: COGS | B70: =H66 -> 621062 | D70: Blended
A71: Amazon Ex | B71: 103750 | D71: COGS | E71: =B70/I66 -> 299.30699
A72: Logi | B72: 239937
A73: Marketing | B73: =113398+300000 -> 413398 | D73: CAC | E73: =B73/I66 -> 199.22795
A74: Net P&L | B74: =B69-SUM(B70:B73) -> 542519.83 | D74: Commisions | E74: =B71/I66 -> 50
A75: P&L % | B75: =B74/B69*100 -> 28.246431 | D75: AOV | E75: =B69/I66 -> 925.62257
A82: June | B82: Flipkart
B84: Total revenue | C84: Total expense | D84: Total P/L | E84: Profit % | F84: P/pcs | G84: Total orders | H84: Product expense | I84: Delivered | J84: Return | K84: Flipkart expenses | L84: RTO% | M84: Only Ad spend
A85: V1 | B85: =11228 -> 11228 | C85: =K85+H85 -> 7476.24 | D85: =B85-C85 -> 3751.76 | E85: =D85/B85*100 -> 33.414321 | F85: =D85/I85 -> 312.64667 | G85: 22 | H85: =270*I85 -> 3240 | I85: 12 | J85: =G85-I85 -> 10 | K85: =4236.24 -> 4236.24 | L85: =J85/G85*100 -> 45.454545 | M85: =20%*B85 -> 2245.6 | P85: =B85/B101*100 -> 8.9799575
A86: V2 | B86: =18285 -> 18285 | C86: =K86+H86 -> 10621.8 | D86: =B86-C86 -> 7663.2 | E86: =D86/B86*100 -> 41.909762 | F86: =D86/I86 -> 478.95 | G86: 23 | H86: =350*I86 -> 5600 | I86: 16 | J86: =G86-I86 -> 7 | K86: =5021.8 -> 5021.8 | L86: =J86/G86*100 -> 30.434783 | M86: =20%*B86 -> 3657 | P86: =B86/B101*100 -> 14.624022
A87: V3 | B87: =1749 -> 1749 | C87: =K87+H87 -> 1960.27 | D87: =B87-C87 -> -211.27 | E87: =D87/B87*100 -> -12.079474 | F87: =D87/I87 -> -211.27 | G87: 2 | H87: =980*I87 -> 980 | I87: 1 | J87: =G87-I87 -> 1 | K87: =980.27 -> 980.27 | L87: =J87/G87*100 -> 50 | M87: =20%*B87 -> 349.8 | P87: =B87/B101*100 -> 1.3988195
A88: V4 | B88: =49838 -> 49838 | C88: =K88+H88 -> 37131.93 | D88: =B88-C88 -> 12706.07 | E88: =D88/B88*100 -> 25.494743 | F88: =D88/I88 -> 117.6488 | G88: 134 | H88: =220*I88 -> 23760 | I88: 108 | J88: =G88-I88 -> 26 | K88: =13371.93 -> 13371.93 | L88: =J88/G88*100 -> 19.402985 | M88: =20%*B88 -> 9967.6 | P88: =B88/B101*100 -> 39.859558
A89: V5 | B89: 0 | C89: =K89+H89 -> 0 | D89: =B89-C89 -> 0 | E89: =D89/B89*100 -> #DIV/0! | F89: =D89/I89 -> #DIV/0! | G89: 0 | H89: =270*I89 -> 0 | I89: 0 | J89: =G89-I89 -> 0 | K89: 0 | L89: =J89/G89*100 -> #DIV/0! | M89: =20%*B89 -> 0 | P89: =B89/B101*100 -> 0
A90: V6 | B90: =6654 -> 6654 | C90: =K90+H90 -> 3948.57 | D90: =B90-C90 -> 2705.43 | E90: =D90/B90*100 -> 40.658702 | F90: =D90/I90 -> 450.905 | G90: 10 | H90: =320*I90 -> 1920 | I90: 6 | J90: =G90-I90 -> 4 | K90: =2028.57 -> 2028.57 | L90: =J90/G90*100 -> 40 | M90: =20%*B90 -> 1330.8 | P90: =B90/B101*100 -> 5.3217525
A91: V7 | B91: =2478 -> 2478 | C91: =K91+H91 -> 1776.97 | D91: =B91-C91 -> 701.03 | E91: =D91/B91*100 -> 28.290153 | F91: =D91/I91 -> 350.515 | G91: 6 | H91: =470*I91 -> 940 | I91: 2 | J91: =G91-I91 -> 4 | K91: =836.97 -> 836.97 | L91: =J91/G91*100 -> 66.666667 | M91: =20%*B91 -> 495.6 | P91: =B91/B101*100 -> 1.9818609
A92: Wooden cal | B92: =614 -> 614 | C92: =K92+H92 -> 1206.6 | D92: =B92-C92 -> -592.6 | E92: =D92/B92*100 -> -96.514658 | F92: =D92/I92 -> -592.6 | G92: 5 | H92: =200*I92 -> 200 | I92: 1 | J92: =G92-I92 -> 4 | K92: =1006.6 -> 1006.6 | L92: =J92/G92*100 -> 80 | M92: =20%*B92 -> 122.8 | P92: =B92/B101*100 -> 0.49106643
A93: V9 | B93: 7556 | C93: =K93+H93 -> 6532 | D93: =B93-C93 -> 1024 | E93: =D93/B93*100 -> 13.552144 | F93: =D93/I93 -> 256 | G93: 9 | H93: =1000*I93 -> 4000 | I93: 4 | J93: =G93-I93 -> 5 | K93: 2532 | L93: =J93/G93*100 -> 55.555556 | M93: 0 | P93: =B93/B101*100 -> 6.0431563
A94: V4V2 | B94: =18944 -> 18944 | C94: =K94+H94 -> 11430.14 | D94: =B94-C94 -> 7513.86 | E94: =D94/B94*100 -> 39.663535 | F94: =D94/I94 -> 536.70429 | G94: 15 | H94: =(220+350)*I94 -> 7980 | I94: 14 | J94: =G94-I94 -> 1 | K94: =3450.14 -> 3450.14 | L94: =J94/G94*100 -> 6.6666667 | M94: =20%*B94 -> 3788.8 | P94: =B94/B101*100 -> 15.151079
A95: V1V4 | B95: 0 | C95: =K95+H95 -> 0 | D95: =B95-C95 -> 0 | E95: =D95/B95*100 -> #DIV/0! | F95: =D95/I95 -> #DIV/0! | G95: 0 | H95: =(270+220)*I95 -> 0 | I95: 0 | J95: =G95-I95 -> 0 | K95: 0 | L95: =J95/G95*100 -> #DIV/0! | M95: =20%*B95 -> 0 | P95: =B95/B101*100 -> 0
A96: V6V2 | B96: =4096 -> 4096 | C96: =K96+H96 -> 2334.78 | D96: =B96-C96 -> 1761.22 | E96: =D96/B96*100 -> 42.998535 | F96: =D96/I96 -> 880.61 | G96: 3 | H96: =(320+350)*I96 -> 1340 | I96: 2 | J96: =G96-I96 -> 1 | K96: =994.78 -> 994.78 | L96: =J96/G96*100 -> 33.333333 | M96: =20%*B96 -> 819.2 | P96: =B96/B101*100 -> 3.275909
A97: V1V2 | B97: =3592 -> 3592 | C97: =K97+H97 -> 1999.39 | D97: =B97-C97 -> 1592.61 | E97: =D97/B97*100 -> 44.337695 | F97: =D97/I97 -> 796.305 | G97: 3 | H97: =(270+350)*I97 -> 1240 | I97: 2 | J97: =G97-I97 -> 1 | K97: =759.39 -> 759.39 | L97: =J97/G97*100 -> 33.333333 | M97: =20%*B97 -> 718.4 | P97: =B97/B101*100 -> 2.8728186
B98: =SUM(B85:B97) -> 125034 | C98: =SUM(C85:C97) -> 86418.69 | D98: =SUM(D85:D97) -> 38615.31 | G98: =SUM(G85:G97) -> 232 | H98: =SUM(H85:H97) -> 51200 | I98: =SUM(I85:I97) -> 168 | J98: =SUM(J85:J97) -> 64 | K98: =SUM(K85:K97) -> 35218.69 | M98: =SUM(M85:M97) -> 23495.6 | P98: =B98/B101*100 -> 100
A101: Total Revenue | B101: =B98 -> 125034
A102: COGS | B102: =H98 -> 51200
A103: Flipkart Ex | B103: =K98-B104 -> 11723.09 | D103: COGS | E103: =B102/I98 -> 304.7619
A104: Marketing | B104: =M98 -> 23495.6 | D104: CAC | E104: =B104/I98 -> 139.85476
A105: Net P&L | B105: =B101-SUM(B102:B104) -> 38615.31 | D105: Commisions | E105: =B103/I98 -> 69.780298
A106: P&L % | B106: =B105/B101*100 -> 30.883848 | D106: AOV | E106: =B101/I98 -> 744.25
A111: June | B111: Blinkit
B113: Total revenue | C113: Total expense | D113: Total P/L | E113: Profit % | F113: P/pcs | G113: Product exp | H113: Total orders | I113: Blinkit exp | J113: Ads | K113: Logistics
A114: V1 | B114: =689*H114 -> 73723 | C114: =J114+G114+I114+K114 -> 31030 | D114: =B114-C114 -> 42693 | E114: =D114/B114*100 -> 57.910015 | F114: =D114/H114 -> 399 | G114: =270*H114 -> 28890 | H114: 107 | I114: 0 | J114: 0 | K114: =20*H114 -> 2140 | M114: 59209
A115: V4 | B115: =359*H115 -> 32669 | C115: =J115+G115+I115+K115 -> 21840 | D115: =B115-C115 -> 10829 | E115: =D115/B115*100 -> 33.147632 | F115: =D115/H115 -> 119 | G115: =220*H115 -> 20020 | H115: 91 | I115: 0 | J115: 0 | K115: =20*H115 -> 1820
A116: V2 | B116: =781*H116 -> 56232 | C116: =J116+G116+I116+K116 -> 26640 | D116: =B116-C116 -> 29592 | E116: =D116/B116*100 -> 52.62484 | F116: =D116/H116 -> 411 | G116: =350*H116 -> 25200 | H116: 72 | I116: 0 | J116: =L116%*M116 -> 0 | K116: =20*H116 -> 1440
A117: V6 | B117: =843*H117 -> 29505 | C117: =J117+G117+I117+K117 -> 12950 | D117: =B117-C117 -> 16555 | E117: =D117/B117*100 -> 56.109134 | F117: =D117/H117 -> 473 | G117: =350*H117 -> 12250 | H117: 35 | I117: 0 | J117: =L117%*M117 -> 0 | K117: =20*H117 -> 700
B118: =SUM(B114:B117) -> 192129 | C118: =SUM(C114:C117) -> 92460 | D118: =SUM(D114:D117) -> 99669 | E118: =SUM(E114:E117) -> 199.79162 | F118: =SUM(F114:F117) -> 1402 | G118: =SUM(G114:G117) -> 86360 | H118: =SUM(H114:H117) -> 305 | I118: 59209 | J118: =SUM(J114:J117) -> 0 | K118: =SUM(K114:K117) -> 6100
A121: Total Revenue | B121: =B118 -> 192129 | D121: Blended
A122: COGS | B122: =G118 -> 86360 | D122: COGS | E122: =B122/H118 -> 283.14754
A123: Logitics | B123: =K118 -> 6100 | D123: CAC | E123: =B124/H118 -> 194.12787
A124: Ad Spent | B124: =I118+J118 -> 59209 | D124: Logistics | E124: =K118/H118 -> 20
...

Sheet July 25
A1: July | B1: Shopify
A3: Products | B3: Total Dilivered Revenue | C3: Total expense | D3: Total P/L | E3: Profit % | F3: P/pcs | G3: Ad spent | H3: Total orders | I3: Shipped | J3: Total COGS | K3: Delivered | L3: Shipping charges | M3: RTO | N3: In-transit | O3: RTO% | P3: Shipped% | Q3: Delivered % | R3: CPD | S3: Cancellation % | T3: COGS/Unit
A4: V1 | B4: 974085.05 | C4: =G4+J4+L4 -> 530084 | D4: =B4-C4 -> 444001.05 | E4: =D4/B4*100 -> 45.581343 | F4: =D4/K4 -> 264.44375 | H4: 1739 | I4: 1728 | J4: =K4*T4 -> 369380 | K4: 1679 | L4: =I4*93 -> 160704 | M4: =I4-K4-N4 -> 44 | N4: 5 | O4: =M4/I4*100 -> 2.5462963 | P4: =I4/H4*100 -> 99.367453 | Q4: =K4/I4*100 -> 97.164352 | R4: =G4/K4 -> 0 | S4: =100-P4 -> 0.63254744 | T4: 220 | W4: Products | X4: Total Cost
A5: V1- P of 2 | B5: 72563.57 | C5: =G5+J5+L5 -> 27462 | D5: =B5-C5 -> 45101.57 | E5: =D5/B5*100 -> 62.154563 | F5: =D5/K5 -> 884.34451 | H5: 54 | I5: 54 | J5: =K5*T5 -> 22440 | K5: 51 | L5: =I5*93 -> 5022 | M5: =I5-K5-N5 -> 3 | O5: =M5/I5*100 -> 5.5555556 | P5: =I5/H5*100 -> 100 | Q5: =K5/I5*100 -> 94.444444 | R5: =G5/K5 -> 0 | T5: 440 | W5: V1 | X5: 220
A6: V2 | B6: 1021573.8 | C6: =G6+J6+L6 -> 360620 | D6: =B6-C6 -> 660953.81 | E6: =D6/B6*100 -> 64.699565 | F6: =D6/K6 -> 747.68531 | H6: 996 | I6: 988 | J6: =K6*T6 -> 268736 | K6: 884 | L6: =I6*93 -> 91884 | M6: =I6-K6-N6 -> 96 | N6: 8 | O6: =M6/I6*100 -> 9.7165992 | P6: =I6/H6*100 -> 99.196787 | Q6: =K6/I6*100 -> 89.473684 | R6: =G6/K6 -> 0 | S6: =100-P6 -> 0.80321285 | T6: 304 | W6: V2 | X6: 304
A7: V2- P of 2 | B7: 62226.26 | C7: =G7+J7+L7 -> 20422 | D7: =B7-C7 -> 41804.26 | E7: =D7/B7*100 -> 67.181058 | F7: =D7/K7 -> 1441.5262 | H7: 30 | I7: 30 | J7: =K7*T7 -> 17632 | K7: 29 | L7: =I7*93 -> 2790 | M7: =I7-K7-N7 -> 1 | O7: =M7/I7*100 -> 3.3333333 | P7: =I7/H7*100 -> 100 | Q7: =K7/I7*100 -> 96.666667 | R7: =G7/K7 -> 0 | T7: 608 | W7: V3 | X7: 662
A8: V3 | B8: 335622.39 | C8: =G8+J8+L8 -> 186846 | D8: =B8-C8 -> 148776.39 | E8: =D8/B8*100 -> 44.328506 | F8: =D8/K8 -> 604.78207 | H8: 265 | I8: 258 | J8: =K8*T8 -> 162852 | K8: 246 | L8: =I8*93 -> 23994 | M8: =I8-K8-N8 -> 12 | O8: =M8/I8*100 -> 4.6511628 | P8: =I8/H8*100 -> 97.358491 | Q8: =K8/I8*100 -> 95.348837 | R8: =G8/K8 -> 0 | S8: =100-P8 -> 2.6415094 | T8: 662 | W8: V4 | X8: 184
A9: V4 | B9: 59048.48 | C9: =G9+J9+L9 -> 31214 | D9: =B9-C9 -> 27834.48 | E9: =D9/B9*100 -> 47.138351 | F9: =D9/K9 -> 253.04073 | H9: 124 | I9: 118 | J9: =K9*T9 -> 20240 | K9: 110 | L9: =I9*93 -> 10974 | M9: =I9-K9-N9 -> 7 | N9: 1 | O9: =M9/I9*100 -> 5.9322034 | P9: =I9/H9*100 -> 95.16129 | Q9: =K9/I9*100 -> 93.220339 | R9: =G9/K9 -> 0 | S9: =100-P9 -> 4.8387097 | T9: 184 | W9: V5 | X9: 206
A10: V4- P of 2 | B10: 10547.63 | C10: =G10+J10+L10 -> 5625 | D10: =B10-C10 -> 4922.63 | E10: =D10/B10*100 -> 46.670484 | F10: =D10/K10 -> 410.21917 | H10: 13 | I10: 13 | J10: =K10*T10 -> 4416 | K10: 12 | L10: =I10*93 -> 1209 | M10: =I10-K10-N10 -> 1 | O10: =M10/I10*100 -> 7.6923077 | P10: =I10/H10*100 -> 100 | Q10: =K10/I10*100 -> 92.307692 | R10: =G10/K10 -> 0 | T10: 368 | W10: V6 | X10: 308
A11: V5 | B11: 0 | C11: 0 | D11: 0 | E11: =D11/B11*100 -> #DIV/0! | F11: 0 | H11: 0 | I11: 0 | J11: 0 | K11: 0 | L11: =I11*93 -> 0 | M11: =I11-K11-N11 -> 0 | T11: 206 | W11: V7 | X11: 435
A12: V6 | B12: 773994.26 | C12: =G12+J12+L12 -> 275750 | D12: =B12-C12 -> 498244.26 | E12: =D12/B12*100 -> 64.373121 | F12: =D12/K12 -> 750.36786 | H12: 772 | I12: 766 | J12: =K12*T12 -> 204512 | K12: 664 | L12: =I12*93 -> 71238 | M12: =I12-K12-N12 -> 91 | N12: 11 | O12: =M12/I12*100 -> 11.879896 | P12: =I12/H12*100 -> 99.222798 | Q12: =K12/I12*100 -> 86.684073 | R12: =G12/K12 -> 0 | S12: =100-P12 -> 0.77720207 | T12: 308 | W12: V8 | X12: 699
A13: V6- P of 2 | B13: 29553.9 | C13: =G13+J13+L13 -> 10019 | D13: =B13-C13 -> 19534.9 | E13: =D13/B13*100 -> 66.099229 | F13: =D13/K13 -> 1395.35 | H13: 16 | I13: 15 | J13: =K13*T13 -> 8624 | K13: 14 | L13: =I13*93 -> 1395 | M13: =I13-K13-N13 -> 1 | O13: =M13/I13*100 -> 6.6666667 | P13: =I13/H13*100 -> 93.75 | Q13: =K13/I13*100 -> 93.333333 | R13: =G13/K13 -> 0 | S13: =100-P13 -> 6.25 | T13: 616 | W13: V9 | X13: 778
A14: V7 | B14: 83132.63 | C14: =G14+J14+L14 -> 46029 | D14: =B14-C14 -> 37103.63 | E14: =D14/B14*100 -> 44.631849 | F14: =D14/K14 -> 426.47851 | H14: 89 | I14: 88 | J14: =K14*T14 -> 37845 | K14: 87 | L14: =I14*93 -> 8184 | M14: =I14-K14-N14 -> 1 | O14: =M14/I14*100 -> 1.1363636 | P14: =I14/H14*100 -> 98.876404 | Q14: =K14/I14*100 -> 98.863636 | R14: =G14/K14 -> 0 | S14: =100-P14 -> 1.1235955 | T14: 435 | W14: V10 | X14: 1009
A15: V8 | B15: 0 | C15: 0 | D15: 0 | E15: =D15/B15*100 -> #DIV/0! | F15: 0 | H15: 0 | I15: 0 | J15: 0 | K15: 0 | L15: =I15*93 -> 0 | M15: =I15-K15-N15 -> 0 | T15: 699
A16: V9 | B16: 1072812.1 | C16: =G16+J16+L16 -> 548095 | D16: =B16-C16 -> 524717.12 | E16: =D16/B16*100 -> 48.910439 | F16: =D16/K16 -> 839.54739 | H16: 670 | I16: 665 | J16: =K16*T16 -> 486250 | K16: 625 | L16: =I16*93 -> 61845 | M16: =I16-K16-N16 -> 39 | N16: 1 | O16: =M16/I16*100 -> 5.8646617 | P16: =I16/H16*100 -> 99.253731 | Q16: =K16/I16*100 -> 93.984962 | R16: =G16/K16 -> 0 | S16: =100-P16 -> 0.74626866 | T16: 778
A17: V9 P of 2 | B17: 33662.44 | C17: =G17+J17+L17 -> 19974 | D17: =B17-C17 -> 13688.44 | E17: =D17/B17*100 -> 40.663838 | F17: =D17/K17 -> 1140.7033 | H17: 14 | I17: 14 | J17: =K17*T17 -> 18672 | K17: 12 | L17: =I17*93 -> 1302 | M17: =I17-K17-N17 -> 2 | O17: =M17/I17*100 -> 14.285714 | P17: =I17/H17*100 -> 100 | Q17: =K17/I17*100 -> 85.714286 | R17: =G17/K17 -> 0 | T17: 1556
A18: V10 | B18: 98679.54 | C18: =G18+J18+L18 -> 63372 | D18: =B18-C18 -> 35307.54 | E18: =D18/B18*100 -> 35.780001 | F18: =D18/K18 -> 619.43053 | H18: 65 | I18: 63 | J18: =K18*T18 -> 57513 | K18: 57 | L18: =I18*93 -> 5859 | M18: =I18-K18-N18 -> 4 | N18: 2 | O18: =M18/I18*100 -> 6.3492063 | P18: =I18/H18*100 -> 96.923077 | Q18: =K18/I18*100 -> 90.47619 | R18: =G18/K18 -> 0 | S18: =100-P18 -> 3.0769231 | T18: 1009
A19: Busy Book | B19: 56466.36 | C19: =G19+J19+L19 -> 43497 | D19: =B19-C19 -> 12969.36 | E19: =D19/B19*100 -> 22.968295 | F19: =D19/K19 -> 102.93143 | H19: 129 | I19: 129 | J19: =K19*T19 -> 31500 | K19: 126 | L19: =I19*93 -> 11997 | M19: =I19-K19-N19 -> 3 | O19: =M19/I19*100 -> 2.3255814 | P19: =I19/H19*100 -> 100 | Q19: =K19/I19*100 -> 97.674419 | R19: =G19/K19 -> 0 | T19: 250
A20: Busy Book Pink | B20: 61001.78 | C20: =G20+J20+L20 -> 28254 | D20: =B20-C20 -> 32747.78 | E20: =D20/B20*100 -> 53.683319 | F20: =D20/K20 -> 467.82543 | H20: 78 | I20: 78 | J20: =K20*T20 -> 21000 | K20: 70 | L20: =I20*93 -> 7254 | M20: =I20-K20-N20 -> 8 | O20: =M20/I20*100 -> 10.25641 | P20: =I20/H20*100 -> 100 | Q20: =K20/I20*100 -> 89.74359 | R20: =G20/K20 -> 0 | T20: 300
A21: Busy Book Blue | B21: 6340.59 | C21: =G21+J21+L21 -> 2844 | D21: =B21-C21 -> 3496.59 | E21: =D21/B21*100 -> 55.14613 | F21: =D21/K21 -> 499.51286 | H21: 8 | I21: 8 | J21: =K21*T21 -> 2100 | K21: 7 | L21: =I21*93 -> 744 | M21: =I21-K21-N21 -> 1 | O21: =M21/I21*100 -> 12.5 | P21: =I21/H21*100 -> 100 | Q21: =K21/I21*100 -> 87.5 | R21: =G21/K21 -> 0 | T21: 300
A22: Human Book | B22: 140649.32 | C22: =G22+J22+L22 -> 78837 | D22: =B22-C22 -> 61812.32 | E22: =D22/B22*100 -> 43.947827 | F22: =D22/K22 -> 312.18343 | H22: 211 | I22: 209 | J22: =K22*T22 -> 59400 | K22: 198 | L22: =I22*93 -> 19437 | M22: =I22-K22-N22 -> 9 | N22: 2 | O22: =M22/I22*100 -> 4.3062201 | P22: =I22/H22*100 -> 99.052133 | Q22: =K22/I22*100 -> 94.736842 | R22: =G22/K22 -> 0 | S22: =100-P22 -> 0.9478673 | T22: 300
A23: V9-V3 Combo | B23: 116723.77 | C23: =G23+J23+L23 -> 61599 | D23: =B23-C23 -> 55124.77 | E23: =D23/B23*100 -> 47.226687 | F23: =D23/K23 -> 1378.1192 | H23: 44 | I23: 43 | J23: =K23*T23 -> 57600 | K23: 40 | L23: =I23*93 -> 3999 | M23: =I23-K23-N23 -> 2 | N23: 1 | O23: =M23/I23*100 -> 4.6511628 | P23: =I23/H23*100 -> 97.727273 | Q23: =K23/I23*100 -> 93.023256 | R23: =G23/K23 -> 0 | S23: =100-P23 -> 2.2727273 | T23: 1440
A24: V9-V10 Combo | B24: 153524.67 | C24: =G24+J24+L24 -> 99733 | D24: =B24-C24 -> 53791.67 | E24: =D24/B24*100 -> 35.037802 | F24: =D24/K24 -> 1014.9372 | H24: 54 | I24: 54 | J24: =K24*T24 -> 94711 | K24: 53 | L24: =I24*93 -> 5022 | M24: =I24-K24-N24 -> 1 | O24: =M24/I24*100 -> 1.8518519 | P24: =I24/H24*100 -> 100 | Q24: =K24/I24*100 -> 98.148148 | R24: =G24/K24 -> 0 | T24: 1787
A25: V7-V4 Combo | B25: 3648 | C25: =G25+J25+L25 -> 1424 | D25: =B25-C25 -> 2224 | E25: =D25/B25*100 -> 60.964912 | F25: =D25/K25 -> 1112 | H25: 2 | I25: 2 | J25: =K25*T25 -> 1238 | K25: 2 | L25: =I25*93 -> 186 | M25: =I25-K25-N25 -> 0 | P25: =I25/H25*100 -> 100 | Q25: =K25/I25*100 -> 100 | R25: =G25/K25 -> 0 | T25: 619
A26: V1-V4 Combo | B26: 78312.62 | C26: =G26+J26+L26 -> 32552 | D26: =B26-C26 -> 45760.62 | E26: =D26/B26*100 -> 58.433264 | F26: =D26/K26 -> 715.00969 | H26: 73 | I26: 72 | J26: =K26*T26 -> 25856 | K26: 64 | L26: =I26*93 -> 6696 | M26: =I26-K26-N26 -> 7 | N26: 1 | O26: =M26/I26*100 -> 9.7222222 | P26: =I26/H26*100 -> 98.630137 | Q26: =K26/I26*100 -> 88.888889 | R26: =G26/K26 -> 0 | S26: =100-P26 -> 1.369863 | T26: 404
A27: V1-V7 Combo | B27: 76267.21 | C27: =G27+J27+L27 -> 33191 | D27: =B27-C27 -> 43076.21 | E27: =D27/B27*100 -> 56.480642 | F27: =D27/K27 -> 979.00477 | H27: 47 | I27: 47 | J27: =K27*T27 -> 28820 | K27: 44 | L27: =I27*93 -> 4371 | M27: =I27-K27-N27 -> 2 | N27: 1 | O27: =M27/I27*100 -> 4.2553191 | P27: =I27/H27*100 -> 100 | Q27: =K27/I27*100 -> 93.617021 | R27: =G27/K27 -> 0 | T27: 655
A28: V6-V2 Combo | B28: 35495.91 | C28: =G28+J28+L28 -> 12690 | D28: =B28-C28 -> 22805.91 | E28: =D28/B28*100 -> 64.249402 | F28: =D28/K28 -> 1266.995 | H28: 19 | I28: 18 | J28: =K28*T28 -> 11016 | K28: 18 | L28: =I28*93 -> 1674 | M28: =I28-K28-N28 -> 0 | P28: =I28/H28*100 -> 94.736842 | Q28: =K28/I28*100 -> 100 | R28: =G28/K28 -> 0 | S28: =100-P28 -> 5.2631579 | T28: 612
A29: V6-V7 Combo | B29: 157668.17 | C29: =G29+J29+L29 -> 74126 | D29: =B29-C29 -> 83542.17 | E29: =D29/B29*100 -> 52.986072 | F29: =D29/K29 -> 949.34284 | H29: 97 | I29: 94 | J29: =K29*T29 -> 65384 | K29: 88 | L29: =I29*93 -> 8742 | M29: =I29-K29-N29 -> 5 | N29: 1 | O29: =M29/I29*100 -> 5.3191489 | P29: =I29/H29*100 -> 96.907216 | Q29: =K29/I29*100 -> 93.617021 | R29: =G29/K29 -> 0 | S29: =100-P29 -> 3.0927835 | T29: 743
A30: V2-V7 Combo | B30: 78961.22 | C30: =G30+J30+L30 -> 35962 | D30: =B30-C30 -> 42999.22 | E30: =D30/B30*100 -> 54.456124 | F30: =D30/K30 -> 999.98186 | H30: 46 | I30: 45 | J30: =K30*T30 -> 31777 | K30: 43 | L30: =I30*93 -> 4185 | M30: =I30-K30-N30 -> 2 | O30: =M30/I30*100 -> 4.4444444 | P30: =I30/H30*100 -> 97.826087 | Q30: =K30/I30*100 -> 95.555556 | R30: =G30/K30 -> 0 | S30: =100-P30 -> 2.173913 | T30: 739
A31: V1-V2 Combo | B31: 46484.13 | C31: =G31+J31+L31 -> 14901 | D31: =B31-C31 -> 31583.13 | E31: =D31/B31*100 -> 67.943898 | F31: =D31/K31 -> 1315.9637 | H31: 25 | I31: 25 | J31: =K31*T31 -> 12576 | K31: 24 | L31: =I31*93 -> 2325 | M31: =I31-K31-N31 -> 1 | O31: =M31/I31*100 -> 4 | P31: =I31/H31*100 -> 100 | Q31: =K31/I31*100 -> 96 | R31: =G31/K31 -> 0 | T31: 524
A32: V6-V4 Combo | B32: 5497 | C32: =G32+J32+L32 -> 1755 | D32: =B32-C32 -> 3742 | E32: =D32/B32*100 -> 68.073495 | F32: =D32/K32 -> 1247.3333 | H32: 3 | I32: 3 | J32: =K32*T32 -> 1476 | K32: 3 | L32: =I32*93 -> 279 | M32: =I32-K32-N32 -> 0 | P32: =I32/H32*100 -> 100 | Q32: =K32/I32*100 -> 100 | R32: =G32/K32 -> 0 | T32: 492
A33: V2-V4 Combo | B33: 21095.32 | C33: =G33+J33+L33 -> 8134 | D33: =B33-C33 -> 12961.32 | E33: =D33/B33*100 -> 61.441685 | F33: =D33/K33 -> 925.80857 | H33: 14 | I33: 14 | J33: =K33*T33 -> 6832 | K33: 14 | L33: =I33*93 -> 1302 | M33: =I33-K33-N33 -> 0 | P33: =I33/H33*100 -> 100 | Q33: =K33/I33*100 -> 100 | R33: =G33/K33 -> 0 | T33: 488
A34: Total | B34: =sum(B4:B33)+80000 -> 5745638.2 | D34: =SUM(D4:D33) -> 3010627.1 | G34: 3292687 | H34: =SUM(H4:H33) -> 5697 | I34: =SUM(I4:I33) -> 5641 | J34: =SUM(J4:J33)+(250*70) -> 2147898 | K34: =SUM(K4:K33) -> 5264 | L34: =SUM(L4:L33) -> 524613 | M34: =SUM(M4:M33) -> 343 | N34: =SUM(N4:N33) -> 34 | O34: =AVERAGE(O4:O33) -> 6.2184303 | P34: =AVERAGE(P4:P33) -> 98.713919 | Q34: =AVERAGE(Q4:Q33) -> 94.149544 | R34: =SUM(R4:R33) -> 0 | S34: =AVERAGE(S4:S33) -> 2.4006854
D36: Blended
A37: Total Units Sold | B37: =K34 -> 5264 | D37: /pc | E37: -41
A38: Total Revenue | B38: =B34 -> 5745638.2 | D38: COGS | E38: =B39/B37 -> 408.03533 | F38: 0.37
A39: COGS | B39: =J34 -> 2147898 | D39: CAC | E39: =B41/B37 -> 625.51045 | F39: 0.57
A40: Logistics | B40: =L34 -> 524613 | D40: Logistics | E40: 99 | F40: 0.09
A41: Marketing | B41: =G34 -> 3292687 | D41: AOV | E41: =B38/B37 -> 1091.4966
A42: P&L | B42: =B38-(B39+B40+B41) -> -219559.85
A43: P&L % | B43: =B42/B38 -> -0.03821331
A46: July | B46: Amazon
B48: Total revenue | C48: Total expense | D48: Total P/L | E48: Profit % | F48: P/pcs | G48: Total orders | H48: Product expense | I48: Delivered | J48: Return | K48: Amazon expense | L48: RTO% | M48: Only Ad spend | N48: Return GMV
A49: V1 | B49: =1122761+1294+18190 -> 1142245 | C49: =K49+H49 -> 616920 | D49: =B49-C49 -> 525325 | E49: =D49/B49*100 -> 45.990571 | F49: =D49/I49 -> 412.66693 | G49: =1352+1+11 -> 1364 | H49: =220*I49 -> 280060 | I49: =1262+1+10 -> 1273 | J49: =G49-I49 -> 91 | K49: =333539+217+3104 -> 336860 | L49: =J49/G49*100 -> 6.6715543 | N49: =J49*999 -> 90909 | O49: =B49/M49 -> #DIV/0! | P49: =B49/B66*100 -> 28.094076
A50: V2 | B50: =2898+1035189 -> 1038087 | C50: =K50+H50 -> 509612.55 | D50: =B50-C50 -> 528474.45 | E50: =D50/B50*100 -> 50.908493 | F50: =D50/I50 -> 545.38127 | G50: =1048+2 -> 1050 | H50: =304*I50 -> 294576 | I50: =967+2 -> 969 | J50: =G50-I50 -> 81 | K50: =461.28+214575.27 -> 215036.55 | L50: =J50/G50*100 -> 7.7142857 | N50: =J50*1119 -> 90639 | O50: =B50/M50 -> #DIV/0! | P50: =B50/B66*100 -> 25.532259
A51: V3 | B51: =86544 -> 86544 | C51: =K51+H51 -> 61310 | D51: =B51-C51 -> 25234 | E51: =D51/B51*100 -> 29.157423 | F51: =D51/I51 -> 371.08824 | G51: 77 | H51: =662*I51 -> 45016 | I51: 68 | J51: =G51-I51 -> 9 | K51: 16294 | L51: =J51/G51*100 -> 11.688312 | N51: =J51*1799 -> 16191 | O51: =B51/M51 -> #DIV/0! | P51: =B51/B66*100 -> 2.1285921
A52: V4 | B52: =1293+288127+1196+5990 -> 296606 | C52: =K52+H52 -> 218222 | D52: =B52-C52 -> 78384 | E52: =D52/B52*100 -> 26.426977 | F52: =D52/I52 -> 115.10132 | G52: =712+2+7+1 -> 722 | H52: =184*I52 -> 125304 | I52: =672+2+7 -> 681 | J52: =G52-I52 -> 41 | K52: =91467+446+740+265 -> 92918 | L52: =J52/G52*100 -> 5.6786704 | N52: =J52*499 -> 20459 | O52: =B52/M52 -> #DIV/0! | P52: =B52/B66*100 -> 7.29517
A53: V5 | B53: 0 | C53: =K53+H53 -> 0 | D53: =B53-C53 -> 0 | E53: - | F53: - | G53: 0 | H53: =250*I53 -> 0 | I53: 0 | J53: =G53-I53 -> 0 | K53: 0 | L53: - | N53: =J53*1049 -> 0 | O53: =B53/M53 -> #DIV/0! | P53: =B53/B66*100 -> 0
A54: V6 | B54: =271667+2896 -> 274563 | C54: =K54+H54 -> 208263 | D54: =B54-C54 -> 66300 | E54: =D54/B54*100 -> 24.147463 | F54: =D54/I54 -> 254.02299 | G54: =296+2 -> 298 | H54: =308*I54 -> 80388 | I54: =259+2 -> 261 | J54: =G54-I54 -> 37 | K54: =126866+1009 -> 127875 | L54: =J54/G54*100 -> 12.416107 | N54: =J54*1249 -> 46213 | O54: =B54/M54 -> #DIV/0! | P54: =B54/B66*100 -> 6.7530116
A55: V7 | B55: =8221+54336 -> 62557 | C55: =K55+H55 -> 76163 | D55: =B55-C55 -> -13606 | E55: =D55/B55*100 -> -21.749764 | F55: =D55/I55 -> -238.70175 | G55: =52+11 -> 63 | H55: =435*I55 -> 24795 | I55: =8+49 -> 57 | J55: =G55-I55 -> 6 | K55: =37903+13465 -> 51368 | L55: =J55/G55*100 -> 9.5238095 | N55: =J55*1349 -> 8094 | O55: =B55/M55 -> #DIV/0! | P55: =B55/B66*100 -> 1.5386201
A56: V8 | B56: 0 | C56: =K56+H56 -> 0 | D56: =B56-C56 -> 0 | E56: - | F56: - | G56: 0 | H56: =800*I56 -> 0 | I56: 0 | J56: =G56-I56 -> 0 | K56: 0 | L56: - | N56: =J56*1899 -> 0 | O56: =B56/M56 -> #DIV/0! | P56: =B56/B66*100 -> 0
A57: V9 | B57: =578784 -> 578784 | C57: =K57+H57 -> 397120 | D57: =B57-C57 -> 181664 | E57: =D57/B57*100 -> 31.387184 | F57: =D57/I57 -> 517.56125 | G57: 397 | H57: =778*I57 -> 273078 | I57: 351 | J57: =G57-I57 -> 46 | K57: =124042 -> 124042 | L57: =J57/G57*100 -> 11.586902 | N57: =J57*1999 -> 91954 | O57: =B57/M57 -> #DIV/0! | P57: =B57/B66*100 -> 14.235476
A58: BB | B58: =32076 -> 32076 | C58: =K58+H58 -> 13386 | D58: =B58-C58 -> 18690 | E58: =D58/B58*100 -> 58.267864 | F58: =D58/I58 -> 6230 | G58: =66 -> 66 | H58: =200*I58 -> 600 | I58: =3 -> 3 | J58: =G58-I58 -> 63 | K58: =12786 -> 12786 | L58: =J58/G58*100 -> 95.454545 | N58: =J58*599 -> 37737 | O58: =B58/M58 -> #DIV/0! | P58: =B58/B66*100 -> 0.78892495
A59: V1V4 | B59: 0 | C59: =K59+H59 -> 0 | D59: =B59-C59 -> 0 | E59: - | F59: - | G59: 0 | H59: =(270+220)*I59 -> 0 | I59: 0 | J59: =G59-I59 -> 0 | K59: 0 | L59: - | O59: =B59/M59 -> #DIV/0! | P59: =B59/B66*100 -> 0
A60: V1V2 | B60: =2249 -> 2249 | C60: =K60+H60 -> 1419 | D60: =B60-C60 -> 830 | E60: =D60/B60*100 -> 36.905291 | F60: =D60/I60 -> #DIV/0! | G60: 3 | H60: =(270+350)*I60 -> 0 | I60: 0 | J60: =G60-I60 -> 3 | K60: =1419 -> 1419 | L60: =J60/G60*100 -> 100 | N60: =J60*2199 -> 6597 | O60: =B60/M60 -> #DIV/0! | P60: =B60/B66*100 -> 0.055315258
A61: V1V6 | B61: =1999 -> 1999 | C61: =K61+H61 -> 939 | D61: =B61-C61 -> 1060 | E61: =D61/B61*100 -> 53.026513 | F61: =D61/I61 -> 1060 | G61: 1 | H61: =(270+320)*I61 -> 590 | I61: 1 | J61: =G61-I61 -> 0 | K61: 349 | L61: =J61/G61*100 -> 0 | N61: =J61*999 -> 0 | O61: =B61/M61 -> #DIV/0! | P61: =B61/B66*100 -> 0.049166385
A62: V2V4 | B62: =49214 -> 49214 | C62: =K62+H62 -> 30494 | D62: =B62-C62 -> 18720 | E62: =D62/B62*100 -> 38.037957 | F62: =D62/I62 -> 480 | G62: 43 | H62: =(350+220)*I62 -> 22230 | I62: 39 | J62: =G62-I62 -> 4 | K62: =8264 -> 8264 | L62: =J62/G62*100 -> 9.3023256 | N62: =J62*1499 -> 5996 | O62: =B62/M62 -> #DIV/0! | P62: =B62/B66*100 -> 1.2104425
A63: V2V6 | B63: =15144 -> 15144 | C63: =K63+H63 -> 15878 | D63: =B63-C63 -> -734 | E63: =D63/B63*100 -> -4.846804 | F63: =D63/I63 -> -104.85714 | G63: 8 | H63: =(350+320)*I63 -> 4690 | I63: 7 | J63: =G63-I63 -> 1 | K63: =11188 -> 11188 | L63: =J63/G63*100 -> 12.5 | N63: =J63*999 -> 999 | O63: =B63/M63 -> #DIV/0! | P63: =B63/B66*100 -> 0.3724741
A64: BB's | B64: =160227+242559 -> 402786 | C64: =K64+H64 -> 272608 | D64: =B64-C64 -> 130178 | E64: =D64/B64*100 -> 32.319395 | F64: =D64/I64 -> 295.18821 | G64: =180+275 -> 455 | H64: =(330)*I64 -> 145530 | I64: =175+266 -> 441 | J64: =G64-I64 -> 14 | K64: =73941+53137 -> 127078 | L64: =J64/G64*100 -> 3.0769231 | N64: =J64*999 -> 13986 | O64: =B64/M64 -> #DIV/0! | P64: =B64/B66*100 -> 9.9067191
A65: V10 | B65: =82932 -> 82932 | C65: =K65+H65 -> 44330 | D65: =B65-C65 -> 38602 | E65: =D65/B65*100 -> 46.546568 | F65: =D65/I65 -> 756.90196 | G65: 57 | H65: =(330)*I65 -> 16830 | I65: 51 | J65: =G65-I65 -> 6 | K65: =27500 -> 27500 | L65: =J65/G65*100 -> 10.526316 | N65: =J65*999 -> 5994 | O65: =B65/M65 -> #DIV/0!
A66: Total | B66: =SUM(B49:B65) -> 4065786 | C66: =SUM(C49:C65) -> 2466664.5 | D66: =SUM(D49:D65) -> 1599121.4 | G66: =SUM(G49:G65) -> 4604 | H66: =SUM(H49:H65) -> 1313687 | I66: =SUM(I49:I65) -> 4202 | J66: =SUM(J49:J65) -> 402 | K66: =SUM(K49:K65) -> 1152977.6
A69: Total Revenue | B69: =B66 -> 4065786
A70: COGS | B70: =H66 -> 1313687 | D70: Blended | G70: 0.4 | H70: =B71*G70 -> 184476.41
A71: Amazon Ex | B71: 461191.02 | D71: COGS | E71: =B70/I66 -> 312.63375 | G71: 0.3 | H71: =B71*G71 -> 138357.31
A72: Logi | B72: 345893.27 | D72: CAC | E72: =B72/I66 -> 82.316341 | G72: 0.3 | H72: =B71*G72 -> 138357.31
A73: Marketing | B73: 345893.27
A74: Net P&L | B74: =B69-SUM(B70:B73) -> 1599121.4 | D74: Commisions | E74: =B71/I66 -> 109.75512
A75: P&L % | B75: =B74/B69*100 -> 39.331176 | D75: AOV | E75: =B69/I66 -> 967.58353
A82: July | B82: Flipkart
B84: Total revenue | C84: Total expense | D84: Total P/L | E84: Profit % | F84: P/pcs | G84: Total orders | H84: Product expense | I84: Delivered | J84: Return | K84: Flipkart expenses | L84: RTO% | M84: Only Ad spend
A85: V1 | B85: =12758 -> 12758 | C85: =K85+H85 -> 7069.07 | D85: =B85-C85 -> 5688.93 | E85: =D85/B85*100 -> 44.59108 | F85: =D85/I85 -> 316.05167 | G85: 23 | H85: =270*I85 -> 4860 | I85: 18 | J85: =G85-I85 -> 5 | K85: =2209.07 -> 2209.07 | L85: =J85/G85*100 -> 21.73913
A86: V2 | B86: =38437 -> 38437 | C86: =K86+H86 -> 21733.85 | D86: =B86-C86 -> 16703.15 | E86: =D86/B86*100 -> 43.455915 | F86: =D86/I86 -> 388.44535 | G86: 64 | H86: =350*I86 -> 15050 | I86: 43 | J86: =G86-I86 -> 21 | K86: =6683.85 -> 6683.85 | L86: =J86/G86*100 -> 32.8125
A87: V3 | B87: 0 | C87: =K87+H87 -> 0 | D87: =B87-C87 -> 0 | E87: =D87/B87*100 -> #DIV/0! | F87: =D87/I87 -> #DIV/0! | G87: 0 | H87: =980*I87 -> 0 | I87: 0 | J87: =G87-I87 -> 0 | K87: 0 | L87: =J87/G87*100 -> #DIV/0!
A88: V4 | B88: =47492+1911 -> 49403 | C88: =K88+H88 -> 29920 | D88: =B88-C88 -> 19483 | E88: =D88/B88*100 -> 39.436876 | F88: =D88/I88 -> 143.25735 | G88: 178 | H88: =220*I88 -> 29920 | I88: 136 | J88: =G88-I88 -> 42 | K88: 0 | L88: =J88/G88*100 -> 23.595506
A89: V5 | B89: 0 | C89: =K89+H89 -> 0 | D89: =B89-C89 -> 0 | E89: =D89/B89*100 -> #DIV/0! | F89: =D89/I89 -> #DIV/0! | G89: 0 | H89: =270*I89 -> 0 | I89: 0 | J89: =G89-I89 -> 0 | K89: 0 | L89: =J89/G89*100 -> #DIV/0!
A90: V6 | B90: =17384 -> 17384 | C90: =K90+H90 -> 8780.46 | D90: =B90-C90 -> 8603.54 | E90: =D90/B90*100 -> 49.491141 | F90: =D90/I90 -> 452.81789 | G90: 23 | H90: =320*I90 -> 6080 | I90: 19 | J90: =G90-I90 -> 4 | K90: =2700.46 -> 2700.46 | L90: =J90/G90*100 -> 17.391304
A91: V7 | B91: =4073 -> 4073 | C91: =K91+H91 -> 2673.63 | D91: =B91-C91 -> 1399.37 | E91: =D91/B91*100 -> 34.357231 | F91: =D91/I91 -> 349.8425 | G91: 8 | H91: =470*I91 -> 1880 | I91: 4 | J91: =G91-I91 -> 4 | K91: =793.63 -> 793.63 | L91: =J91/G91*100 -> 50
A92: Wooden cal | B92: =496 -> 496 | C92: =K92+H92 -> 273.03 | D92: =B92-C92 -> 222.97 | E92: =D92/B92*100 -> 44.953629 | F92: =D92/I92 -> 222.97 | G92: 2 | H92: =200*I92 -> 200 | I92: 1 | J92: =G92-I92 -> 1 | K92: =73.03 -> 73.03 | L92: =J92/G92*100 -> 50
A93: V9 | B93: =15390 -> 15390 | C93: =K93+H93 -> 12542.3 | D93: =B93-C93 -> 2847.7 | E93: =D93/B93*100 -> 18.503574 | F93: =D93/I93 -> 316.41111 | G93: 20 | H93: =1000*I93 -> 9000 | I93: 9 | J93: =G93-I93 -> 11 | K93: =3542.3 -> 3542.3 | L93: =J93/G93*100 -> 55
A94: V4V2 | B94: =8462 -> 8462 | C94: =K94+H94 -> 6147.27 | D94: =B94-C94 -> 2314.73 | E94: =D94/B94*100 -> 27.354408 | F94: =D94/I94 -> 257.19222 | G94: 13 | H94: =(220+350)*I94 -> 5130 | I94: 9 | J94: =G94-I94 -> 4 | K94: =1017.27 -> 1017.27 | L94: =J94/G94*100 -> 30.769231
A95: V1V4 | B95: =6339 -> 6339 | C95: =K95+H95 -> 3987 | D95: =B95-C95 -> 2352 | E95: =D95/B95*100 -> 37.103644 | F95: =D95/I95 -> 392 | G95: 8 | H95: =(270+220)*I95 -> 2940 | I95: 6 | J95: =G95-I95 -> 2 | K95: =1047 -> 1047 | L95: =J95/G95*100 -> 25
A96: V6V2 | B96: =5183 -> 5183 | C96: =K96+H96 -> 2618.4 | D96: =B96-C96 -> 2564.6 | E96: =D96/B96*100 -> 49.480996 | F96: =D96/I96 -> 854.86667 | G96: 4 | H96: =(320+350)*I96 -> 2010 | I96: 3 | J96: =G96-I96 -> 1 | K96: =608.4 -> 608.4 | L96: =J96/G96*100 -> 25
A97: V1V2 | B97: =14722 -> 14722 | C97: =K97+H97 -> 7294.2 | D97: =B97-C97 -> 7427.8 | E97: =D97/B97*100 -> 50.453743 | F97: =D97/I97 -> 825.31111 | G97: 9 | H97: =(270+350)*I97 -> 5580 | I97: 9 | J97: =G97-I97 -> 0 | K97: =1714.2 -> 1714.2 | L97: =J97/G97*100 -> 0
B98: =SUM(B85:B97) -> 172647 | C98: =SUM(C85:C97) -> 103039.21 | D98: =SUM(D85:D97) -> 69607.79 | G98: =SUM(G85:G97) -> 352 | H98: =SUM(H85:H97) -> 82650 | I98: =SUM(I85:I97) -> 257 | J98: =SUM(J85:J97) -> 95 | K98: =SUM(K85:K97) -> 20389.21 | M98: 12275
A101: Total Revenue | B101: =B98 -> 172647
A102: COGS | B102: =H98 -> 82650
A103: Flipkart Ex | B103: =K98-B104 -> 8114.21 | D103: COGS | E103: =B102/I98 -> 321.59533
A104: Marketing | B104: =M98 -> 12275 | D104: CAC | E104: =B104/I98 -> 47.762646
A105: Net P&L | B105: =B101-SUM(B102:B104) -> 69607.79 | D105: Commisions | E105: =B103/I98 -> 31.572802
A106: P&L % | B106: =B105/B101*100 -> 40.317984 | D106: AOV | E106: =B101/I98 -> 671.77821
A111: July | B111: Blinkit
B113: Total revenue | C113: Total expense | D113: Total P/L | E113: Profit % | F113: P/pcs | G113: Product exp | H113: Total orders | I113: Blinkit exp | J113: Ads | K113: Logistics
A114: V1 | B114: =689*H114 -> 112996 | C114: =J114+G114+I114+K114 -> 41820 | D114: =B114-C114 -> 71176 | E114: =D114/B114*100 -> 62.98984 | F114: =D114/H114 -> 434 | G114: =235*H114 -> 38540 | H114: 164 | I114: 0 | J114: 0 | K114: =20*H114 -> 3280 | M114: 59209
A115: V4 | B115: =359*H115 -> 61030 | C115: =J115+G115+I115+K115 -> 37230 | D115: =B115-C115 -> 23800 | E115: =D115/B115*100 -> 38.997214 | F115: =D115/H115 -> 140 | G115: =199*H115 -> 33830 | H115: 170 | I115: 0 | J115: 0 | K115: =20*H115 -> 3400
A116: V2 | B116: =781*H116 -> 106216 | C116: =J116+G116+I116+K116 -> 46104 | D116: =B116-C116 -> 60112 | E116: =D116/B116*100 -> 56.59411 | F116: =D116/H116 -> 442 | G116: =319*H116 -> 43384 | H116: 136 | I116: 0 | J116: =L116%*M116 -> 0 | K116: =20*H116 -> 2720
A117: V6 | B117: =843*H117 -> 85143 | C117: =J117+G117+I117+K117 -> 34643 | D117: =B117-C117 -> 50500 | E117: =D117/B117*100 -> 59.311981 | F117: =D117/H117 -> 500 | G117: =323*H117 -> 32623 | H117: 101 | I117: 0 | J117: =L117%*M117 -> 0 | K117: =20*H117 -> 2020
B118: =SUM(B114:B117) -> 365385 | C118: =SUM(C114:C117) -> 159797 | D118: =SUM(D114:D117) -> 205588 | E118: =SUM(E114:E117) -> 217.89315 | F118: =SUM(F114:F117) -> 1516 | G118: =SUM(G114:G117) -> 148377 | H118: =SUM(H114:H117) -> 571 | I118: =134501 -> 134501 | J118: =SUM(J114:J117) -> 0 | K118: =SUM(K114:K117) -> 11420
A121: Total Revenue | B121: =B118 -> 365385 | D121: Blended | E121: 125/pcs
A122: COGS | B122: =G118 -> 148377 | D122: COGS | E122: =B122/H118 -> 259.85464
A123: Logitics | B123: =K118 -> 11420 | D123: CAC | E123: =B124/H118 -> 235.55342
...

Sheet Aug 25
A1: August | B1: Shopify
A3: Products | B3: Total Dilivered Revenue | C3: Total expense | D3: Total P/L | E3: Profit % | F3: P/pcs | G3: Ad spent | H3: Total orders | I3: Shipped | J3: Total COGS | K3: Delivered | L3: Shipping charges | M3: RTO | N3: In-transit | O3: RTO% | P3: Shipped% | Q3: Delivered % | R3: CPD | S3: Cancellation % | T3: COGS/Unit
A4: V1 | B4: 942559.2 | C4: =G4+J4+L4 -> 345301 | D4: =B4-C4 -> 597258.2 | E4: =D4/B4*100 -> 63.36559 | F4: =D4/K4 -> 557.14384 | H4: 1205 | I4: 1177 | J4: =K4*T4 -> 235840 | K4: 1072 | L4: =I4*93 -> 109461 | M4: =I4-K4-N4 -> 92 | N4: 13 | O4: =M4/I4*100 -> 7.8164826 | P4: =I4/H4*100 -> 97.676349 | Q4: =K4/I4*100 -> 91.079014 | R4: =G4/K4 -> 0 | S4: =(I4-H4)/H4 -> -0.023236515 | T4: 220 | W4: Products | X4: Total Cost
A5: V1- P of 2 | B5: 63231.48 | C5: =G5+J5+L5 -> 24357 | D5: =B5-C5 -> 38874.48 | E5: =D5/B5*100 -> 61.47963 | F5: =D5/K5 -> 863.87733 | H5: 52 | I5: 49 | J5: =K5*T5 -> 19800 | K5: 45 | L5: =I5*93 -> 4557 | M5: =I5-K5-N5 -> 4 | O5: =M5/I5*100 -> 8.1632653 | P5: =I5/H5*100 -> 94.230769 | Q5: =K5/I5*100 -> 91.836735 | R5: =G5/K5 -> 0 | S5: =(I5-H5)/H5 -> -0.057692308 | T5: 440 | W5: V1 | X5: 220
A6: V2 | B6: 1349421.9 | C6: =G6+J6+L6 -> 515558 | D6: =B6-C6 -> 833863.86 | E6: =D6/B6*100 -> 61.794157 | F6: =D6/K6 -> 663.90435 | H6: 1466 | I6: 1438 | J6: =K6*T6 -> 381824 | K6: 1256 | L6: =I6*93 -> 133734 | M6: =I6-K6-N6 -> 170 | N6: 12 | O6: =M6/I6*100 -> 11.821975 | P6: =I6/H6*100 -> 98.090041 | Q6: =K6/I6*100 -> 87.343533 | R6: =G6/K6 -> 0 | S6: =(I6-H6)/H6 -> -0.019099591 | T6: 304 | W6: V2 | X6: 304
A7: V2- P of 2 | B7: 53423.07 | C7: =G7+J7+L7 -> 19814 | D7: =B7-C7 -> 33609.07 | E7: =D7/B7*100 -> 62.911154 | F7: =D7/K7 -> 1200.3239 | H7: 30 | I7: 30 | J7: =K7*T7 -> 17024 | K7: 28 | L7: =I7*93 -> 2790 | M7: =I7-K7-N7 -> 2 | O7: =M7/I7*100 -> 6.6666667 | P7: =I7/H7*100 -> 100 | Q7: =K7/I7*100 -> 93.333333 | R7: =G7/K7 -> 0 | S7: =(I7-H7)/H7 -> 0 | T7: 608 | W7: V3 | X7: 662
A8: V3 | B8: 299646.27 | C8: =G8+J8+L8 -> 165208 | D8: =B8-C8 -> 134438.27 | E8: =D8/B8*100 -> 44.865658 | F8: =D8/K8 -> 625.29428 | H8: 309 | I8: 246 | J8: =K8*T8 -> 142330 | K8: 215 | L8: =I8*93 -> 22878 | M8: =I8-K8-N8 -> 29 | N8: 2 | O8: =M8/I8*100 -> 11.788618 | P8: =I8/H8*100 -> 79.61165 | Q8: =K8/I8*100 -> 87.398374 | R8: =G8/K8 -> 0 | S8: =(I8-H8)/H8 -> -0.2038835 | T8: 662 | W8: V4 | X8: 184
A9: V4 | B9: 100529.77 | C9: =G9+J9+L9 -> 57446 | D9: =B9-C9 -> 43083.77 | E9: =D9/B9*100 -> 42.856728 | F9: =D9/K9 -> 215.41885 | H9: 227 | I9: 222 | J9: =K9*T9 -> 36800 | K9: 200 | L9: =I9*93 -> 20646 | M9: =I9-K9-N9 -> 21 | N9: 1 | O9: =M9/I9*100 -> 9.4594595 | P9: =I9/H9*100 -> 97.797357 | Q9: =K9/I9*100 -> 90.09009 | R9: =G9/K9 -> 0 | S9: =(I9-H9)/H9 -> -0.022026432 | T9: 184 | W9: V5 | X9: 206
A10: V4- P of 2 | B10: 25519.54 | C10: =G10+J10+L10 -> 15035 | D10: =B10-C10 -> 10484.54 | E10: =D10/B10*100 -> 41.084361 | F10: =D10/K10 -> 338.21097 | H10: 44 | I10: 39 | J10: =K10*T10 -> 11408 | K10: 31 | L10: =I10*93 -> 3627 | M10: =I10-K10-N10 -> 8 | O10: =M10/I10*100 -> 20.512821 | P10: =I10/H10*100 -> 88.636364 | Q10: =K10/I10*100 -> 79.487179 | R10: =G10/K10 -> 0 | S10: =(I10-H10)/H10 -> -0.11363636 | T10: 368 | W10: V6 | X10: 308
A11: V4- P of 3 | B11: 1170.23 | C11: =G11+J11+L11 -> 461 | D11: =B11-C11 -> 709.23 | E11: =D11/B11*100 -> 60.606035 | F11: =D11/K11 -> 709.23 | H11: 1 | I11: 1 | J11: =K11*T11 -> 368 | K11: 1 | L11: =I11*93 -> 93 | M11: =I11-K11-N11 -> 0 | O11: =M11/I11*100 -> 0 | P11: =I11/H11*100 -> 100 | Q11: =K11/I11*100 -> 100 | R11: =G11/K11 -> 0 | S11: =(I11-H11)/H11 -> 0 | T11: 368
A12: V5 | B12: 0 | C12: 0 | D12: 0 | E12: 0 | F12: 0 | H12: 0 | I12: 0 | J12: 0 | K12: 0 | L12: =I12*93 -> 0 | M12: =I12-K12-N12 -> 0 | S12: =(I12-H12)/H12 -> #DIV/0! | T12: 206 | W12: V7 | X12: 435
A13: V6 | B13: 1288854.1 | C13: =G13+J13+L13 -> 493116 | D13: =B13-C13 -> 795738.05 | E13: =D13/B13*100 -> 61.739966 | F13: =D13/K13 -> 666.44728 | H13: 1367 | I13: 1348 | J13: =K13*T13 -> 367752 | K13: 1194 | L13: =I13*93 -> 125364 | M13: =I13-K13-N13 -> 143 | N13: 11 | O13: =M13/I13*100 -> 10.608309 | P13: =I13/H13*100 -> 98.610095 | Q13: =K13/I13*100 -> 88.575668 | R13: =G13/K13 -> 0 | S13: =(I13-H13)/H13 -> -0.013899049 | T13: 308 | W13: V8 | X13: 699
A14: V6- P of 2 | B14: 68710.27 | C14: =G14+J14+L14 -> 27965 | D14: =B14-C14 -> 40745.27 | E14: =D14/B14*100 -> 59.300116 | F14: =D14/K14 -> 1072.2439 | H14: 49 | I14: 49 | J14: =K14*T14 -> 23408 | K14: 38 | L14: =I14*93 -> 4557 | M14: =I14-K14-N14 -> 11 | O14: =M14/I14*100 -> 22.44898 | P14: =I14/H14*100 -> 100 | Q14: =K14/I14*100 -> 77.55102 | R14: =G14/K14 -> 0 | S14: =(I14-H14)/H14 -> 0 | T14: 616 | W14: V9 | X14: 778
A15: V7 | B15: 81985.44 | C15: =G15+J15+L15 -> 39693 | D15: =B15-C15 -> 42292.44 | E15: =D15/B15*100 -> 51.585306 | F15: =D15/K15 -> 563.8992 | H15: 84 | I15: 76 | J15: =K15*T15 -> 32625 | K15: 75 | L15: =I15*93 -> 7068 | M15: =I15-K15-N15 -> 1 | O15: =M15/I15*100 -> 1.3157895 | P15: =I15/H15*100 -> 90.47619 | Q15: =K15/I15*100 -> 98.684211 | R15: =G15/K15 -> 0 | S15: =(I15-H15)/H15 -> -0.095238095 | T15: 435 | W15: V10 | X15: 1009
A16: V8 | B16: 78328.33 | C16: 0 | D16: 0 | E16: =D16/B16*100 -> 0 | F16: 0 | H16: 65 | I16: 59 | J16: 0 | K16: 55 | L16: =I16*93 -> 5487 | M16: =I16-K16-N16 -> 4 | S16: =(I16-H16)/H16 -> -0.092307692 | T16: 699
A17: V9 | B17: 1219942.1 | C17: =G17+J17+L17 -> 622983 | D17: =B17-C17 -> 596959.15 | E17: =D17/B17*100 -> 48.933398 | F17: =D17/K17 -> 846.75057 | H17: 865 | I17: 801 | J17: =K17*T17 -> 548490 | K17: 705 | L17: =I17*93 -> 74493 | M17: =I17-K17-N17 -> 91 | N17: 5 | O17: =M17/I17*100 -> 11.360799 | P17: =I17/H17*100 -> 92.601156 | Q17: =K17/I17*100 -> 88.014981 | R17: =G17/K17 -> 0 | S17: =(I17-H17)/H17 -> -0.073988439 | T17: 778
A18: V9 P of 2 | B18: 45827.25 | C18: =G18+J18+L18 -> 29868 | D18: =B18-C18 -> 15959.25 | E18: =D18/B18*100 -> 34.824804 | F18: =D18/K18 -> 886.625 | H18: 28 | I18: 20 | J18: =K18*T18 -> 28008 | K18: 18 | L18: =I18*93 -> 1860 | M18: =I18-K18-N18 -> 2 | O18: =M18/I18*100 -> 10 | P18: =I18/H18*100 -> 71.428571 | Q18: =K18/I18*100 -> 90 | R18: =G18/K18 -> 0 | S18: =(I18-H18)/H18 -> -0.28571429 | T18: 1556
A19: V10 | B19: 149456.29 | C19: =G19+J19+L19 -> 110479 | D19: =B19-C19 -> 38977.29 | E19: =D19/B19*100 -> 26.079391 | F19: =D19/K19 -> 389.7729 | H19: 123 | I19: 103 | J19: =K19*T19 -> 100900 | K19: 100 | L19: =I19*93 -> 9579 | M19: =I19-K19-N19 -> 3 | O19: =M19/I19*100 -> 2.9126214 | P19: =I19/H19*100 -> 83.739837 | Q19: =K19/I19*100 -> 97.087379 | R19: =G19/K19 -> 0 | S19: =(I19-H19)/H19 -> -0.16260163 | T19: 1009
A20: Busy Book | B20: 0 | C20: 0 | D20: 0 | E20: 0 | F20: 0 | H20: 0 | I20: 0 | J20: 0 | K20: 0 | L20: =I20*93 -> 0 | M20: =I20-K20-N20 -> 0 | O20: 0 | P20: 0 | Q20: 0 | R20: 0 | S20: =(I20-H20)/H20 -> #DIV/0! | T20: 250
A21: Busy Book Pink | B21: 120438.63 | C21: =G21+J21+L21 -> 58866 | D21: =B21-C21 -> 61572.63 | E21: =D21/B21*100 -> 51.123655 | F21: =D21/K21 -> 421.73034 | H21: 185 | I21: 162 | J21: =K21*T21 -> 43800 | K21: 146 | L21: =I21*93 -> 15066 | M21: =I21-K21-N21 -> 16 | O21: =M21/I21*100 -> 9.8765432 | P21: =I21/H21*100 -> 87.567568 | Q21: =K21/I21*100 -> 90.123457 | R21: =G21/K21 -> 0 | S21: =(I21-H21)/H21 -> -0.12432432 | T21: 300
A22: Busy Book Blue | B22: 40924.57 | C22: =G22+J22+L22 -> 18915 | D22: =B22-C22 -> 22009.57 | E22: =D22/B22*100 -> 53.780822 | F22: =D22/K22 -> 478.46891 | H22: 77 | I22: 55 | J22: =K22*T22 -> 13800 | K22: 46 | L22: =I22*93 -> 5115 | M22: =I22-K22-N22 -> 9 | O22: =M22/I22*100 -> 16.363636 | P22: =I22/H22*100 -> 71.428571 | Q22: =K22/I22*100 -> 83.636364 | R22: =G22/K22 -> 0 | S22: =(I22-H22)/H22 -> -0.28571429 | T22: 300
A23: Human Book | B23: 91236.38 | C23: =G23+J23+L23 -> 55392 | D23: =B23-C23 -> 35844.38 | E23: =D23/B23*100 -> 39.287376 | F23: =D23/K23 -> 256.03129 | H23: 249 | I23: 144 | J23: =K23*T23 -> 42000 | K23: 140 | L23: =I23*93 -> 13392 | M23: =I23-K23-N23 -> 4 | O23: =M23/I23*100 -> 2.7777778 | P23: =I23/H23*100 -> 57.831325 | Q23: =K23/I23*100 -> 97.222222 | R23: =G23/K23 -> 0 | S23: =(I23-H23)/H23 -> -0.42168675 | T23: 300
A24: V9-V3 Combo | B24: 73657.35 | C24: =G24+J24+L24 -> 39951 | D24: =B24-C24 -> 33706.35 | E24: =D24/B24*100 -> 45.761014 | F24: =D24/K24 -> 1296.3981 | H24: 48 | I24: 27 | J24: =K24*T24 -> 37440 | K24: 26 | L24: =I24*93 -> 2511 | M24: =I24-K24-N24 -> 1 | O24: =M24/I24*100 -> 3.7037037 | P24: =I24/H24*100 -> 56.25 | Q24: =K24/I24*100 -> 96.296296 | R24: =G24/K24 -> 0 | S24: =(I24-H24)/H24 -> -0.4375 | T24: 1440
A25: V9-V10 Combo | B25: 77391.53 | C25: =G25+J25+L25 -> 50946 | D25: =B25-C25 -> 26445.53 | E25: =D25/B25*100 -> 34.171091 | F25: =D25/K25 -> 979.46407 | H25: 36 | I25: 29 | J25: =K25*T25 -> 48249 | K25: 27 | L25: =I25*93 -> 2697 | M25: =I25-K25-N25 -> 2 | O25: =M25/I25*100 -> 6.8965517 | P25: =I25/H25*100 -> 80.555556 | Q25: =K25/I25*100 -> 93.103448 | R25: =G25/K25 -> 0 | S25: =(I25-H25)/H25 -> -0.19444444 | T25: 1787
A26: V7-V4 Combo | B26: 7145.28 | C26: =G26+J26+L26 -> 2848 | D26: =B26-C26 -> 4297.28 | E26: =D26/B26*100 -> 60.14152 | F26: =D26/K26 -> 1074.32 | H26: 5 | I26: 4 | J26: =K26*T26 -> 2476 | K26: 4 | L26: =I26*93 -> 372 | M26: =I26-K26-N26 -> 0 | O26: =M26/I26*100 -> 0 | P26: =I26/H26*100 -> 80 | Q26: =K26/I26*100 -> 100 | R26: =G26/K26 -> 0 | S26: =(I26-H26)/H26 -> -0.2 | T26: 619
A27: V1-V4 Combo | B27: 92452.94 | C27: =G27+J27+L27 -> 38051 | D27: =B27-C27 -> 54401.94 | E27: =D27/B27*100 -> 58.842845 | F27: =D27/K27 -> 715.815 | H27: 79 | I27: 79 | J27: =K27*T27 -> 30704 | K27: 76 | L27: =I27*93 -> 7347 | M27: =I27-K27-N27 -> 3 | O27: =M27/I27*100 -> 3.7974684 | P27: =I27/H27*100 -> 100 | Q27: =K27/I27*100 -> 96.202532 | R27: =G27/K27 -> 0 | S27: =(I27-H27)/H27 -> 0 | T27: 404
A28: V1-V7 Combo | B28: 50024.6 | C28: =G28+J28+L28 -> 19448 | D28: =B28-C28 -> 30576.6 | E28: =D28/B28*100 -> 61.123127 | F28: =D28/K28 -> 1176.0231 | H28: 28 | I28: 26 | J28: =K28*T28 -> 17030 | K28: 26 | L28: =I28*93 -> 2418 | M28: =I28-K28-N28 -> 0 | O28: =M28/I28*100 -> 0 | P28: =I28/H28*100 -> 92.857143 | Q28: =K28/I28*100 -> 100 | R28: =G28/K28 -> 0 | S28: =(I28-H28)/H28 -> -0.071428571 | T28: 655
A29: V6-V2 Combo | B29: 40157.75 | C29: =G29+J29+L29 -> 14193 | D29: =B29-C29 -> 25964.75 | E29: =D29/B29*100 -> 64.656884 | F29: =D29/K29 -> 1298.2375 | H29: 23 | I29: 21 | J29: =K29*T29 -> 12240 | K29: 20 | L29: =I29*93 -> 1953 | M29: =I29-K29-N29 -> 1 | O29: =M29/I29*100 -> 4.7619048 | P29: =I29/H29*100 -> 91.304348 | Q29: =K29/I29*100 -> 95.238095 | R29: =G29/K29 -> 0 | S29: =(I29-H29)/H29 -> -0.086956522 | T29: 612
A30: V6-V7 Combo | B30: 193336.68 | C30: =G30+J30+L30 -> 86294 | D30: =B30-C30 -> 107042.68 | E30: =D30/B30*100 -> 55.365945 | F30: =D30/K30 -> 1039.2493 | H30: 118 | I30: 105 | J30: =K30*T30 -> 76529 | K30: 103 | L30: =I30*93 -> 9765 | M30: =I30-K30-N30 -> 2 | O30: =M30/I30*100 -> 1.9047619 | P30: =I30/H30*100 -> 88.983051 | Q30: =K30/I30*100 -> 98.095238 | R30: =G30/K30 -> 0 | S30: =(I30-H30)/H30 -> -0.11016949 | T30: 743
A31: V2-V7 Combo | B31: 92600.5 | C31: =G31+J31+L31 -> 40768 | D31: =B31-C31 -> 51832.5 | E31: =D31/B31*100 -> 55.97432 | F31: =D31/K31 -> 1057.8061 | H31: 55 | I31: 49 | J31: =K31*T31 -> 36211 | K31: 49 | L31: =I31*93 -> 4557 | M31: =I31-K31-N31 -> 0 | O31: =M31/I31*100 -> 0 | P31: =I31/H31*100 -> 89.090909 | Q31: =K31/I31*100 -> 100 | R31: =G31/K31 -> 0 | S31: =(I31-H31)/H31 -> -0.10909091 | T31: 739
A32: V1-V2 Combo | B32: 41994.66 | C32: =G32+J32+L32 -> 13667 | D32: =B32-C32 -> 28327.66 | E32: =D32/B32*100 -> 67.455386 | F32: =D32/K32 -> 1287.6209 | H32: 26 | I32: 23 | J32: =K32*T32 -> 11528 | K32: 22 | L32: =I32*93 -> 2139 | M32: =I32-K32-N32 -> 1 | O32: =M32/I32*100 -> 4.3478261 | P32: =I32/H32*100 -> 88.461538 | Q32: =K32/I32*100 -> 95.652174 | R32: =G32/K32 -> 0 | S32: =(I32-H32)/H32 -> -0.11538462 | T32: 524
... A34: V2-V4 Combo | B34: 31361.35 | C34: =G34+J34+L34 -> 12387 | D34: =B34-C34 -> 18974.35 | E34: =D34/B34*100 -> 60.502338 | F34: =D34/K34 -> 903.54048 | H34: 24 | I34: 23 | J34: =K34*T34 -> 10248 | K34: 21 | L34: =I34*93 -> 2139 | M34: =I34-K34-N34 -> 2 | O34: =M34/I34*100 -> 8.6956522 | P34: =I34/H34*100 -> 95.833333 | Q34: =K34/I34*100 -> 91.304348 | R34: =G34/K34 -> 0 | S34: =(I34-H34)/H34 -> -0.041666667 | T34: 488
A35: Total | B35: =sum(B4:B34)+100000 -> 6824691.3 | D35: =SUM(D4:D34) -> 3726182.9 | G35: 4282226 | H35: =SUM(H4:H34) -> 6870 | I35: =SUM(I4:I34) -> 6407 | J35: =SUM(J4:J34) -> 2329816 | K35: =SUM(K4:K34) -> 5741 | L35: =SUM(L4:L34) -> 595851 | M35: =SUM(M4:M34) -> 622 | N35: =SUM(N4:N34) -> 44 | O35: =M35/K35 -> 0.10834349 | P35: =AVERAGE(P4:P34) -> 85.27799 | Q35: =AVERAGE(Q4:Q34) -> 89.563989 | R35: =SUM(R4:R34) -> 0 | S35: =(I35-H35)/H35 -> -0.067394469
D38: Blended | L38: =L35/H35 -> 86.732314
A39: Total Units Sold | B39: =K35 -> 5741
A40: Total Revenue | B40: =B35 -> 6824691.3 | D40: COGS | E40: =B41/B39 -> 405.82059
A41: COGS | B41: =J35 -> 2329816 | D41: CAC | E41: =G35/B39 -> 745.90246 | K41: Total freight charges | L41: 735769
A42: Logistics | B42: =L35 -> 595851 | D42: Logistics | E42: =B42/B39 -> 103.78871 | L42: 6870
A43: Marketing | B43: =G35 -> 4282226 | D43: AOV | E43: =B40/B39 -> 1188.7635 | L43: =L41/L42 -> 107.09884
A44: P&L | B44: =B40-(B41+B42+B43) -> -383201.73
A45: P&L % | B45: =B44/B40 -> -0.056149314
A48: Aug | B48: Amazon
B50: Total revenue | C50: Total expense | D50: Total P/L | E50: Profit % | F50: P/pcs | G50: Total orders | H50: Product expense | I50: Delivered | J50: Return | K50: Amazon expense | L50: RTO% | M50: Only Ad spend | N50: Return GMV
A51: V1 | B51: =1138708.83+14251.38+11082.28+2599 -> 1166641.5 | C51: =K51+H51+M51 -> 581417.76 | D51: =B51-C51 -> 585223.73 | E51: =D51/B51*100 -> 50.163117 | F51: =D51/I51 -> 467.80474 | G51: =1341+11+8+2 -> 1362 | H51: =220*I51 -> 275220 | I51: =1232+11+7+1 -> 1251 | J51: =G51-I51 -> 111 | K51: =( 291920.38+2454.39+2042.38 +725.78 )- (111681.35+147.51) -> 185314.07 | L51: =J51/G51*100 -> 8.1497797 | M51: =120883.69 -> 120883.69 | N51: =J51*999 -> 110889 | O51: =B51/M51 -> 9.6509421 | P51: =B51/B69*100 -> 37.092427
A52: V2 | B52: =692116.65+13022.36 -> 705139.01 | C52: =K52+H52+M52 -> 414596.77 | D52: =B52-C52 -> 290542.24 | E52: =D52/B52*100 -> 41.203541 | F52: =D52/I52 -> 451.15255 | G52: =692+9 -> 701 | H52: =304*I52 -> 195776 | I52: =635+9 -> 644 | J52: =G52-I52 -> 57 | K52: =(173490.05+2055.76) -34613.56 -> 140932.25 | L52: =J52/G52*100 -> 8.1312411 | M52: =77888.52 -> 77888.52 | N52: =J52*1119 -> 63783 | O52: =B52/M52 -> 9.0531828 | P52: =B52/B69*100 -> 22.419327
A53: V3 | B53: =17982+31780 -> 49762 | C53: =K53+H53+M53 -> 34936.57 | D53: =B53-C53 -> 14825.43 | E53: =D53/B53*100 -> 29.792673 | F53: =D53/I53 -> 436.04206 | G53: =9+28 -> 37 | H53: =662*I53 -> 22508 | I53: =9+25 -> 34 | J53: =G53-I53 -> 3 | K53: =(5689.34+6732.75 )-(3339.18+0) -> 9082.91 | L53: =J53/G53*100 -> 8.1081081 | M53: =3345.66 -> 3345.66 | N53: =J53*1799 -> 5397 | O53: =B53/M53 -> 14.873597 | P53: =B53/B69*100 -> 1.5821427
A54: V4 | B54: =6469.13+223276.52+6079.2 -> 235824.85 | C54: =K54+H54+M54 -> 186281.05 | D54: =B54-C54 -> 49543.8 | E54: =D54/B54*100 -> 21.008727 | F54: =D54/I54 -> 94.730019 | G54: =552+10+7 -> 569 | H54: =184*I54 -> 96232 | I54: =506+10+7 -> 523 | J54: =G54-I54 -> 46 | K54: =(939.08+67761.06+737.96 ) -(10.98+28250.59) -> 41176.53 | L54: =J54/G54*100 -> 8.0843585 | M54: =48872.52 -> 48872.52 | N54: =J54*499 -> 22954 | O54: =B54/M54 -> 4.8253057 | P54: =B54/B69*100 -> 7.4978613
A55: V5 | B55: 0 | C55: =K55+H55+M55 -> 0 | D55: =B55-C55 -> 0 | E55: =D55/B55*100 -> #DIV/0! | F55: =D55/I55 -> #DIV/0! | G55: 0 | H55: =250*I55 -> 0 | I55: 0 | J55: =G55-I55 -> 0 | K55: 0 | L55: =J55/G55*100 -> #DIV/0! | M55: 0 | N55: =J55*1049 -> 0 | O55: =B55/M55 -> #DIV/0! | P55: =B55/B69*100 -> 0
A56: V6 | B56: =338681 -> 338681 | C56: =K56+H56+M56 -> 268370.75 | D56: =B56-C56 -> 70310.25 | E56: =D56/B56*100 -> 20.760022 | F56: =D56/I56 -> 229.02362 | G56: =345 -> 345 | H56: =308*I56 -> 94556 | I56: =307 -> 307 | J56: =G56-I56 -> 38 | K56: =(144146.76+956.42)-70714.36 -> 74388.82 | L56: =J56/G56*100 -> 11.014493 | M56: =99425.93 -> 99425.93 | N56: =J56*1249 -> 47462 | O56: =B56/M56 -> 3.4063649 | P56: =B56/B69*100 -> 10.76809
A57: V7 | B57: =123498.91 -> 123498.91 | C57: =K57+H57+M57 -> 120968.89 | D57: =B57-C57 -> 2530.02 | E57: =D57/B57*100 -> 2.0486173 | F57: =D57/I57 -> 22.589464 | G57: =122 -> 122 | H57: =435*I57 -> 48720 | I57: =112 -> 112 | J57: =G57-I57 -> 10 | K57: =59245.81-35860.19 -> 23385.62 | L57: =J57/G57*100 -> 8.1967213 | M57: =48863.27 -> 48863.27 | N57: =J57*1349 -> 13490 | O57: =B57/M57 -> 2.5274385 | P57: =B57/B69*100 -> 3.9265484
A58: V8 | B58: 0 | C58: =K58+H58+M58 -> 0 | D58: =B58-C58 -> 0 | E58: =D58/B58*100 -> #DIV/0! | F58: =D58/I58 -> #DIV/0! | G58: 0 | H58: =800*I58 -> 0 | I58: 0 | J58: =G58-I58 -> 0 | K58: 0 | L58: =J58/G58*100 -> #DIV/0! | M58: 0 | N58: =J58*1899 -> 0 | O58: =B58/M58 -> #DIV/0! | P58: =B58/B69*100 -> 0
A59: V9 | B59: =29887+122036.98 -> 151923.98 | C59: =K59+H59+M59 -> 146678.44 | D59: =B59-C59 -> 5245.54 | E59: =D59/B59*100 -> 3.45274 | F59: =D59/I59 -> 63.97 | G59: =13+81 -> 94 | H59: =778*I59 -> 63796 | I59: =13+69 -> 82 | J59: =G59-I59 -> 12 | K59: =(3839.49+29382.45 )-(2525.93-10919.85) -> 41615.86 | L59: =J59/G59*100 -> 12.765957 | M59: =41266.58 -> 41266.58 | N59: =J59*1999 -> 23988 | O59: =B59/M59 -> 3.6815258 | P59: =B59/B69*100 -> 4.8303006
A60: BB | B60: =20363 -> 20363 | C60: =K60+H60+M60 -> 16189.54 | D60: =B60-C60 -> 4173.46 | E60: =D60/B60*100 -> 20.49531 | F60: =D60/I60 -> 107.01179 | G60: =45 -> 45 | H60: =200*I60 -> 7800 | I60: =39 -> 39 | J60: =G60-I60 -> 6 | K60: =8457.32 -(4605.01) -> 3852.31 | L60: =J60/G60*100 -> 13.333333 | M60: =4537.23 -> 4537.23 | N60: =J60*599 -> 3594 | O60: =B60/M60 -> 4.4879806 | P60: =B60/B69*100 -> 0.64742519
A61: V1V4 | B61: 0 | C61: =K61+H61+M61 -> 0 | D61: =B61-C61 -> 0 | E61: =D61/B61*100 -> #DIV/0! | F61: =D61/I61 -> #DIV/0! | G61: 0 | H61: =(270+220)*I61 -> 0 | I61: 0 | J61: =G61-I61 -> 0 | K61: 0 | L61: =J61/G61*100 -> #DIV/0! | M61: 0 | O61: =B61/M61 -> #DIV/0! | P61: =B61/B69*100 -> 0
A62: V1V2 | B62: =4198 -> 4198 | C62: =K62+H62+M62 -> 1892.76 | D62: =B62-C62 -> 2305.24 | E62: =D62/B62*100 -> 54.912816 | F62: =D62/I62 -> 1152.62 | G62: 2 | H62: =(270+350)*I62 -> 1240 | I62: 2 | J62: =G62-I62 -> 0 | K62: =652.76 -> 652.76 | L62: =J62/G62*100 -> 0 | M62: 0 | N62: =J62*2199 -> 0 | O62: =B62/M62 -> #DIV/0! | P62: =B62/B69*100 -> 0.13347203
A63: V1V6 | B63: =2199 -> 2199 | C63: =K63+H63+M63 -> 1267.76 | D63: =B63-C63 -> 931.24 | E63: =D63/B63*100 -> 42.34834 | F63: =D63/I63 -> 931.24 | G63: 2 | H63: =(270+320)*I63 -> 590 | I63: 1 | J63: =G63-I63 -> 1 | K63: =677.76 -> 677.76 | L63: =J63/G63*100 -> 50 | M63: 0 | N63: =J63*999 -> 999 | O63: =B63/M63 -> #DIV/0! | P63: =B63/B69*100 -> 0.069915435
A64: V2V4 | B64: =33178 -> 33178 | C64: =K64+H64+M64 -> 20431.42 | D64: =B64-C64 -> 12746.58 | E64: =D64/B64*100 -> 38.418771 | F64: =D64/I64 -> 554.19913 | G64: 25 | H64: =(350+220)*I64 -> 13110 | I64: 23 | J64: =G64-I64 -> 2 | K64: =5933.36 -> 5933.36 | L64: =J64/G64*100 -> 8 | M64: =1388.06 -> 1388.06 | N64: =J64*1499 -> 2998 | O64: =B64/M64 -> 23.902425 | P64: =B64/B69*100 -> 1.0548678
A65: V2V6 | B65: 0 | C65: =K65+H65+M65 -> 0 | D65: =B65-C65 -> 0 | E65: =D65/B65*100 -> #DIV/0! | F65: =D65/I65 -> #DIV/0! | G65: 0 | H65: =(350+320)*I65 -> 0 | I65: 0 | J65: =G65-I65 -> 0 | K65: 0 | L65: =J65/G65*100 -> #DIV/0! | M65: 0 | N65: =J65*999 -> 0 | O65: =B65/M65 -> #DIV/0! | P65: =B65/B69*100 -> 0
A66: BB's | B66: =191147+108489 -> 299636 | C66: =K66+H66+M66 -> 210033.63 | D66: =B66-C66 -> 89602.37 | E66: =D66/B66*100 -> 29.90374 | F66: =D66/I66 -> 282.65732 | G66: =219+115 -> 334 | H66: =(330)*I66 -> 104610 | I66: =206+111 -> 317 | J66: =G66-I66 -> 17 | K66: =(47289.89+43637.21 )-(14756.16+24603.99-167.33 ) -> 51734.28 | L66: =J66/G66*100 -> 5.0898204 | M66: =35490.99+ 18198.36 -> 53689.35 | N66: =J66*999 -> 16983 | O66: =B66/M66 -> 5.5809206 | P66: =B66/B69*100 -> 9.5266854
A67: HBB | B67: =14183 -> 14183 | C67: =K67+H67+M67 -> 20159.68 | D67: =B67-C67 -> -5976.68 | E67: =D67/B67*100 -> -42.139745 | F67: =D67/I67 -> -351.56941 | G67: =19 -> 19 | H67: =(330)*I67 -> 5610 | I67: =17 -> 17 | J67: =G67-I67 -> 2 | K67: =21599.48-19011.44 -> 2588.04 | L67: =J67/G67*100 -> 10.526316 | M67: =11961.64 -> 11961.64 | N67: =J67*999 -> 1998 | O67: =B67/M67 -> 1.185707
A68: V10 | B68: =48074+2499 -> 50573 | C68: =K68+H68+M68 -> 66855.77 | D68: =B68-C68 -> -16282.77 | E68: =D68/B68*100 -> -32.196567 | F68: =D68/I68 -> -525.25065 | G68: =37+1 -> 38 | H68: =(330)*I68 -> 10230 | I68: =30+1 -> 31 | J68: =G68-I68 -> 7 | K68: =(15684.13+2583.13)-(6640.04-1430.4) -> 13057.62 | L68: =J68/G68*100 -> 18.421053 | M68: =43568.15 -> 43568.15 | N68: =J68*999 -> 6993
A69: Total | B69: =SUM(B51:B67) -> 3145228.2 | C69: =SUM(C51:C67) -> 2023225 | D69: =SUM(D51:D67) -> 1122003.2 | G69: =SUM(G51:G67) -> 3657 | H69: =SUM(H51:H67) -> 929768 | I69: =SUM(I51:I67) -> 3352 | J69: =SUM(J51:J67) -> 305 | K69: =SUM(K51:K67) -> 581334.57 | M69: =SUM(M51:M68) -> 555690.6
A72: Total Revenue | B72: =B69 -> 3145228.2
A73: COGS | B73: =H69 -> 929768 | D73: Blended
A74: Amazon Ex | B74: 348800 | D74: COGS | E74: =B73/I69 -> 277.37709
A75: Logi | B75: 232533
A76: Marketing | B76: =M69 -> 555690.6 | D76: CAC | E76: =B76/I69 -> 165.77882
A77: Net P&L | B77: =B72-SUM(B73:B76) -> 1078436.6 | D77: Commisions | E77: =B74/I69 -> 104.05728
A78: P&L % | B78: =B77/B72*100 -> 34.288025 | D78: AOV | E78: =B72/I69 -> 938.31391
A85: Aug | B85: Flipkart
B87: Total revenue | C87: Total expense | D87: Total P/L | E87: Profit % | F87: P/pcs | G87: Total orders | H87: Product expense | I87: Delivered | J87: Return | K87: Flipkart expenses | L87: RTO% | M87: Only Ad spend
A88: V1 | B88: =18174 -> 18174 | C88: =K88+H88 -> 9392.35 | D88: =B88-C88 -> 8781.65 | E88: =D88/B88*100 -> 48.319853 | F88: =D88/I88 -> 351.266 | G88: 38 | H88: =220*I88 -> 5500 | I88: 25 | J88: =G88-I88 -> 13 | K88: =3892.35 -> 3892.35 | L88: =J88/G88*100 -> 34.210526
A89: V2 | B89: =38557 -> 38557 | C89: =K89+H89 -> 17485.97 | D89: =B89-C89 -> 21071.03 | E89: =D89/B89*100 -> 54.649039 | F89: =D89/I89 -> 468.24511 | G89: 66 | H89: =304*I89 -> 13680 | I89: 45 | J89: =G89-I89 -> 21 | K89: =3805.97 -> 3805.97 | L89: =J89/G89*100 -> 31.818182
A90: V3 | B90: =1528 -> 1528 | C90: =K90+H90 -> 1251.35 | D90: =B90-C90 -> 276.65 | E90: =D90/B90*100 -> 18.105366 | F90: =D90/I90 -> 276.65 | G90: 3 | H90: =662*I90 -> 662 | I90: 1 | J90: =G90-I90 -> 2 | K90: =589.35 -> 589.35 | L90: =J90/G90*100 -> 66.666667
A91: V4 | B91: =45570 -> 45570 | C91: =K91+H91 -> 32926.44 | D91: =B91-C91 -> 12643.56 | E91: =D91/B91*100 -> 27.745359 | F91: =D91/I91 -> 97.258154 | G91: 181 | H91: =184*I91 -> 23920 | I91: 130 | J91: =G91-I91 -> 51 | K91: =9006.44 -> 9006.44 | L91: =J91/G91*100 -> 28.176796
A92: BB | B92: =2160 -> 2160 | C92: =K92+H92 -> 1577.55 | D92: =B92-C92 -> 582.45 | E92: =D92/B92*100 -> 26.965278 | F92: =D92/I92 -> 116.49 | G92: 5 | H92: =270*I92 -> 1350 | I92: 5 | J92: =G92-I92 -> 0 | K92: =227.55 -> 227.55 | L92: =J92/G92*100 -> 0
A93: V6 | B93: =6636 -> 6636 | C93: =K93+H93 -> 4421.1 | D93: =B93-C93 -> 2214.9 | E93: =D93/B93*100 -> 33.377034 | F93: =D93/I93 -> 316.41429 | G93: 17 | H93: =320*I93 -> 2240 | I93: 7 | J93: =G93-I93 -> 10 | K93: =2181.1 -> 2181.1 | L93: =J93/G93*100 -> 58.823529
A94: V7 | B94: =985 -> 985 | C94: =K94+H94 -> 1438.8 | D94: =B94-C94 -> -453.8 | E94: =D94/B94*100 -> -46.071066 | F94: =D94/I94 -> -151.26667 | G94: 4 | H94: =470*I94 -> 1410 | I94: 3 | J94: =G94-I94 -> 1 | K94: =28.8 -> 28.8 | L94: =J94/G94*100 -> 25
A95: Wooden cal | B95: =1488 -> 1488 | C95: =K95+H95 -> 1763.41 | D95: =B95-C95 -> -275.41 | E95: =D95/B95*100 -> -18.508737 | F95: =D95/I95 -> -39.344286 | G95: 17 | H95: =200*I95 -> 1400 | I95: 7 | J95: =G95-I95 -> 10 | K95: =363.41 -> 363.41 | L95: =J95/G95*100 -> 58.823529
A96: V9 | B96: =12504 -> 12504 | C96: =K96+H96 -> 9772.82 | D96: =B96-C96 -> 2731.18 | E96: =D96/B96*100 -> 21.84245 | F96: =D96/I96 -> 341.3975 | G96: 20 | H96: =1000*I96 -> 8000 | I96: 8 | J96: =G96-I96 -> 12 | K96: =1772.82 -> 1772.82 | L96: =J96/G96*100 -> 60
A97: V10 | B97: =3304 -> 3304 | C97: =K97+H97+M97 -> 1272.86 | D97: =B97-C97 -> 2031.14 | E97: =D97/B97*100 -> 61.475182 | F97: =D97/I97 -> 1015.57 | G97: 3 | H97: =(330)*I97 -> 660 | I97: 2 | J97: =G97-I97 -> 1 | K97: =612.86 -> 612.86 | L97: =J97/G97*100 -> 33.333333 | N97: =J97*999 -> 999
A98: V1Cal | B98: =3867 -> 3867 | C98: =K98+H98 -> 2194.48 | D98: =B98-C98 -> 1672.52 | E98: =D98/B98*100 -> 43.251099 | F98: =D98/I98 -> 557.50667 | G98: 4 | H98: =(220+350)*I98 -> 1710 | I98: 3 | J98: =G98-I98 -> 1 | K98: =484.48 -> 484.48 | L98: =J98/G98*100 -> 25
A99: V1V4 | B99: =2258 -> 2258 | C99: =K99+H99 -> 1427.3 | D99: =B99-C99 -> 830.7 | E99: =D99/B99*100 -> 36.789194 | F99: =D99/I99 -> 415.35 | G99: 3 | H99: =(220+350)*I99 -> 1140 | I99: 2 | J99: =G99-I99 -> 1 | K99: =287.3 -> 287.3 | L99: =J99/G99*100 -> 33.333333
A100: V6V2 | B100: =6908 -> 6908 | C100: =K100+H100 -> 4156.28 | D100: =B100-C100 -> 2751.72 | E100: =D100/B100*100 -> 39.833816 | F100: =D100/I100 -> 687.93 | G100: 8 | H100: =(320+350)*I100 -> 2680 | I100: 4 | J100: =G100-I100 -> 4 | K100: =1476.28 -> 1476.28 | L100: =J100/G100*100 -> 50
A101: V1V2 | B101: =8175 -> 8175 | C101: =K101+H101 -> 4100.5 | D101: =B101-C101 -> 4074.5 | E101: =D101/B101*100 -> 49.840979 | F101: =D101/I101 -> 814.9 | G101: 9 | H101: =(270+350)*I101 -> 3100 | I101: 5 | J101: =G101-I101 -> 4 | K101: =1000.5 -> 1000.5 | L101: =J101/G101*100 -> 44.444444
B102: =SUM(B88:B101) -> 152114 | C102: =SUM(C88:C101) -> 93181.21 | D102: =SUM(D88:D101) -> 58932.79 | G102: =SUM(G88:G101) -> 378 | H102: =SUM(H88:H101) -> 67452 | I102: =SUM(I88:I101) -> 247 | J102: =SUM(J88:J101) -> 131 | K102: =SUM(K88:K101) -> 25729.21 | M102: 0
A105: Total Revenue | B105: =B102 -> 152114
A106: COGS | B106: =H102 -> 67452
A107: Flipkart Ex | B107: =K102-B108 -> 25729.21 | D107: COGS | E107: =B106/I102 -> 273.08502
A108: Marketing | B108: =M102 -> 0 | D108: CAC | E108: =B108/I102 -> 0
A109: Net P&L | B109: =B105-SUM(B106:B108) -> 58932.79 | D109: Commisions | E109: =B107/I102 -> 104.16684
A110: P&L % | B110: =B109/B105*100 -> 38.742515 | D110: AOV | E110: =B105/I102 -> 615.84615
A115: Aug | B115: Blinkit
B117: Total revenue | C117: Total expense | D117: Total P/L | E117: Profit % | F117: P/pcs | G117: Product exp | H117: Total orders | I117: Blinkit exp | J117: Ads | K117: Logistics
A118: V1 | B118: =689*H118 -> 188786 | C118: =J118+G118+I118+K118 -> 69870 | D118: =B118-C118 -> 118916 | E118: =D118/B118*100 -> 62.98984 | F118: =D118/H118 -> 434 | G118: =235*H118 -> 64390 | H118: 274 | I118: 0 | J118: 0 | K118: =20*H118 -> 5480 | M118: 59209
A119: V4 | B119: =359*H119 -> 88314 | C119: =J119+G119+I119+K119 -> 53874 | D119: =B119-C119 -> 34440 | E119: =D119/B119*100 -> 38.997214 | F119: =D119/H119 -> 140 | G119: =199*H119 -> 48954 | H119: 246 | I119: 0 | J119: 0 | K119: =20*H119 -> 4920
A120: V2 | B120: =781*H120 -> 153076 | C120: =J120+G120+I120+K120 -> 66444 | D120: =B120-C120 -> 86632 | E120: =D120/B120*100 -> 56.59411 | F120: =D120/H120 -> 442 | G120: =319*H120 -> 62524 | H120: 196 | I120: 0 | J120: =L120%*M120 -> 0 | K120: =20*H120 -> 3920
A121: V6 | B121: =843*H121 -> 185460 | C121: =J121+G121+I121+K121 -> 75460 | D121: =B121-C121 -> 110000 | E121: =D121/B121*100 -> 59.311981 | F121: =D121/H121 -> 500 | G121: =323*H121 -> 71060 | H121: 220 | I121: 0 | J121: =L121%*M121 -> 0 | K121: =20*H121 -> 4400
B122: =SUM(B118:B121) -> 615636 | C122: =SUM(C118:C121) -> 265648 | D122: =SUM(D118:D121) -> 349988 | E122: =SUM(E118:E121) -> 217.89315 | F122: =SUM(F118:F121) -> 1516 | G122: =SUM(G118:G121) -> 246928 | H122: =SUM(H118:H121) -> 936 | I122: 144647 | J122: 144647 | K122: =SUM(K118:K121) -> 18720
A125: Total Revenue | B125: =B122 -> 615636 | D125: Blended | E125: 125/pcs
...

Sheet Sep 25
A1: Sept | B1: Shopify
A3: Products | B3: Total Dilivered Revenue | C3: Total expense | D3: Total P/L | E3: Profit % | F3: P/pcs | G3: Ad spent | H3: Total orders | I3: Shipped | J3: Total COGS | K3: Delivered | L3: Shipping charges | M3: RTO | N3: In-transit | O3: RTO% | P3: Shipped% | Q3: Delivered % | R3: CPD | S3: Cancellation % | T3: COGS/Unit
A4: V1 | B4: 1060146.8 | C4: =G4+J4+L4 -> 443851 | E4: =D4/B4*100 -> 0 | F4: =D4/K4 -> 0 | H4: 1666 | I4: 1607 | J4: =K4*T4 -> 294400 | K4: 1472 | L4: =I4*93 -> 149451 | M4: =I4-K4-N4 -> 101 | N4: 34 | O4: =M4/I4*100 -> 6.2850031 | P4: =I4/H4*100 -> 96.458583 | Q4: =K4/I4*100 -> 91.599253 | R4: =G4/K4 -> 0 | S4: =(I4-H4)/H4 -> -0.035414166 | T4: 200
A5: V1- P of 2 | B5: 89095.37 | C5: =G5+J5+L5 -> 33765 | E5: =D5/B5*100 -> 0 | F5: =D5/K5 -> 0 | H5: 69 | I5: 65 | J5: =K5*T5 -> 27720 | K5: 63 | L5: =I5*93 -> 6045 | M5: =I5-K5-N5 -> 2 | O5: =M5/I5*100 -> 3.0769231 | P5: =I5/H5*100 -> 94.202899 | Q5: =K5/I5*100 -> 96.923077 | R5: =G5/K5 -> 0 | S5: =(I5-H5)/H5 -> -0.057971014 | T5: 440
A6: V2 | B6: 1349666.9 | C6: =G6+J6+L6 -> 500050 | E6: =D6/B6*100 -> 0 | F6: =D6/K6 -> 0 | H6: 1464 | I6: 1402 | J6: =K6*T6 -> 369664 | K6: 1216 | L6: =I6*93 -> 130386 | M6: =I6-K6-N6 -> 177 | N6: 9 | O6: =M6/I6*100 -> 12.624822 | P6: =I6/H6*100 -> 95.765027 | Q6: =K6/I6*100 -> 86.733238 | R6: =G6/K6 -> 0 | S6: =(I6-H6)/H6 -> -0.042349727 | T6: 304
A7: V2- P of 2 | B7: 78984.77 | C7: =G7+J7+L7 -> 30000 | E7: =D7/B7*100 -> 0 | F7: =D7/K7 -> 0 | H7: 50 | I7: 48 | J7: =K7*T7 -> 25536 | K7: 42 | L7: =I7*93 -> 4464 | M7: =I7-K7-N7 -> 6 | O7: =M7/I7*100 -> 12.5 | P7: =I7/H7*100 -> 96 | Q7: =K7/I7*100 -> 87.5 | R7: =G7/K7 -> 0 | S7: =(I7-H7)/H7 -> -0.04 | T7: 608
A8: V3 | B8: 57975.83 | C8: =G8+J8+L8 -> 27180 | E8: =D8/B8*100 -> 0 | F8: =D8/K8 -> 0 | H8: 36 | I8: 36 | J8: =K8*T8 -> 23832 | K8: 36 | L8: =I8*93 -> 3348 | M8: =I8-K8-N8 -> 0 | O8: =M8/I8*100 -> 0 | P8: =I8/H8*100 -> 100 | Q8: =K8/I8*100 -> 100 | R8: =G8/K8 -> 0 | T8: 662
A9: V4 | B9: 85165.2 | C9: =G9+J9+L9 -> 43964 | E9: =D9/B9*100 -> 0 | F9: =D9/K9 -> 0 | H9: 179 | I9: 172 | J9: =K9*T9 -> 27968 | K9: 152 | L9: =I9*93 -> 15996 | M9: =I9-K9-N9 -> 20 | O9: =M9/I9*100 -> 11.627907 | P9: =I9/H9*100 -> 96.089385 | Q9: =K9/I9*100 -> 88.372093 | R9: =G9/K9 -> 0 | S9: =(I9-H9)/H9 -> -0.039106145 | T9: 184
A10: V4- P of 2 | B10: 22692.4 | C10: =G10+J10+L10 -> 11343 | E10: =D10/B10*100 -> 0 | F10: =D10/K10 -> 0 | H10: 28 | I10: 27 | J10: =K10*T10 -> 8832 | K10: 24 | L10: =I10*93 -> 2511 | M10: =I10-K10-N10 -> 3 | O10: =M10/I10*100 -> 11.111111 | P10: =I10/H10*100 -> 96.428571 | Q10: =K10/I10*100 -> 88.888889 | R10: =G10/K10 -> 0 | S10: =(I10-H10)/H10 -> -0.035714286 | T10: 368
A11: V4- P of 3 | B11: 0 | C11: =G11+J11+L11 -> 0 | E11: =D11/B11*100 -> #DIV/0! | F11: =D11/K11 -> #DIV/0! | H11: 0 | I11: 0 | J11: =K11*T11 -> 0 | K11: 0 | L11: =I11*93 -> 0 | M11: =I11-K11-N11 -> 0 | O11: 0 | P11: =I11/H11*100 -> #DIV/0! | Q11: =K11/I11*100 -> #DIV/0! | R11: =G11/K11 -> #DIV/0! | T11: 368
A12: V5 | B12: 0 | C12: 0 | E12: 0 | F12: 0 | H12: 0 | I12: 0 | J12: 0 | K12: 0 | L12: =I12*93 -> 0 | M12: =I12-K12-N12 -> 0 | O12: 0 | P12: =I12/H12*100 -> #DIV/0! | Q12: =K12/I12*100 -> #DIV/0! | T12: 206
A13: V6 | B13: 906942.62 | C13: =G13+J13+L13 -> 330972 | E13: =D13/B13*100 -> 0 | F13: =D13/K13 -> 0 | H13: 935 | I13: 916 | J13: =K13*T13 -> 245784 | K13: 798 | L13: =I13*93 -> 85188 | M13: =I13-K13-N13 -> 114 | N13: 4 | O13: =M13/I13*100 -> 12.445415 | P13: =I13/H13*100 -> 97.967914 | Q13: =K13/I13*100 -> 87.117904 | R13: =G13/K13 -> 0 | S13: =(I13-H13)/H13 -> -0.020320856 | T13: 308
A14: V6- P of 2 | B14: 81089.61 | C14: =G14+J14+L14 -> 31754 | E14: =D14/B14*100 -> 0 | F14: =D14/K14 -> 0 | H14: 51 | I14: 50 | J14: =K14*T14 -> 27104 | K14: 44 | L14: =I14*93 -> 4650 | M14: =I14-K14-N14 -> 6 | O14: =M14/I14*100 -> 12 | P14: =I14/H14*100 -> 98.039216 | Q14: =K14/I14*100 -> 88 | R14: =G14/K14 -> 0 | S14: =(I14-H14)/H14 -> -0.019607843 | T14: 616
A15: V7 | B15: 0 | C15: =G15+J15+L15 -> 12672 | E15: =D15/B15*100 -> #DIV/0! | F15: =D15/K15 -> 0 | H15: 29 | I15: 24 | J15: =K15*T15 -> 10440 | K15: 24 | L15: =I15*93 -> 2232 | M15: =I15-K15-N15 -> 0 | O15: =M15/I15*100 -> 0 | P15: =I15/H15*100 -> 82.758621 | Q15: =K15/I15*100 -> 100 | R15: =G15/K15 -> 0 | S15: =(I15-H15)/H15 -> -0.17241379 | T15: 435
A16: V8 | B16: 49925.76 | C16: 0 | E16: =D16/B16*100 -> 0 | F16: 0 | H16: 45 | I16: 34 | J16: =K16*T16 -> 20970 | K16: 30 | L16: =I16*93 -> 3162 | M16: =I16-K16-N16 -> 4 | O16: =M16/I16*100 -> 11.764706 | P16: =I16/H16*100 -> 75.555556 | Q16: =K16/I16*100 -> 88.235294 | S16: =(I16-H16)/H16 -> -0.24444444 | T16: 699
A17: V9 | B17: 1351112.5 | C17: =G17+J17+L17 -> 653071 | E17: =D17/B17*100 -> 0 | F17: =D17/K17 -> 0 | H17: 858 | I17: 815 | J17: =K17*T17 -> 577276 | K17: 742 | L17: =I17*93 -> 75795 | M17: =I17-K17-N17 -> 71 | N17: 2 | O17: =M17/I17*100 -> 8.7116564 | P17: =I17/H17*100 -> 94.988345 | Q17: =K17/I17*100 -> 91.042945 | R17: =G17/K17 -> 0 | S17: =(I17-H17)/H17 -> -0.05011655 | T17: 778
A18: V9 P of 2 | B18: 75381.54 | C18: =G18+J18+L18 -> 43246 | E18: =D18/B18*100 -> 0 | F18: =D18/K18 -> 0 | H18: 36 | I18: 30 | J18: =K18*T18 -> 40456 | K18: 26 | L18: =I18*93 -> 2790 | M18: =I18-K18-N18 -> 4 | O18: =M18/I18*100 -> 13.333333 | P18: =I18/H18*100 -> 83.333333 | Q18: =K18/I18*100 -> 86.666667 | R18: =G18/K18 -> 0 | S18: =(I18-H18)/H18 -> -0.16666667 | T18: 1556
A19: V10 | B19: 83457.04 | C19: =G19+J19+L19 -> 52380 | E19: =D19/B19*100 -> 0 | F19: =D19/K19 -> 0 | H19: 86 | I19: 75 | J19: =K19*T19 -> 45405 | K19: 45 | L19: =I19*93 -> 6975 | M19: =I19-K19-N19 -> 30 | O19: =M19/I19*100 -> 40 | P19: =I19/H19*100 -> 87.209302 | Q19: =K19/I19*100 -> 60 | R19: =G19/K19 -> 0 | S19: =(I19-H19)/H19 -> -0.12790698 | T19: 1009
A20: Busy Book | B20: 0 | C20: 0 | E20: 0 | F20: 0 | H20: 0 | I20: 0 | J20: =K20*T20 -> 0 | K20: 0 | L20: =I20*93 -> 0 | M20: =I20-K20-N20 -> 0 | O20: 0 | P20: 0 | Q20: 0 | R20: 0 | T20: 250
A21: Busy Book Pink | B21: 64724.37 | C21: =G21+J21+L21 -> 31512 | E21: =D21/B21*100 -> 0 | F21: =D21/K21 -> 0 | H21: 148 | I21: 84 | J21: =K21*T21 -> 23700 | K21: 79 | L21: =I21*93 -> 7812 | M21: =I21-K21-N21 -> 5 | O21: =M21/I21*100 -> 5.952381 | P21: =I21/H21*100 -> 56.756757 | Q21: =K21/I21*100 -> 94.047619 | R21: =G21/K21 -> 0 | S21: =(I21-H21)/H21 -> -0.43243243 | T21: 300
A22: Busy Book Blue | B22: 10042.07 | C22: =G22+J22+L22 -> 4902 | E22: =D22/B22*100 -> 0 | F22: =D22/K22 -> 0 | H22: 14 | I22: 14 | J22: =K22*T22 -> 3600 | K22: 12 | L22: =I22*93 -> 1302 | M22: =I22-K22-N22 -> 2 | O22: =M22/I22*100 -> 14.285714 | P22: =I22/H22*100 -> 100 | Q22: =K22/I22*100 -> 85.714286 | R22: =G22/K22 -> 0 | T22: 300
A23: Human Book | B23: 2257.16 | C23: =G23+J23+L23 -> 1179 | E23: =D23/B23*100 -> 0 | F23: =D23/K23 -> 0 | H23: 5 | I23: 3 | J23: =K23*T23 -> 900 | K23: 3 | L23: =I23*93 -> 279 | M23: =I23-K23-N23 -> 0 | O23: =M23/I23*100 -> 0 | P23: =I23/H23*100 -> 60 | Q23: =K23/I23*100 -> 100 | R23: =G23/K23 -> 0 | S23: =(I23-H23)/H23 -> -0.4 | T23: 300
A24: V9-V3 Combo | B24: 41271.17 | C24: =G24+J24+L24 -> 21555 | E24: =D24/B24*100 -> 0 | F24: =D24/K24 -> 0 | H24: 29 | I24: 15 | J24: =K24*T24 -> 20160 | K24: 14 | L24: =I24*93 -> 1395 | M24: =I24-K24-N24 -> 1 | O24: =M24/I24*100 -> 6.6666667 | P24: =I24/H24*100 -> 51.724138 | Q24: =K24/I24*100 -> 93.333333 | R24: =G24/K24 -> 0 | S24: =(I24-H24)/H24 -> -0.48275862 | T24: 1440
A25: V9-V10 Combo | B25: 44770.51 | C25: =G25+J25+L25 -> 31010 | E25: =D25/B25*100 -> 0 | F25: =D25/K25 -> 0 | H25: 41 | I25: 26 | J25: =K25*T25 -> 28592 | K25: 16 | L25: =I25*93 -> 2418 | M25: =I25-K25-N25 -> 10 | O25: =M25/I25*100 -> 38.461538 | P25: =I25/H25*100 -> 63.414634 | Q25: =K25/I25*100 -> 61.538462 | R25: =G25/K25 -> 0 | S25: =(I25-H25)/H25 -> -0.36585366 | T25: 1787
A26: V7-V4 Combo | B26: 3748 | C26: =G26+J26+L26 -> 1424 | E26: =D26/B26*100 -> 0 | F26: =D26/K26 -> 0 | H26: 2 | I26: 2 | J26: =K26*T26 -> 1238 | K26: 2 | L26: =I26*93 -> 186 | M26: =I26-K26-N26 -> 0 | O26: =M26/I26*100 -> 0 | P26: =I26/H26*100 -> 100 | Q26: =K26/I26*100 -> 100 | R26: =G26/K26 -> 0 | T26: 619
A27: V1-V4 Combo | B27: 59814.49 | C27: =G27+J27+L27 -> 25719 | E27: =D27/B27*100 -> 0 | F27: =D27/K27 -> 0 | H27: 56 | I27: 55 | J27: =K27*T27 -> 20604 | K27: 51 | L27: =I27*93 -> 5115 | M27: =I27-K27-N27 -> 4 | O27: =M27/I27*100 -> 7.2727273 | P27: =I27/H27*100 -> 98.214286 | Q27: =K27/I27*100 -> 92.727273 | R27: =G27/K27 -> 0 | S27: =(I27-H27)/H27 -> -0.017857143 | T27: 404
A28: V1-V7 Combo | B28: 11593 | C28: =G28+J28+L28 -> 5236 | E28: =D28/B28*100 -> 0 | F28: =D28/K28 -> 0 | H28: 8 | I28: 7 | J28: =K28*T28 -> 4585 | K28: 7 | L28: =I28*93 -> 651 | M28: =I28-K28-N28 -> 0 | O28: =M28/I28*100 -> 0 | P28: =I28/H28*100 -> 87.5 | Q28: =K28/I28*100 -> 100 | R28: =G28/K28 -> 0 | S28: =(I28-H28)/H28 -> -0.125 | T28: 655
A29: V6-V2 Combo | B29: 56170.99 | C29: =G29+J29+L29 -> 19740 | E29: =D29/B29*100 -> 0 | F29: =D29/K29 -> 0 | H29: 29 | I29: 28 | J29: =K29*T29 -> 17136 | K29: 28 | L29: =I29*93 -> 2604 | M29: =I29-K29-N29 -> 0 | O29: =M29/I29*100 -> 0 | P29: =I29/H29*100 -> 96.551724 | Q29: =K29/I29*100 -> 100 | R29: =G29/K29 -> 0 | S29: =(I29-H29)/H29 -> -0.034482759 | T29: 612
A30: V6-V7 Combo | B30: 56021.1 | C30: =G30+J30+L30 -> 24244 | E30: =D30/B30*100 -> 0 | F30: =D30/K30 -> 0 | H30: 36 | I30: 29 | J30: =K30*T30 -> 21547 | K30: 29 | L30: =I30*93 -> 2697 | M30: =I30-K30-N30 -> 0 | O30: =M30/I30*100 -> 0 | P30: =I30/H30*100 -> 80.555556 | Q30: =K30/I30*100 -> 100 | R30: =G30/K30 -> 0 | S30: =(I30-H30)/H30 -> -0.19444444 | T30: 743
A31: V2-V7 Combo | B31: 24137 | C31: =G31+J31+L31 -> 10816 | E31: =D31/B31*100 -> 0 | F31: =D31/K31 -> 0 | H31: 16 | I31: 13 | J31: =K31*T31 -> 9607 | K31: 13 | L31: =I31*93 -> 1209 | M31: =I31-K31-N31 -> 0 | O31: =M31/I31*100 -> 0 | P31: =I31/H31*100 -> 81.25 | Q31: =K31/I31*100 -> 100 | R31: =G31/K31 -> 0 | S31: =(I31-H31)/H31 -> -0.1875 | T31: 739
A32: V1-V2 Combo | B32: 55191.59 | C32: =G32+J32+L32 -> 17555 | E32: =D32/B32*100 -> 0 | F32: =D32/K32 -> 0 | H32: 32 | I32: 31 | J32: =K32*T32 -> 14672 | K32: 28 | L32: =I32*93 -> 2883 | M32: =I32-K32-N32 -> 3 | O32: =M32/I32*100 -> 9.6774194 | P32: =I32/H32*100 -> 96.875 | Q32: =K32/I32*100 -> 90.322581 | R32: =G32/K32 -> 0 | S32: =(I32-H32)/H32 -> -0.03125 | T32: 524
A33: V6-V4 Combo | B33: 10286.34 | C33: =G33+J33+L33 -> 3510 | E33: =D33/B33*100 -> 0 | F33: =D33/K33 -> 0 | H33: 6 | I33: 6 | J33: =K33*T33 -> 2952 | K33: 6 | L33: =I33*93 -> 558 | M33: =I33-K33-N33 -> 0 | O33: =M33/I33*100 -> 0 | P33: =I33/H33*100 -> 100 | Q33: =K33/I33*100 -> 100 | R33: =G33/K33 -> 0 | T33: 492
A34: V2-V4 Combo | B34: 28689.54 | C34: =G34+J34+L34 -> 11132 | E34: =D34/B34*100 -> 0 | F34: =D34/K34 -> 0 | H34: 20 | I34: 20 | J34: =K34*T34 -> 9272 | K34: 19 | L34: =I34*93 -> 1860 | M34: =I34-K34-N34 -> 1 | O34: =M34/I34*100 -> 5 | P34: =I34/H34*100 -> 100 | Q34: =K34/I34*100 -> 95 | R34: =G34/K34 -> 0 | T34: 488
A35: Total | B35: =sum(B4:B34)+160000 -> 5920353.7 | G35: 4131781 | H35: =SUM(H4:H34) -> 5974 | I35: =SUM(I4:I34) -> 5634 | J35: =SUM(J4:J34) -> 1923952 | K35: =SUM(K4:K34) -> 5021 | L35: =SUM(L4:L34) -> 523962 | M35: =SUM(M4:M34) -> 564 | N35: =SUM(N4:N34) -> 49 | O35: =M35/K35 -> 0.11232822 | P35: =I35/H35 -> 0.94308671 | Q35: =K35/H35 -> 0.84047539 | R35: =SUM(R4:R34) -> #DIV/0!
D38: Blended
A39: Total Units Sold | B39: =K35 -> 5021
A40: Total Revenue | B40: =B35 -> 5920353.7 | D40: COGS | E40: =B41/B39 -> 383.18104
A41: COGS | B41: =J35 -> 1923952 | D41: CAC | E41: =G35/B39 -> 822.90002
A42: Logistics | B42: =L35 -> 523962 | D42: Logistics | E42: =B42/B39 -> 104.35411
A43: Marketing | B43: =G35 -> 4131781 | D43: AOV | E43: =B40/B39 -> 1179.1184
A44: P&L | B44: =B40-(B41+B42+B43) -> -659341.35
A45: P&L %
A48: Sept | B48: Amazon
B50: Total revenue | C50: Total expense | D50: Total P/L | E50: Profit % | F50: P/pcs | G50: Total orders | H50: Product expense | I50: Delivered | J50: Return | K50: Amazon expense | L50: RTO% | M50: Only Ad spend | N50: Return GMV
A51: V1 | B51: =1282967.14+210.6+12986.45+85579.32 -> 1381743.5 | C51: =K51+H51+M51 -> 738498.18 | D51: =B51-C51 -> 643245.33 | E51: =D51/B51*100 -> 46.553165 | F51: =D51/I51 -> 412.86607 | G51: =1600+1+8+66 -> 1675 | H51: =220*I51 -> 342760 | I51: =1485+7+66 -> 1558 | J51: =G51-I51 -> 117 | K51: =(361233.87+563.39+2347.07+15863.59)-(150548.09) -> 229459.83 | L51: =J51/I51*100 -> 7.5096277 | M51: 166278.35 | N51: =J51*999 -> 116883 | O51: =B51/M51 -> 8.3098221 | P51: =B51/#REF!*100 -> #REF!
A52: V2 | B52: 1053340.5 | C52: =K52+H52+M52 -> 593950.11 | D52: =B52-C52 -> 459390.42 | E52: =D52/B52*100 -> 43.612717 | F52: =D52/I52 -> 414.98683 | G52: =1189 -> 1189 | H52: =304*I52 -> 336528 | I52: =1107 -> 1107 | J52: =G52-I52 -> 82 | K52: =(204827.82)-(27004.57) -> 177823.25 | L52: =J52/G52*100 -> 6.8965517 | M52: 79598.86 | N52: =J52*1119 -> 91758 | O52: =B52/M52 -> 13.233111 | P52: =B52/#REF!*100 -> #REF!
A53: V3 | B53: =2426.14+555.82 -> 2981.96 | C53: =K53+H53+M53 -> 6774.78 | D53: =B53-C53 -> -3792.82 | E53: =D53/B53*100 -> -127.19218 | F53: =D53/I53 -> -1896.41 | G53: =4+4 -> 8 | H53: =662*I53 -> 1324 | I53: =2 -> 2 | J53: =G53-I53 -> 6 | K53: =(3040.42+2410.36)-(1896.11) -> 3554.67 | L53: =J53/G53*100 -> 75 | M53: 1896.11 | N53: =J53*1799 -> 10794 | O53: =B53/M53 -> 1.5726725 | P53: =B53/#REF!*100 -> #REF!
A54: V4 | B54: =10367.3+177437.51 -> 187804.81 | C54: =K54+H54+M54 -> 146669.25 | D54: =B54-C54 -> 41135.56 | E54: =D54/B54*100 -> 21.903358 | F54: =D54/I54 -> 92.647658 | G54: =16+458 -> 474 | H54: =184*I54 -> 81696 | I54: =16+428 -> 444 | J54: =G54-I54 -> 30 | K54: =(1733.26+54510.3)-(21527.99) -> 34715.57 | L54: =J54/G54*100 -> 6.3291139 | M54: 30257.68 | N54: =J54*499 -> 14970 | O54: =B54/M54 -> 6.2068477 | P54: =B54/#REF!*100 -> #REF!
A55: V6 | B55: =529028.26+13041 -> 542069.26 | C55: =K55+H55+M55 -> 391282.29 | D55: =B55-C55 -> 150786.97 | E55: =D55/B55*100 -> 27.81692 | F55: =D55/I55 -> 265.93822 | G55: =594+9 -> 603 | H55: =308*I55 -> 174636 | I55: =558+9 -> 567 | J55: =G55-I55 -> 36 | K55: =(188241.09+2429.33)-(95699.61+18.57) -> 94952.24 | L55: =J55/G55*100 -> 5.9701493 | M55: 121694.05 | N55: =J55*1249 -> 44964 | O55: =B55/M55 -> 4.4543612 | P55: =B55/#REF!*100 -> #REF!
A56: V7 | B56: =64596.27 -> 64596.27 | C56: =K56+H56+M56 -> 69044.72 | D56: =B56-C56 -> -4448.45 | E56: =D56/B56*100 -> -6.8865431 | F56: =D56/I56 -> -74.140833 | G56: =62 -> 62 | H56: =435*I56 -> 26100 | I56: =60 -> 60 | J56: =G56-I56 -> 2 | K56: =(35767.3)-(24808.01) -> 10959.29 | L56: =J56/G56*100 -> 3.2258065 | M56: 31985.43 | N56: =J56*1349 -> 2698 | O56: =B56/M56 -> 2.019553 | P56: =B56/#REF!*100 -> #REF!
A57: V9 | B57: =75198.13+229796.07 -> 304994.2 | C57: =K57+H57+M57 -> 229830.82 | D57: =B57-C57 -> 75163.38 | E57: =D57/B57*100 -> 24.6442 | F57: =D57/I57 -> 455.53564 | G57: =39+157 -> 196 | H57: =778*I57 -> 128370 | I57: =32+133 -> 165 | J57: =G57-I57 -> 31 | K57: =(42167.5+53995.17 )-(28155.87+7664.32) -> 60342.48 | L57: =J57/G57*100 -> 15.816327 | M57: 41118.34 | N57: =J57*1999 -> 61969 | O57: =B57/M57 -> 7.4174736 | P57: =B57/#REF!*100 -> #REF!
A58: V10 | B58: =64163.35+7497 -> 71660.35 | C58: =K58+H58+M58 -> 75093.36 | D58: =B58-C58 -> -3433.01 | E58: =D58/B58*100 -> -4.7906688 | F58: =D58/I58 -> -76.289111 | G58: =43+3 -> 46 | H58: =(900)*I58 -> 40500 | I58: =42+3 -> 45 | J58: =G58-I58 -> 1 | K58: =(19089.19+5259.06)-(8002.47-2972.15) -> 19317.93 | L58: =J58/G58*100 -> 2.173913 | M58: 15275.43 | N58: =J58*999 -> 999 | O58: =B58/M58 -> 4.6912165 | P58: =B58/#REF!*100 -> #REF!
A59: BB | B59: =12277 -> 12277 | C59: =K59+H59+M59 -> 13465.62 | D59: =B59-C59 -> -1188.62 | E59: =D59/B59*100 -> -9.6816812 | F59: =D59/I59 -> -49.525833 | G59: =24 -> 24 | H59: =200*I59 -> 4800 | I59: =24 -> 24 | J59: =G59-I59 -> 0 | K59: =(8538.99)-(6645.1) -> 1893.89 | L59: =J59/G59*100 -> 0 | M59: 6771.73 | N59: =J59*599 -> 0 | O59: =B59/M59 -> 1.8129784 | P59: =B59/#REF!*100 -> #REF!
A60: V1V4 | C60: =K60+H60+M60 -> 0 | D60: =B60-C60 -> 0 | E60: =D60/B60*100 -> #DIV/0! | F60: =D60/I60 -> #DIV/0! | H60: =(270+220)*I60 -> 0 | J60: =G60-I60 -> 0 | L60: =J60/G60*100 -> #DIV/0! | O60: =B60/M60 -> #DIV/0! | P60: =B60/#REF!*100 -> #REF!
A61: V1V2 | B61: =6589.94 -> 6589.94 | C61: =K61+H61+M61 -> 2618.39 | D61: =B61-C61 -> 3971.55 | E61: =D61/B61*100 -> 60.266861 | F61: =D61/I61 -> 1323.85 | G61: =3 -> 3 | H61: =(220+304)*I61 -> 1572 | I61: =3 -> 3 | J61: =G61-I61 -> 0 | K61: =1046.39 -> 1046.39 | L61: =J61/G61*100 -> 0 | N61: =J61*2199 -> 0 | O61: =B61/M61 -> #DIV/0! | P61: =B61/#REF!*100 -> #REF!
A62: V1V6 | B62: =4398 -> 4398 | C62: =K62+H62+M62 -> 1935.76 | D62: =B62-C62 -> 2462.24 | E62: =D62/B62*100 -> 55.985448 | F62: =D62/I62 -> 1231.12 | G62: =2 -> 2 | H62: =(220+308)*I62 -> 1056 | I62: =2 -> 2 | J62: =G62-I62 -> 0 | K62: =879.76 -> 879.76 | L62: =J62/G62*100 -> 0 | N62: =J62*999 -> 0 | O62: =B62/M62 -> #DIV/0! | P62: =B62/#REF!*100 -> #REF!
A63: V2V4 | B63: =12573.04 -> 12573.04 | C63: =K63+H63+M63 -> 8227.34 | D63: =B63-C63 -> 4345.7 | E63: =D63/B63*100 -> 34.563638 | F63: =D63/I63 -> 434.57 | G63: =14 -> 14 | H63: =(304+184)*I63 -> 4880 | I63: =10 -> 10 | J63: =G63-I63 -> 4 | K63: =3341.14 -> 3341.14 | L63: =J63/G63*100 -> 28.571429 | M63: 6.2 | N63: =J63*1499 -> 5996 | O63: =B63/M63 -> 2027.9097 | P63: =B63/#REF!*100 -> #REF!
A64: V2V6 | B64: =6171.28 -> 6171.28 | C64: =K64+H64+M64 -> 2844.07 | D64: =B64-C64 -> 3327.21 | E64: =D64/B64*100 -> 53.914423 | F64: =D64/I64 -> 1109.07 | G64: =3 -> 3 | H64: =(304+308)*I64 -> 1836 | I64: =3 -> 3 | J64: =G64-I64 -> 0 | K64: =1008.07 -> 1008.07 | L64: =J64/G64*100 -> 0 | N64: =J64*999 -> 0 | O64: =B64/M64 -> #DIV/0! | P64: =B64/#REF!*100 -> #REF!
A65: V9V10 | B65: =21288.93 -> 21288.93 | C65: =K65+H65+M65 -> 16289.59 | D65: =B65-C65 -> 4999.34 | E65: =D65/B65*100 -> 23.483285 | F65: =D65/I65 -> 714.19143 | G65: =7 -> 7 | H65: =(1900)*I65 -> 13300 | I65: =7 -> 7 | J65: =G65-I65 -> 0 | K65: =2989.59 -> 2989.59 | L65: =J65/G65*100 -> 0 | N65: =J65*999 -> 0 | O65: =B65/M65 -> #DIV/0! | P65: =B65/#REF!*100 -> #REF!
A66: BB's | B66: =2119.67+1798+16371.62 -> 20289.29 | C66: =K66+H66+M66 -> 23068.21 | D66: =B66-C66 -> -2778.92 | E66: =D66/B66*100 -> -13.696487 | F66: =D66/I66 -> -213.76308 | G66: =3+2+11 -> 16 | H66: =(330)*I66 -> 4290 | I66: =2+2+9 -> 13 | J66: =G66-I66 -> 3 | K66: =(32.87+5410.15+1123.24+7596.4)-(3843.61-456.94+4190.82) -> 6585.17 | L66: =J66/G66*100 -> 18.75 | M66: =8363.86+3829.18 -> 12193.04 | N66: =J66*999 -> 2997 | O66: =B66/M66 -> 1.6640059 | P66: =B66/#REF!*100 -> #REF!
A67: HBB | B67: =13685.26 -> 13685.26 | C67: =K67+H67+M67 -> 13358.4 | D67: =B67-C67 -> 326.86 | E67: =D67/B67*100 -> 2.3884091 | F67: =D67/I67 -> 18.158889 | G67: =19 -> 19 | H67: =(330)*I67 -> 5940 | I67: =18 -> 18 | J67: =G67-I67 -> 1 | K67: =(22412.77)-(20373.05) -> 2039.72 | L67: =J67/G67*100 -> 5.2631579 | M67: 5378.68 | N67: =J67*999 -> 999 | O67: =B67/M67 -> 2.5443529
A68: Total | B68: =SUM(B51:B67) -> 3706463.6 | C68: =SUM(C51:C67) -> 2332950.9 | D68: =SUM(D51:D67) -> 1373512.7 | G68: =SUM(G51:G67) -> 4341 | H68: =SUM(H51:H67) -> 1169588 | I68: =SUM(I51:I67) -> 4028 | K68: =SUM(K51:K67) -> 650908.99 | M68: =SUM(M51:M67) -> 512453.9
A71: Total Revenue | B71: =B68 -> 3706463.6
A72: COGS | B72: =H68 -> 1169588 | D72: Blended
A73: Amazon Ex | B73: 449509 | D73: COGS | E73: =B72/I68 -> 290.36445
A74: Logi | B74: 201400
A75: Marketing | B75: =M68 -> 512453.9 | D75: CAC | E75: =B75/I68 -> 127.22291
A76: Net P&L | B76: =B71-SUM(B72:B75) -> 1373512.7 | D76: Commisions | E76: =B73/I68 -> 111.59608
A77: P&L % | B77: =B76/B71*100 -> 37.057229 | D77: AOV | E77: =B71/I68 -> 920.17468
A84: Sept | B84: Flipkart
B86: Total revenue | C86: Total expense | D86: Total P/L | E86: Profit % | F86: P/pcs | G86: Total orders | H86: Product expense | I86: Delivered | J86: Return | K86: Flipkart expenses | L86: RTO% | M86: Only Ad spend
A87: V1 | B87: =14454+25865.05 -> 40319.05 | C87: =K87+H87 -> 12835 | D87: =B87-C87 -> 27484.05 | E87: =D87/B87*100 -> 68.166413 | F87: =D87/I87 -> 624.6375 | G87: 56 | H87: =220*I87 -> 9680 | I87: =19 +25 -> 44 | J87: =G87-I87 -> 12 | K87: 3155 | L87: =J87/G87*100 -> 21.428571 | M87: =972+295 -> 1267
A88: V2 | B88: =67932 +24024 -> 91956 | C88: =K88+H88 -> 43668 | D88: =B88-C88 -> 48288 | E88: =D88/B88*100 -> 52.512071 | F88: =D88/I88 -> 435.02703 | G88: 141 | H88: =304*I88 -> 33744 | I88: =82 +29 -> 111 | J88: =G88-I88 -> 30 | K88: =9924 -> 9924 | L88: =J88/G88*100 -> 21.276596 | M88: =1717 -> 1717
A89: V3 | B89: =7688 -> 7688 | C89: =K89+H89 -> 4866 | D89: =B89-C89 -> 2822 | E89: =D89/B89*100 -> 36.706556 | F89: =D89/I89 -> 470.33333 | G89: =10 -> 10 | H89: =662*I89 -> 3972 | I89: =6 -> 6 | J89: =G89-I89 -> 4 | K89: 894 | L89: =J89/G89*100 -> 40 | M89: =126 -> 126
A90: V4 | B90: =47933+1464 -> 49397 | C90: =K90+H90 -> 35225 | D90: =B90-C90 -> 14172 | E90: =D90/B90*100 -> 28.690001 | F90: =D90/I90 -> 110.71875 | G90: =194+4 -> 198 | H90: =184*I90 -> 23552 | I90: =126+2 -> 128 | J90: =G90-I90 -> 70 | K90: =11673 -> 11673 | L90: =J90/G90*100 -> 35.353535 | M90: =3024+242 -> 3266
A91: BB | B91: =2160 -> 2160 | C91: =K91+H91 -> 2184 | D91: =B91-C91 -> -24 | E91: =D91/B91*100 -> -1.1111111 | F91: =D91/I91 -> -4.8 | G91: =9 -> 9 | H91: =270*I91 -> 1350 | I91: =5 -> 5 | J91: =G91-I91 -> 4 | K91: 834 | L91: =J91/G91*100 -> 44.444444 | M91: =1207 -> 1207
A92: V6 | B92: =22370 +45712.61 -> 68082.61 | C92: =K92+H92 -> 25631 | D92: =B92-C92 -> 42451.61 | E92: =D92/B92*100 -> 62.353088 | F92: =D92/I92 -> 606.45157 | G92: 85 | H92: =308*I92 -> 21560 | I92: =23 +47 -> 70 | J92: =G92-I92 -> 15 | K92: 4071 | L92: =J92/G92*100 -> 17.647059 | M92: =1206 -> 1206
A93: V7 | B93: =2955 -> 2955 | C93: =K93+H93 -> 1756 | D93: =B93-C93 -> 1199 | E93: =D93/B93*100 -> 40.575296 | F93: =D93/I93 -> 399.66667 | G93: =4 -> 4 | H93: =435*I93 -> 1305 | I93: =3 -> 3 | J93: =G93-I93 -> 1 | K93: 451 | L93: =J93/G93*100 -> 25 | M93: =137 -> 137
A94: Wooden cal | B94: =496 -> 496 | C94: =K94+H94 -> 237 | D94: =B94-C94 -> 259 | E94: =D94/B94*100 -> 52.217742 | F94: =D94/I94 -> 259 | G94: =3 -> 3 | H94: =200*I94 -> 200 | I94: =1 -> 1 | J94: =G94-I94 -> 2 | K94: 37 | L94: =J94/G94*100 -> 66.666667 | M94: =428 -> 428
A95: V9 | B95: =26604+1563 -> 28167 | C95: =K95+H95 -> 19755 | D95: =B95-C95 -> 8412 | E95: =D95/B95*100 -> 29.864735 | F95: =D95/I95 -> 442.73684 | G95: =32+3 -> 35 | H95: =778*I95 -> 14782 | I95: =18+1 -> 19 | J95: =G95-I95 -> 16 | K95: =4355+618 -> 4973 | L95: =J95/G95*100 -> 45.714286 | M95: =248 -> 248
A96: V10 | B96: =6660 -> 6660 | C96: =K96+H96+M96 -> 4027 | D96: =B96-C96 -> 2633 | E96: =D96/B96*100 -> 39.534535 | F96: =D96/I96 -> 526.6 | G96: =12 -> 12 | H96: =(330)*I96 -> 1650 | I96: =5 -> 5 | J96: =G96-I96 -> 7 | K96: 2063 | L96: =J96/G96*100 -> 58.333333 | M96: =314 -> 314 | N96: =J96*999 -> 6993
A97: V1Cal | B97: 0 | C97: =K97+H97 -> 6 | D97: =B97-C97 -> -6 | E97: =D97/B97*100 -> #DIV/0! | F97: =D97/I97 -> #DIV/0! | G97: 1 | H97: =(220+350)*I97 -> 0 | I97: 0 | J97: =G97-I97 -> 1 | K97: 6 | L97: =J97/G97*100 -> 100
A98: V1V4 | B98: =10152 -> 10152 | C98: =K98+H98 -> 5181 | D98: =B98-C98 -> 4971 | E98: =D98/B98*100 -> 48.965721 | F98: =D98/I98 -> 552.33333 | G98: =15 -> 15 | H98: =(220+184)*I98 -> 3636 | I98: =9 -> 9 | J98: =G98-I98 -> 6 | K98: 1545 | L98: =J98/G98*100 -> 40 | M98: =437 -> 437
A99: V6V2 | B99: =22343 -> 22343 | C99: =K99+H99 -> 11810 | D99: =B99-C99 -> 10533 | E99: =D99/B99*100 -> 47.142282 | F99: =D99/I99 -> 810.23077 | G99: =20 -> 20 | H99: =(304+308)*I99 -> 7956 | I99: =13 -> 13 | J99: =G99-I99 -> 7 | K99: 3854 | L99: =J99/G99*100 -> 35 | M99: =3370 -> 3370
A100: V1V2 | B100: =21255 -> 21255 | C100: =K100+H100 -> 9888 | D100: =B100-C100 -> 11367 | E100: =D100/B100*100 -> 53.479181 | F100: =D100/I100 -> 874.38462 | G100: =21 -> 21 | H100: =(220+304)*I100 -> 6812 | I100: =13 -> 13 | J100: =G100-I100 -> 8 | K100: 3076 | L100: =J100/G100*100 -> 38.095238 | M100: =2584 -> 2584
B101: =SUM(B87:B100) -> 351630.66 | C101: =SUM(C87:C100) -> 177069 | D101: =SUM(D87:D100) -> 174561.66 | G101: =SUM(G87:G100) -> 610 | H101: =SUM(H87:H100) -> 130199 | I101: =SUM(I87:I100) -> 427 | J101: =SUM(J87:J100) -> 183 | K101: =SUM(K87:K100) -> 46556 | M101: =SUM(M87:M100) -> 16307
A104: Total Revenue | B104: =B101 -> 351630.66
A105: COGS | B105: =H101 -> 130199
A106: Flipkart Ex | B106: =K101 -> 46556 | D106: COGS | E106: =B105/$I$101 -> 304.91569
A107: Marketing | B107: =M101 -> 16307 | D107: CAC | E107: =B106/$I$101 -> 109.03045
A108: Net P&L | B108: =B104-SUM(B105:B107) -> 158568.66 | D108: Commisions | E108: =B107/$I$101 -> 38.189696
A109: P&L % | B109: =B108/B104*100 -> 45.095231 | D109: AOV | E109: =B108/$I$101 -> 371.35518
A114: Sept | B114: Blinkit
B116: Total revenue | C116: Total expense | D116: Total P/L | E116: Profit % | F116: P/pcs | G116: Product exp | H116: Total orders | I116: Blinkit exp | J116: Ads | K116: Logistics
A117: V1 | B117: =689*H117 -> 158470 | C117: =J117+G117+I117+K117 -> 55200 | D117: =B117-C117 -> 103270 | E117: =D117/B117*100 -> 65.166909 | F117: =D117/H117 -> 449 | G117: =220*H117 -> 50600 | H117: 230 | I117: 0 | J117: 0 | K117: =20*H117 -> 4600 | M117: 59209
A118: V4 | B118: =359*H118 -> 80057 | C118: =J118+G118+I118+K118 -> 45492 | D118: =B118-C118 -> 34565 | E118: =D118/B118*100 -> 43.175487 | F118: =D118/H118 -> 155 | G118: =184*H118 -> 41032 | H118: 223 | I118: 0 | J118: 0 | K118: =20*H118 -> 4460
A119: V2 | B119: =781*H119 -> 119493 | C119: =J119+G119+I119+K119 -> 49572 | D119: =B119-C119 -> 69921 | E119: =D119/B119*100 -> 58.514725 | F119: =D119/H119 -> 457 | G119: =304*H119 -> 46512 | H119: 153 | I119: 0 | J119: =L119%*M119 -> 0 | K119: =20*H119 -> 3060
A120: V6 | B120: =843*H120 -> 153426 | C120: =J120+G120+I120+K120 -> 59696 | D120: =B120-C120 -> 93730 | E120: =D120/B120*100 -> 61.09134 | F120: =D120/H120 -> 515 | G120: =308*H120 -> 56056 | H120: 182 | I120: 0 | J120: =L120%*M120 -> 0 | K120: =20*H120 -> 3640
B121: =SUM(B117:B120) -> 511446 | C121: =SUM(C117:C120) -> 209960 | D121: =SUM(D117:D120) -> 301486 | E121: =SUM(E117:E120) -> 227.94846 | F121: =SUM(F117:F120) -> 1576 | G121: =SUM(G117:G120) -> 194200 | H121: =SUM(H117:H120) -> 788 | J121: =162565 -> 162565 | K121: =SUM(K117:K120) -> 15760
A124: Total Revenue | B124: =B121 -> 511446 | D124: Blended | E124: 125/pcs
...

Sheet Oct 25
A1: OCT | B1: Shopify
A3: Products | B3: Total Dilivered Revenue | C3: Total expense | D3: Total P/L | E3: Profit % | F3: P/pcs | G3: Ad spent | H3: Total orders | I3: Shipped | J3: Total COGS | K3: Delivered | L3: Shipping charges | M3: RTO | N3: In-transit | O3: RTO% | P3: Shipped% | Q3: Delivered % | R3: CPD | S3: Cancellation % | T3: COGS/Unit
A4: V1 | B4: 1196483.1 | C4: =G4+J4+L4 -> 551420 | E4: =D4/B4*100 -> 0 | F4: =D4/K4 -> 0 | H4: 2038 | I4: 2000 | J4: =K4*T4 -> 365420 | K4: 1661 | L4: =I4*93 -> 186000 | M4: =I4-K4-N4 -> 154 | N4: 185 | O4: =IFERROR(M4/I4*100,0) -> 7.7 | P4: =I4/H4*100 -> 98.135427 | Q4: =K4/I4*100 -> 83.05 | R4: =G4/K4 -> 0 | S4: =(I4-H4)/H4 -> -0.018645731 | T4: 220 | V4: V1 | W4: =T4 -> 220
A5: V1- P of 2 | B5: 31703.54 | C5: =G5+J5+L5 -> 12098 | E5: =D5/B5*100 -> 0 | F5: =D5/K5 -> 0 | H5: 26 | I5: 26 | J5: =K5*T5 -> 9680 | K5: 22 | L5: =I5*93 -> 2418 | M5: =I5-K5-N5 -> 2 | N5: 2 | O5: =IFERROR(M5/I5*100,0) -> 7.6923077 | P5: =I5/H5*100 -> 100 | Q5: =K5/I5*100 -> 84.615385 | R5: =G5/K5 -> 0 | S5: =(I5-H5)/H5 -> 0 | T5: 440 | V5: V2 | W5: 304
A6: V2 | B6: 2149467.1 | C6: =G6+J6+L6 -> 1006528 | E6: =D6/B6*100 -> 0 | F6: =D6/K6 -> 0 | H6: 2968 | I6: 2896 | J6: =K6*T6 -> 737200 | K6: 2425 | L6: =I6*93 -> 269328 | M6: =I6-K6-N6 -> 310 | N6: 161 | O6: =IFERROR(M6/I6*100,0) -> 10.70442 | P6: =I6/H6*100 -> 97.574124 | Q6: =K6/I6*100 -> 83.736188 | R6: =G6/K6 -> 0 | S6: =(I6-H6)/H6 -> -0.02425876 | T6: 304 | V6: V3 | W6: 662
A7: V2- P of 2 | B7: 70141.54 | C7: =G7+J7+L7 -> 30000 | E7: =D7/B7*100 -> 0 | F7: =D7/K7 -> 0 | H7: 50 | I7: 48 | J7: =K7*T7 -> 25536 | K7: 42 | L7: =I7*93 -> 4464 | M7: =I7-K7-N7 -> 4 | N7: 2 | O7: =IFERROR(M7/I7*100,0) -> 8.3333333 | P7: =I7/H7*100 -> 96 | Q7: =K7/I7*100 -> 87.5 | R7: =G7/K7 -> 0 | S7: =(I7-H7)/H7 -> -0.04 | T7: 608 | V7: V4 | W7: 184
A8: V3 | B8: 177154.23 | C8: =G8+J8+L8 -> 91754 | E8: =D8/B8*100 -> 0 | F8: =D8/K8 -> 0 | H8: 177 | I8: 168 | J8: =K8*T8 -> 76130 | K8: 115 | L8: =I8*93 -> 15624 | M8: =I8-K8-N8 -> 8 | N8: 45 | O8: =IFERROR(M8/I8*100,0) -> 4.7619048 | P8: =I8/H8*100 -> 94.915254 | Q8: =K8/I8*100 -> 68.452381 | R8: =G8/K8 -> 0 | S8: =(I8-H8)/H8 -> -0.050847458 | T8: 662 | V8: V5
A9: V4 | B9: 117929.53 | C9: =G9+J9+L9 -> 78963 | E9: =D9/B9*100 -> 0 | F9: =D9/K9 -> 0 | H9: 308 | I9: 303 | J9: =K9*T9 -> 50784 | K9: 276 | L9: =I9*93 -> 28179 | M9: =I9-K9-N9 -> 19 | N9: 8 | O9: =IFERROR(M9/I9*100,0) -> 6.2706271 | P9: =I9/H9*100 -> 98.376623 | Q9: =K9/I9*100 -> 91.089109 | R9: =G9/K9 -> 0 | S9: =(I9-H9)/H9 -> -0.016233766 | T9: 184 | V9: V6 | W9: 308
A10: V4- P of 2 | B10: 25139.86 | C10: =G10+J10+L10 -> 14756 | E10: =D10/B10*100 -> 0 | F10: =D10/K10 -> 0 | H10: 37 | I10: 36 | J10: =K10*T10 -> 11408 | K10: 31 | L10: =I10*93 -> 3348 | M10: =I10-K10-N10 -> 4 | N10: 1 | O10: =IFERROR(M10/I10*100,0) -> 11.111111 | P10: =I10/H10*100 -> 97.297297 | Q10: =K10/I10*100 -> 86.111111 | R10: =G10/K10 -> 0 | S10: =(I10-H10)/H10 -> -0.027027027 | T10: 368 | V10: V7
A11: V4- P of 3 | B11: 2368.1 | C11: =G11+J11+L11 -> 922 | E11: =D11/B11*100 -> 0 | F11: =D11/K11 -> 0 | H11: 2 | I11: 2 | J11: =K11*T11 -> 736 | K11: 2 | L11: =I11*93 -> 186 | M11: =I11-K11-N11 -> 0 | O11: =IFERROR(M11/I11*100,0) -> 0 | P11: =I11/H11*100 -> 100 | Q11: =K11/I11*100 -> 100 | R11: =G11/K11 -> 0 | S11: =(I11-H11)/H11 -> 0 | T11: 368 | V11: V8 | W11: 699
A12: V5 | B12: 0 | C12: 0 | E12: 0 | F12: 0 | H12: 0 | I12: 0 | J12: 0 | K12: 0 | L12: =I12*93 -> 0 | M12: =I12-K12-N12 -> 0 | O12: =IFERROR(M12/I12*100,0) -> 0 | P12: =I12/H12*100 -> #DIV/0! | Q12: =K12/I12*100 -> #DIV/0! | S12: =(I12-H12)/H12 -> #DIV/0! | T12: 206 | V12: V9 | W12: 778
A13: V6 | B13: 1913522 | C13: =G13+J13+L13 -> 926317 | E13: =D13/B13*100 -> 0 | F13: =D13/K13 -> 0 | H13: 2755 | I13: 2681 | J13: =K13*T13 -> 676984 | K13: 2198 | L13: =I13*93 -> 249333 | M13: =I13-K13-N13 -> 263 | N13: 220 | O13: =IFERROR(M13/I13*100,0) -> 9.8097725 | P13: =I13/H13*100 -> 97.313975 | Q13: =K13/I13*100 -> 81.984334 | R13: =G13/K13 -> 0 | S13: =(I13-H13)/H13 -> -0.026860254 | T13: 308 | V13: V10 | W13: 780
A14: V6- P of 2 | B14: 66895.66 | C14: =G14+J14+L14 -> 28488 | E14: =D14/B14*100 -> 0 | F14: =D14/K14 -> 0 | H14: 51 | I14: 48 | J14: =K14*T14 -> 24024 | K14: 39 | L14: =I14*93 -> 4464 | M14: =I14-K14-N14 -> 3 | N14: 6 | O14: =IFERROR(M14/I14*100,0) -> 6.25 | P14: =I14/H14*100 -> 94.117647 | Q14: =K14/I14*100 -> 81.25 | R14: =G14/K14 -> 0 | S14: =(I14-H14)/H14 -> -0.058823529 | T14: 616
A15: V7 | B15: 0 | C15: =G15+J15+L15 -> 0 | E15: =D15/B15*100 -> #DIV/0! | F15: =D15/K15 -> #DIV/0! | H15: 0 | I15: 0 | J15: =K15*T15 -> 0 | K15: 0 | L15: =I15*93 -> 0 | M15: =I15-K15-N15 -> 0 | O15: =IFERROR(M15/I15*100,0) -> 0 | P15: =I15/H15*100 -> #DIV/0! | Q15: =K15/I15*100 -> #DIV/0! | R15: =G15/K15 -> #DIV/0! | S15: =(I15-H15)/H15 -> #DIV/0! | T15: 435
A16: V8 | B16: 18926.61 | C16: 0 | E16: =D16/B16*100 -> 0 | F16: 0 | H16: 27 | I16: 14 | J16: =K16*T16 -> 8388 | K16: 12 | L16: =I16*93 -> 1302 | M16: =I16-K16-N16 -> 2 | O16: =IFERROR(M16/I16*100,0) -> 14.285714 | P16: =I16/H16*100 -> 51.851852 | Q16: =K16/I16*100 -> 85.714286 | S16: =(I16-H16)/H16 -> -0.48148148 | T16: 699
A17: V9 | B17: 1758860.6 | C17: =G17+J17+L17 -> 971694 | E17: =D17/B17*100 -> 0 | F17: =D17/K17 -> 0 | H17: 1330 | I17: 1288 | J17: =K17*T17 -> 851910 | K17: 1095 | L17: =I17*93 -> 119784 | M17: =I17-K17-N17 -> 101 | N17: 92 | O17: =IFERROR(M17/I17*100,0) -> 7.8416149 | P17: =I17/H17*100 -> 96.842105 | Q17: =K17/I17*100 -> 85.015528 | R17: =G17/K17 -> 0 | S17: =(I17-H17)/H17 -> -0.031578947 | T17: 778
A18: V9 P of 2 | B18: 52504.46 | C18: =G18+J18+L18 -> 33073 | E18: =D18/B18*100 -> 0 | F18: =D18/K18 -> 0 | H18: 23 | I18: 21 | J18: =K18*T18 -> 31120 | K18: 20 | L18: =I18*93 -> 1953 | M18: =I18-K18-N18 -> 0 | N18: 1 | O18: =IFERROR(M18/I18*100,0) -> 0 | P18: =I18/H18*100 -> 91.304348 | Q18: =K18/I18*100 -> 95.238095 | R18: =G18/K18 -> 0 | S18: =(I18-H18)/H18 -> -0.086956522 | T18: 1556
A19: V10 | B19: 15703.28 | C19: =G19+J19+L19 -> 10104 | E19: =D19/B19*100 -> 0 | F19: =D19/K19 -> 0 | H19: 43 | I19: 11 | J19: =K19*T19 -> 9081 | K19: 9 | L19: =I19*93 -> 1023 | M19: =I19-K19-N19 -> 1 | N19: 1 | O19: =IFERROR(M19/I19*100,0) -> 9.0909091 | P19: =I19/H19*100 -> 25.581395 | Q19: =K19/I19*100 -> 81.818182 | R19: =G19/K19 -> 0 | S19: =(I19-H19)/H19 -> -0.74418605 | T19: 1009
A20: Busy Book | B20: 0 | C20: 0 | E20: 0 | F20: 0 | H20: 0 | I20: 0 | J20: =K20*T20 -> 0 | K20: 0 | L20: =I20*93 -> 0 | M20: =I20-K20-N20 -> 0 | O20: =IFERROR(M20/I20*100,0) -> 0 | P20: 0 | Q20: 0 | R20: 0 | S20: =(I20-H20)/H20 -> #DIV/0! | T20: 250
A21: Busy Book Pink | B21: 52539.01 | C21: =G21+J21+L21 -> 24768 | E21: =D21/B21*100 -> 0 | F21: =D21/K21 -> 0 | H21: 76 | I21: 76 | J21: =K21*T21 -> 17700 | K21: 59 | L21: =I21*93 -> 7068 | M21: =I21-K21-N21 -> 17 | O21: =IFERROR(M21/I21*100,0) -> 22.368421 | P21: =I21/H21*100 -> 100 | Q21: =K21/I21*100 -> 77.631579 | R21: =G21/K21 -> 0 | S21: =(I21-H21)/H21 -> 0 | T21: 300
A22: Busy Book Blue | B22: 169868.97 | C22: =G22+J22+L22 -> 83520 | E22: =D22/B22*100 -> 0 | F22: =D22/K22 -> 0 | H22: 258 | I22: 240 | J22: =K22*T22 -> 61200 | K22: 204 | L22: =I22*93 -> 22320 | M22: =I22-K22-N22 -> 11 | N22: 25 | O22: =IFERROR(M22/I22*100,0) -> 4.5833333 | P22: =I22/H22*100 -> 93.023256 | Q22: =K22/I22*100 -> 85 | R22: =G22/K22 -> 0 | S22: =(I22-H22)/H22 -> -0.069767442 | T22: 300
A23: Human Book | B23: 0 | C23: =G23+J23+L23 -> 0 | E23: =D23/B23*100 -> #DIV/0! | F23: =D23/K23 -> #DIV/0! | H23: 0 | I23: 0 | J23: =K23*T23 -> 0 | K23: 0 | L23: =I23*93 -> 0 | M23: =I23-K23-N23 -> -14 | N23: 14 | O23: =IFERROR(M23/I23*100,0) -> 0 | P23: =I23/H23*100 -> #DIV/0! | Q23: =K23/I23*100 -> #DIV/0! | R23: =G23/K23 -> #DIV/0! | S23: =(I23-H23)/H23 -> #DIV/0! | T23: 300
A24: V9-V3 Combo | B24: 71297.16 | C24: =G24+J24+L24 -> 36003 | E24: =D24/B24*100 -> 0 | F24: =D24/K24 -> 0 | H24: 37 | I24: 31 | J24: =K24*T24 -> 33120 | K24: 23 | L24: =I24*93 -> 2883 | M24: =I24-K24-N24 -> 2 | N24: 6 | O24: =IFERROR(M24/I24*100,0) -> 6.4516129 | P24: =I24/H24*100 -> 83.783784 | Q24: =K24/I24*100 -> 74.193548 | R24: =G24/K24 -> 0 | S24: =(I24-H24)/H24 -> -0.16216216 | T24: 1440
A25: V9-V10 Combo | B25: 6654.09 | C25: =G25+J25+L25 -> 3760 | E25: =D25/B25*100 -> 0 | F25: =D25/K25 -> 0 | H25: 15 | I25: 2 | J25: =K25*T25 -> 3574 | K25: 2 | L25: =I25*93 -> 186 | M25: =I25-K25-N25 -> 0 | O25: =IFERROR(M25/I25*100,0) -> 0 | P25: =I25/H25*100 -> 13.333333 | Q25: =K25/I25*100 -> 100 | R25: =G25/K25 -> 0 | S25: =(I25-H25)/H25 -> -0.86666667 | T25: 1787
A26: V7-V4 Combo | B26: 0 | C26: =G26+J26+L26 -> 0 | E26: =D26/B26*100 -> #DIV/0! | F26: =D26/K26 -> #DIV/0! | H26: 0 | I26: 0 | J26: =K26*T26 -> 0 | K26: 0 | L26: =I26*93 -> 0 | M26: =I26-K26-N26 -> 0 | O26: =IFERROR(M26/I26*100,0) -> 0 | P26: =I26/H26*100 -> #DIV/0! | Q26: =K26/I26*100 -> #DIV/0! | R26: =G26/K26 -> #DIV/0! | S26: =(I26-H26)/H26 -> #DIV/0! | T26: 619
A27: V1-V4 Combo | B27: 36478.75 | C27: =G27+J27+L27 -> 15375 | E27: =D27/B27*100 -> 0 | F27: =D27/K27 -> 0 | H27: 36 | I27: 35 | J27: =K27*T27 -> 12120 | K27: 30 | L27: =I27*93 -> 3255 | M27: =I27-K27-N27 -> 1 | N27: 4 | O27: =IFERROR(M27/I27*100,0) -> 2.8571429 | P27: =I27/H27*100 -> 97.222222 | Q27: =K27/I27*100 -> 85.714286 | R27: =G27/K27 -> 0 | S27: =(I27-H27)/H27 -> -0.027777778 | T27: 404
A28: V1-V7 Combo | B28: 0 | C28: =G28+J28+L28 -> 0 | E28: =D28/B28*100 -> #DIV/0! | F28: =D28/K28 -> #DIV/0! | H28: 0 | I28: 0 | J28: =K28*T28 -> 0 | K28: 0 | L28: =I28*93 -> 0 | M28: =I28-K28-N28 -> 0 | O28: =IFERROR(M28/I28*100,0) -> 0 | P28: =I28/H28*100 -> #DIV/0! | Q28: =K28/I28*100 -> #DIV/0! | R28: =G28/K28 -> #DIV/0! | S28: =(I28-H28)/H28 -> #DIV/0! | T28: 655
A29: V6-V2 Combo | B29: 20022.39 | C29: =G29+J29+L29 -> 7236 | E29: =D29/B29*100 -> 0 | F29: =D29/K29 -> 0 | H29: 14 | I29: 12 | J29: =K29*T29 -> 6120 | K29: 10 | L29: =I29*93 -> 1116 | M29: =I29-K29-N29 -> 2 | O29: =IFERROR(M29/I29*100,0) -> 16.666667 | P29: =I29/H29*100 -> 85.714286 | Q29: =K29/I29*100 -> 83.333333 | R29: =G29/K29 -> 0 | S29: =(I29-H29)/H29 -> -0.14285714 | T29: 612
A30: V6-V7 Combo | B30: 0 | C30: =G30+J30+L30 -> 0 | E30: =D30/B30*100 -> #DIV/0! | F30: =D30/K30 -> #DIV/0! | H30: 0 | I30: 0 | J30: =K30*T30 -> 0 | K30: 0 | L30: =I30*93 -> 0 | M30: =I30-K30-N30 -> 0 | O30: =IFERROR(M30/I30*100,0) -> 0 | P30: =I30/H30*100 -> #DIV/0! | Q30: =K30/I30*100 -> #DIV/0! | R30: =G30/K30 -> #DIV/0! | S30: =(I30-H30)/H30 -> #DIV/0! | T30: 743
A31: V2-V7 Combo | B31: 0 | C31: =G31+J31+L31 -> 0 | E31: =D31/B31*100 -> #DIV/0! | F31: =D31/K31 -> #DIV/0! | H31: 0 | I31: 0 | J31: =K31*T31 -> 0 | K31: 0 | L31: =I31*93 -> 0 | M31: =I31-K31-N31 -> 0 | O31: =IFERROR(M31/I31*100,0) -> 0 | P31: =I31/H31*100 -> #DIV/0! | Q31: =K31/I31*100 -> #DIV/0! | R31: =G31/K31 -> #DIV/0! | S31: =(I31-H31)/H31 -> #DIV/0! | T31: 739
A32: V1-V2 Combo | B32: 51802.92 | C32: =G32+J32+L32 -> 16752 | E32: =D32/B32*100 -> 0 | F32: =D32/K32 -> 0 | H32: 30 | I32: 28 | J32: =K32*T32 -> 14148 | K32: 27 | L32: =I32*93 -> 2604 | M32: =I32-K32-N32 -> 1 | O32: =IFERROR(M32/I32*100,0) -> 3.5714286 | P32: =I32/H32*100 -> 93.333333 | Q32: =K32/I32*100 -> 96.428571 | R32: =G32/K32 -> 0 | S32: =(I32-H32)/H32 -> -0.066666667 | T32: 524
A33: V6-V4 Combo | B33: 1899 | C33: =G33+J33+L33 -> 678 | E33: =D33/B33*100 -> 0 | F33: =D33/K33 -> 0 | H33: 2 | I33: 2 | J33: =K33*T33 -> 492 | K33: 1 | L33: =I33*93 -> 186 | M33: =I33-K33-N33 -> 0 | N33: 1 | O33: =IFERROR(M33/I33*100,0) -> 0 | P33: =I33/H33*100 -> 100 | Q33: =K33/I33*100 -> 50 | R33: =G33/K33 -> 0 | S33: =(I33-H33)/H33 -> 0 | T33: 492
A34: V2-V4 Combo | B34: 10039.47 | C34: =G34+J34+L34 -> 4160 | E34: =D34/B34*100 -> 0 | F34: =D34/K34 -> 0 | H34: 8 | I34: 8 | J34: =K34*T34 -> 3416 | K34: 7 | L34: =I34*93 -> 744 | M34: =I34-K34-N34 -> 1 | O34: =IFERROR(M34/I34*100,0) -> 12.5 | P34: =I34/H34*100 -> 100 | Q34: =K34/I34*100 -> 87.5 | R34: =G34/K34 -> 0 | S34: =(I34-H34)/H34 -> 0 | T34: 488
A35: Total | B35: =sum(B4:B34)+600000 -> 8617401.5 | D35: =SUM(D4:D34) -> 0 | G35: 5116490 | H35: =SUM(H4:H34) -> 10311 | I35: =SUM(I4:I34) -> 9976 | J35: =SUM(J4:J34)+22800 -> 3053091 | K35: =SUM(K4:K34) -> 8310 | L35: =SUM(L4:L34) -> 927768 | M35: =SUM(M4:M34) -> 892 | N35: =SUM(N4:N34) -> 774 | O35: =M35/K35 -> 0.10734055 | P35: =I35/H35 -> 0.96751043 | Q35: =K35/H35 -> 0.80593541 | R35: =SUM(R4:R34) -> #DIV/0!
D38: Blended
A39: Total Units Sold | B39: =K35 -> 8310
A40: Total Revenue | B40: =B35 -> 8617401.5 | D40: COGS | E40: =B41/B39 -> 367.39964
A41: COGS | B41: =J35 -> 3053091 | D41: CAC | E41: =G35/B39 -> 615.70277 | F41: =E41/E43*100 -> 59.373931
A42: Logistics | B42: =L35 -> 927768 | D42: Logistics | E42: =B42/B39 -> 111.64477
A43: Marketing | B43: =G35 -> 5116490 | D43: AOV | E43: =B40/B39 -> 1036.9918
A44: P&L | B44: =B40-(B41+B42+B43) -> -479947.51
A45: P&L % | B45: =B44/B40 -> -0.055695155
A49: Oct | B49: Amazon
B51: Total revenue | C51: Total expense | D51: Total P/L | E51: Profit % | F51: P/pcs | G51: Total orders | H51: Product expense | I51: Delivered | J51: Return | K51: Amazon expense | L51: RTO% | M51: Only Ad spend | N51: Return GMV
A52: V1 | B52: =1089387.77+2588.22+2499 -> 1094475 | C52: =K52+H52+M52 -> 626105.32 | D52: =B52-C52 -> 468369.67 | E52: =D52/B52*100 -> 42.794004 | F52: =D52/I52 -> 336.9566 | G52: =1501+3+1 -> 1505 | H52: =220*I52 -> 305800 | I52: =1386+3+1 -> 1390 | J52: =G52-I52 -> 115 | K52: =(318476.23+405.16+387.39)-(136413.88) -> 182854.9 | L52: =J52/I52*100 -> 8.2733813 | M52: 137450.42 | N52: =J52*999 -> 114885 | O52: =B52/M52 -> 7.9626893 | P52: =B52/#REF!*100 -> #REF!
A53: V2 | B53: =4343.55+1134566.44 -> 1138910 | C53: =K53+H53+M53 -> 645457.72 | D53: =B53-C53 -> 493452.27 | E53: =D53/B53*100 -> 43.326714 | F53: =D53/I53 -> 370.45966 | G53: =3+1453 -> 1456 | H53: =304*I53 -> 404928 | I53: =3+1329 -> 1332 | J53: =G53-I53 -> 124 | K53: =(721.58+196393.86)-(38031.25) -> 159084.19 | L53: =J53/G53*100 -> 8.5164835 | M53: 81445.53 | N53: =J53*1119 -> 138756 | O53: =B53/M53 -> 13.983702 | P53: =B53/#REF!*100 -> #REF!
A54: V3 | B54: =73395.26+1993.24 -> 75388.5 | C54: =K54+H54+M54 -> 66726.57 | D54: =B54-C54 -> 8661.93 | E54: =D54/B54*100 -> 11.489723 | F54: =D54/I54 -> 139.70855 | G54: =61+1 -> 62 | H54: =662*I54 -> 41044 | I54: =61+1 -> 62 | J54: =G54-I54 -> 0 | K54: =(13189.55+1906.47)-1588.19 -> 13507.83 | L54: =J54/G54*100 -> 0 | M54: 12174.74 | N54: =J54*1799 -> 0 | O54: =B54/M54 -> 6.1922062 | P54: =B54/#REF!*100 -> #REF!
A55: V4 | B55: =290251.93 -> 290251.93 | C55: =K55+H55+M55 -> 209885.81 | D55: =B55-C55 -> 80366.12 | E55: =D55/B55*100 -> 27.688402 | F55: =D55/I55 -> 118.88479 | G55: =707 -> 707 | H55: =184*I55 -> 124384 | I55: =676 -> 676 | J55: =G55-I55 -> 31 | K55: =(74956.84)-(29595.12) -> 45361.72 | L55: =J55/G55*100 -> 4.3847242 | M55: 40140.09 | N55: =J55*499 -> 15469 | O55: =B55/M55 -> 7.2309736 | P55: =B55/#REF!*100 -> #REF!
A56: V6 | B56: =598036.91+4340.1 -> 602377.01 | C56: =K56+H56+M56 -> 469566.19 | D56: =B56-C56 -> 132810.82 | E56: =D56/B56*100 -> 22.04779 | F56: =D56/I56 -> 171.59021 | G56: =851+3 -> 854 | H56: =308*I56 -> 238392 | I56: =771+3 -> 774 | J56: =G56-I56 -> 80 | K56: =(203239.64+694.59)-(113209.61+16) -> 90708.62 | L56: =J56/G56*100 -> 9.3676815 | M56: 140465.57 | N56: =J56*1249 -> 99920 | O56: =B56/M56 -> 4.2884317 | P56: =B56/#REF!*100 -> #REF!
A57: V7 | B57: =76648.19 -> 76648.19 | C57: =K57+H57+M57 -> 90273.76 | D57: =B57-C57 -> -13625.57 | E57: =D57/B57*100 -> -17.776767 | F57: =D57/I57 -> -176.95545 | G57: =80 -> 80 | H57: =435*I57 -> 33495 | I57: =77 -> 77 | J57: =G57-I57 -> 3 | K57: =46295.28-31939.1 -> 14356.18 | L57: =J57/G57*100 -> 3.75 | M57: 42422.58 | N57: =J57*1349 -> 4047 | O57: =B57/M57 -> 1.8067781 | P57: =B57/#REF!*100 -> #REF!
A58: V9 | B58: =34650.4+357175.09 -> 391825.49 | C58: =K58+H58+M58 -> 287618.99 | D58: =B58-C58 -> 104206.5 | E58: =D58/B58*100 -> 26.59513 | F58: =D58/I58 -> 425.33265 | G58: =21+259 -> 280 | H58: =778*I58 -> 190610 | I58: =19+226 -> 245 | J58: =G58-I58 -> 35 | K58: =(15189.56+72740.99)-(9384.36+11404.89) -> 67141.3 | L58: =J58/G58*100 -> 12.5 | M58: 29867.69 | N58: =J58*1999 -> 69965 | O58: =B58/M58 -> 13.118708 | P58: =B58/#REF!*100 -> #REF!
A59: V10 | B59: =37142.1 -> 37142.1 | C59: =K59+H59+M59 -> 33559.94 | D59: =B59-C59 -> 3582.16 | E59: =D59/B59*100 -> 9.6444735 | F59: =D59/I59 -> 223.885 | G59: =17 -> 17 | H59: =(900)*I59 -> 14400 | I59: =16 -> 16 | J59: =G59-I59 -> 1 | K59: =(12886.36)-(7209.97) -> 5676.39 | L59: =J59/G59*100 -> 5.8823529 | M59: 13483.55 | N59: =J59*999 -> 999 | O59: =B59/M59 -> 2.7546232 | P59: =B59/#REF!*100 -> #REF!
A60: BB | B60: =5388 -> 5388 | C60: =K60+H60+M60 -> 4188.5 | D60: =B60-C60 -> 1199.5 | E60: =D60/B60*100 -> 22.262435 | F60: =D60/I60 -> 92.269231 | G60: =13 -> 13 | H60: =200*I60 -> 2600 | I60: =13 -> 13 | J60: =G60-I60 -> 0 | K60: =1260.25-409.3 -> 850.95 | L60: =J60/G60*100 -> 0 | M60: 737.55 | N60: =J60*599 -> 0 | O60: =B60/M60 -> 7.3052674 | P60: =B60/#REF!*100 -> #REF!
A61: V1V4 | C61: =K61+H61+M61 -> 0 | D61: =B61-C61 -> 0 | E61: =D61/B61*100 -> #DIV/0! | F61: =D61/I61 -> #DIV/0! | H61: =(270+220)*I61 -> 0 | J61: =G61-I61 -> 0 | L61: =J61/G61*100 -> #DIV/0! | O61: =B61/M61 -> #DIV/0! | P61: =B61/#REF!*100 -> #REF!
A62: V1V2 | B62: =5993.86 -> 5993.86 | C62: =K62+H62+M62 -> 2625.89 | D62: =B62-C62 -> 3367.97 | E62: =D62/B62*100 -> 56.190335 | F62: =D62/I62 -> 1122.6567 | G62: 3 | H62: =(220+304)*I62 -> 1572 | I62: 3 | J62: =G62-I62 -> 0 | K62: =1053.89 -> 1053.89 | L62: =J62/G62*100 -> 0 | N62: =J62*2199 -> 0 | O62: =B62/M62 -> #DIV/0! | P62: =B62/#REF!*100 -> #REF!
A63: V1V6 | C63: =K63+H63+M63 -> 0 | D63: =B63-C63 -> 0 | E63: =D63/B63*100 -> #DIV/0! | F63: =D63/I63 -> #DIV/0! | H63: =(220+308)*I63 -> 0 | J63: =G63-I63 -> 0 | L63: =J63/G63*100 -> #DIV/0! | N63: =J63*999 -> 0 | O63: =B63/M63 -> #DIV/0! | P63: =B63/#REF!*100 -> #REF!
A64: V2V4 | B64: =20904 -> 20904 | C64: =K64+H64+M64 -> 13244.22 | D64: =B64-C64 -> 7659.78 | E64: =D64/B64*100 -> 36.642652 | F64: =D64/I64 -> 425.54333 | G64: =20 -> 20 | H64: =(304+184)*I64 -> 8784 | I64: =18 -> 18 | J64: =G64-I64 -> 2 | K64: =4448.04 -> 4448.04 | L64: =J64/G64*100 -> 10 | M64: 12.18 | N64: =J64*1499 -> 2998 | O64: =B64/M64 -> 1716.2562 | P64: =B64/#REF!*100 -> #REF!
A65: V2V6 | B65: =6288.29 -> 6288.29 | C65: =K65+H65+M65 -> 2894.37 | D65: =B65-C65 -> 3393.92 | E65: =D65/B65*100 -> 53.972066 | F65: =D65/I65 -> 1131.3067 | G65: =3 -> 3 | H65: =(304+308)*I65 -> 1836 | I65: =3 -> 3 | J65: =G65-I65 -> 0 | K65: =1037.64 -> 1037.64 | L65: =J65/G65*100 -> 0 | M65: 20.73 | N65: =J65*999 -> 0 | O65: =B65/M65 -> 303.3425 | P65: =B65/#REF!*100 -> #REF!
A66: V9V10 | C66: =K66+H66+M66 -> 0 | D66: =B66-C66 -> 0 | E66: =D66/B66*100 -> #DIV/0! | F66: =D66/I66 -> #DIV/0! | H66: =(1900)*I66 -> 0 | J66: =G66-I66 -> 0 | L66: =J66/G66*100 -> #DIV/0! | N66: =J66*999 -> 0 | O66: =B66/M66 -> #DIV/0! | P66: =B66/#REF!*100 -> #REF!
A67: BB's | B67: =147323.76+71324.17+1799 -> 220446.93 | C67: =K67+H67+M67 -> 139492.64 | D67: =B67-C67 -> 80954.29 | E67: =D67/B67*100 -> 36.722802 | F67: =D67/I67 -> 299.8307 | G67: =188+91+1 -> 280 | H67: =(330)*I67 -> 89100 | I67: =180+89+1 -> 270 | J67: =G67-I67 -> 10 | K67: =(27601.78+20297.39+271.89 )-(6170.44+9800.19) -> 32200.43 | L67: =J67/G67*100 -> 3.5714286 | M67: 18192.21 | N67: =J67*999 -> 9990 | O67: =B67/M67 -> 12.117655 | P67: =B67/#REF!*100 -> #REF!
A68: HBB | B68: =49627.64 -> 49627.64 | C68: =K68+H68+M68 -> 83530.83 | D68: =B68-C68 -> -33903.19 | E68: =D68/B68*100 -> -68.315136 | F68: =D68/I68 -> -484.33129 | G68: =72 -> 72 | H68: =(330)*I68 -> 23100 | I68: =70 -> 70 | J68: =G68-I68 -> 2 | K68: =60478.47-53420.48 -> 7057.99 | L68: =J68/G68*100 -> 2.7777778 | M68: 53372.84 | N68: =J68*999 -> 1998 | O68: =B68/M68 -> 0.92982948
A69: Total | B69: =SUM(B52:B68) -> 4015666.9 | C69: =SUM(C52:C68) -> 2675170.8 | D69: =SUM(D52:D68) -> 1340496.2 | G69: =SUM(G52:G68) -> 5352 | H69: =SUM(H52:H68) -> 1480045 | I69: =SUM(I52:I68) -> 4949 | K69: 585340.07 | M69: =SUM(M52:M68) -> 569785.68
A72: Total Revenue | B72: =B69 -> 4015666.9
A73: COGS | B73: =H69 -> 1480045 | D73: Blended
A74: Amazon Ex | B74: 337890 | D74: COGS | E74: =B73/I69 -> 299.05941 | I74: =B75/I69 -> 50
A75: Logi | B75: 247450
A76: Marketing | B76: =M69 -> 569785.68 | D76: CAC | E76: =B76/I69 -> 115.13148
A77: Net P&L | B77: =B72-SUM(B73:B76) -> 1380496.2 | D77: Commisions | E77: =B74/I69 -> 68.274399
A78: P&L % | B78: =B77/B72*100 -> 34.377758 | D78: AOV | E78: =B72/I69 -> 811.40976
A85: Oct | B85: Flipkart
B87: Total revenue | C87: Total expense | D87: Total P/L | E87: Profit % | F87: P/pcs | G87: Total orders | H87: Product expense | I87: Delivered | J87: Return | K87: Flipkart expenses | L87: RTO% | M87: Only Ad spend
A88: V1 | B88: =14454 -> 14454 | C88: =K88+H88 -> 7335 | D88: =B88-C88 -> 7119 | E88: =D88/B88*100 -> 49.252802 | F88: =D88/I88 -> 374.68421 | G88: =31 -> 31 | H88: =220*I88 -> 4180 | I88: =19 -> 19 | J88: =G88-I88 -> 12 | K88: =3155 -> 3155 | L88: =J88/G88*100 -> 38.709677 | M88: =318+115 -> 433
A89: V2 | B89: =67129 -> 67129 | C89: =K89+H89 -> 34452 | D89: =B89-C89 -> 32677 | E89: =D89/B89*100 -> 48.677919 | F89: =D89/I89 -> 403.41975 | G89: 112 | H89: =304*I89 -> 24624 | I89: 81 | J89: =G89-I89 -> 31 | K89: 9828 | L89: =J89/G89*100 -> 27.678571 | M89: =2273 -> 2273
A90: V3 | B90: =7688 -> 7688 | C90: =K90+H90 -> 4866 | D90: =B90-C90 -> 2822 | E90: =D90/B90*100 -> 36.706556 | F90: =D90/I90 -> 470.33333 | G90: 10 | H90: =662*I90 -> 3972 | I90: 6 | J90: =G90-I90 -> 4 | K90: 894 | L90: =J90/G90*100 -> 40 | M90: =252 -> 252
A91: V4 | B91: =47933+1464 -> 49397 | C91: =K91+H91 -> 35041 | D91: =B91-C91 -> 14356 | E91: =D91/B91*100 -> 29.062494 | F91: =D91/I91 -> 113.03937 | G91: =194+2 -> 196 | H91: =184*I91 -> 23368 | I91: =126+1 -> 127 | J91: =G91-I91 -> 69 | K91: 11673 | L91: =J91/G91*100 -> 35.204082 | M91: =4201+164 -> 4365
A92: BB | B92: =2160 -> 2160 | C92: =K92+H92 -> 2184 | D92: =B92-C92 -> -24 | E92: =D92/B92*100 -> -1.1111111 | F92: =D92/I92 -> -4.8 | G92: =9 -> 9 | H92: =270*I92 -> 1350 | I92: =5 -> 5 | J92: =G92-I92 -> 4 | K92: =834 -> 834 | L92: =J92/G92*100 -> 44.444444 | M92: =1093 -> 1093
A93: V6 | B93: =22370 -> 22370 | C93: =K93+H93 -> 11155 | D93: =B93-C93 -> 11215 | E93: =D93/B93*100 -> 50.134108 | F93: =D93/I93 -> 487.6087 | G93: =38 -> 38 | H93: =308*I93 -> 7084 | I93: =23 -> 23 | J93: =G93-I93 -> 15 | K93: 4071 | L93: =J93/G93*100 -> 39.473684 | M93: =191 -> 191
A94: V7 | B94: =2955 -> 2955 | C94: =K94+H94 -> 1756 | D94: =B94-C94 -> 1199 | E94: =D94/B94*100 -> 40.575296 | F94: =D94/I94 -> 399.66667 | G94: =4 -> 4 | H94: =435*I94 -> 1305 | I94: =3 -> 3 | J94: =G94-I94 -> 1 | K94: =451 -> 451 | L94: =J94/G94*100 -> 25
A95: Wooden cal | B95: =496 -> 496 | C95: =K95+H95 -> 237 | D95: =B95-C95 -> 259 | E95: =D95/B95*100 -> 52.217742 | F95: =D95/I95 -> 259 | G95: =3 -> 3 | H95: =200*I95 -> 200 | I95: =1 -> 1 | J95: =G95-I95 -> 2 | K95: =37 -> 37 | L95: =J95/G95*100 -> 66.666667
A96: V9 | B96: =26604+1563 -> 28167 | C96: =K96+H96 -> 19934 | D96: =B96-C96 -> 8233 | E96: =D96/B96*100 -> 29.22924 | F96: =D96/I96 -> 433.31579 | G96: =35 -> 35 | H96: =778*I96 -> 14782 | I96: =19 -> 19 | J96: =G96-I96 -> 16 | K96: 5152 | L96: =J96/G96*100 -> 45.714286 | M96: =569 -> 569
A97: V10 | B97: =6660 -> 6660 | C97: =K97+H97+M97 -> 3713 | D97: =B97-C97 -> 2947 | E97: =D97/B97*100 -> 44.249249 | F97: =D97/I97 -> 589.4 | G97: =12 -> 12 | H97: =(330)*I97 -> 1650 | I97: =5 -> 5 | J97: =G97-I97 -> 7 | K97: 2063 | L97: =J97/G97*100 -> 58.333333 | N97: =J97*999 -> 6993
A98: V1Cal | C98: =K98+H98 -> 0 | D98: =B98-C98 -> 0 | E98: =D98/B98*100 -> #DIV/0! | F98: =D98/I98 -> #DIV/0! | G98: 0 | H98: =(220+350)*I98 -> 0 | J98: =G98-I98 -> 0 | L98: =J98/G98*100 -> #DIV/0!
A99: V1V4 | B99: =10152 -> 10152 | C99: =K99+H99 -> 5181 | D99: =B99-C99 -> 4971 | E99: =D99/B99*100 -> 48.965721 | F99: =D99/I99 -> 552.33333 | G99: =15 -> 15 | H99: =(220+184)*I99 -> 3636 | I99: =9 -> 9 | J99: =G99-I99 -> 6 | K99: 1545 | L99: =J99/G99*100 -> 40 | M99: =1322 -> 1322
A100: V6V2 | B100: =23871 -> 23871 | C100: =K100+H100 -> 11810 | D100: =B100-C100 -> 12061 | E100: =D100/B100*100 -> 50.525743 | F100: =D100/I100 -> 927.76923 | G100: 20 | H100: =(304+308)*I100 -> 7956 | I100: 13 | J100: =G100-I100 -> 7 | K100: 3854 | L100: =J100/G100*100 -> 35 | M100: =850 -> 850
A101: V1V2 | B101: =21255 -> 21255 | C101: =K101+H101 -> 9888 | D101: =B101-C101 -> 11367 | E101: =D101/B101*100 -> 53.479181 | F101: =D101/I101 -> 874.38462 | G101: =21 -> 21 | H101: =(220+304)*I101 -> 6812 | I101: =13 -> 13 | J101: =G101-I101 -> 8 | K101: 3076 | L101: =J101/G101*100 -> 38.095238 | M101: =1753 -> 1753
B102: =SUM(B88:B101) -> 256754 | C102: =SUM(C88:C101) -> 147552 | D102: =SUM(D88:D101) -> 109202 | G102: =SUM(G88:G101) -> 506 | H102: =SUM(H88:H101) -> 100919 | I102: =SUM(I88:I101) -> 324 | J102: =SUM(J88:J101) -> 182 | K102: =SUM(K88:K101) -> 46633 | M102: =SUM(M89:M101) -> 12668
A105: Total Revenue | B105: =B102 -> 256754
A106: COGS | B106: =H102 -> 100919 | L106: Total Revenue | M106: 419537
A107: Flipkart Ex | B107: =K102 -> 46633 | D107: COGS | E107: =B106/$I$102 -> 311.4784 | L107: Units | M107: 459
A108: Marketing | B108: =M102 -> 12668 | D108: CAC | E108: =B107/$I$102 -> 143.92901 | L108: AOV | M108: =M106/M107 -> 914.02397
A109: Net P&L | B109: =B105-SUM(B106:B108) -> 96534 | D109: Commisions | E109: =B108/$I$102 -> 39.098765 | L109: Adspend | M109: =M102 -> 12668
A110: P&L % | B110: =B109/B105*100 -> 37.597856 | D110: AOV | E110: =B109/$I$102 -> 297.94444 | L110: Roas | M110: 17
A115: Oct | B115: Blinkit
B117: Total revenue | C117: Total expense | D117: Total P/L | E117: Profit % | F117: P/pcs | G117: Product exp | H117: Total orders | I117: Blinkit exp | J117: Ads | K117: Logistics
A118: V1 | B118: =689*H118 -> 129532 | C118: =J118+G118+I118+K118 -> 45120 | D118: =B118-C118 -> 84412 | E118: =D118/B118*100 -> 65.166909 | F118: =D118/H118 -> 449 | G118: =220*H118 -> 41360 | H118: 188 | I118: 0 | J118: 0 | K118: =20*H118 -> 3760 | M118: 59209
A119: V4 | B119: =359*H119 -> 65697 | C119: =J119+G119+I119+K119 -> 37332 | D119: =B119-C119 -> 28365 | E119: =D119/B119*100 -> 43.175487 | F119: =D119/H119 -> 155 | G119: =184*H119 -> 33672 | H119: 183 | I119: 0 | J119: 0 | K119: =20*H119 -> 3660
A120: V2 | B120: =781*H120 -> 101530 | C120: =J120+G120+I120+K120 -> 42120 | D120: =B120-C120 -> 59410 | E120: =D120/B120*100 -> 58.514725 | F120: =D120/H120 -> 457 | G120: =304*H120 -> 39520 | H120: 130 | I120: 0 | J120: =L120%*M120 -> 0 | K120: =20*H120 -> 2600
A121: V6 | B121: =843*H121 -> 127293 | C121: =J121+G121+I121+K121 -> 49528 | D121: =B121-C121 -> 77765 | E121: =D121/B121*100 -> 61.09134 | F121: =D121/H121 -> 515 | G121: =308*H121 -> 46508 | H121: 151 | I121: 0 | J121: =L121%*M121 -> 0 | K121: =20*H121 -> 3020
B122: =SUM(B118:B121) -> 424052 | C122: =SUM(C118:C121) -> 174100 | D122: =SUM(D118:D121) -> 249952 | E122: =SUM(E118:E121) -> 227.94846 | F122: =SUM(F118:F121) -> 1576 | G122: =SUM(G118:G121) -> 161060 | H122: =SUM(H118:H121) -> 652 | J122: =161733 -> 161733 | K122: =SUM(K118:K121) -> 13040
A125: Total Revenue | B125: =B122 -> 424052 | D125: Blended | E125: 125/pcs
...

Sheet Nov 25
A1: Nov | B1: Shopify
A3: Products | B3: Total Delivered Revenue | C3: Total expense | D3: Total P/L | E3: Profit % | F3: P/pcs | G3: Ad spent | H3: Total orders | I3: Shipped | J3: Total COGS | K3: Delivered | L3: Shipping charges | M3: RTO | N3: In-transit | O3: RTO% | P3: Shipped% | Q3: Delivered % | R3: CPD | S3: Cancellation % | T3: COGS/Unit
A4: V1 | B4: 1261476.8 | C4: =G4+J4+L4 -> 476693 | E4: =D4/B4*100 -> 0 | F4: =D4/K4 -> 0 | H4: 1616 | I4: 1601 | J4: =K4*T4 -> 327800 | K4: 1490 | L4: =I4*93 -> 148893 | M4: =I4-K4-N4 -> 107 | N4: 4 | O4: =IFERROR(M4/I4*100,0) -> 6.6833229 | P4: =I4/H4*100 -> 99.071782 | Q4: =K4/I4*100 -> 93.066833 | R4: =G4/K4 -> 0 | S4: =(I4-H4)/H4 -> -0.0092821782 | T4: 220
A5: V1- P of 2 | B5: 43047.62 | C5: =G5+J5+L5 -> 15296 | E5: =D5/B5*100 -> 0 | F5: =D5/K5 -> 0 | H5: 32 | I5: 32 | J5: =K5*T5 -> 12320 | K5: 28 | L5: =I5*93 -> 2976 | M5: =I5-K5-N5 -> 4 | O5: =IFERROR(M5/I5*100,0) -> 12.5 | P5: =I5/H5*100 -> 100 | Q5: =K5/I5*100 -> 87.5 | R5: =G5/K5 -> 0 | S5: =(I5-H5)/H5 -> 0 | T5: 440
A6: V2 | B6: 1187763.4 | C6: =G6+J6+L6 -> 460335 | E6: =D6/B6*100 -> 0 | F6: =D6/K6 -> 0 | H6: 1260 | I6: 1243 | J6: =K6*T6 -> 344736 | K6: 1134 | L6: =I6*93 -> 115599 | M6: =I6-K6-N6 -> 105 | N6: 4 | O6: =IFERROR(M6/I6*100,0) -> 8.4473049 | P6: =I6/H6*100 -> 98.650794 | Q6: =K6/I6*100 -> 91.230893 | R6: =G6/K6 -> 0 | S6: =(I6-H6)/H6 -> -0.013492063 | T6: 304
A7: V2- P of 2 | B7: 40108.74 | C7: =G7+J7+L7 -> 14020 | E7: =D7/B7*100 -> 0 | F7: =D7/K7 -> 0 | H7: 21 | I7: 20 | J7: =K7*T7 -> 12160 | K7: 20 | L7: =I7*93 -> 1860 | M7: =I7-K7-N7 -> -2 | N7: 2 | O7: =IFERROR(M7/I7*100,0) -> -10 | P7: =I7/H7*100 -> 95.238095 | Q7: =K7/I7*100 -> 100 | R7: =G7/K7 -> 0 | S7: =(I7-H7)/H7 -> -0.047619048 | T7: 608
A8: V3 | B8: 286681.15 | C8: =G8+J8+L8 -> 153615 | E8: =D8/B8*100 -> 0 | F8: =D8/K8 -> 0 | H8: 228 | I8: 221 | J8: =K8*T8 -> 133062 | K8: 201 | L8: =I8*93 -> 20553 | M8: =I8-K8-N8 -> 20 | O8: =IFERROR(M8/I8*100,0) -> 9.0497738 | P8: =I8/H8*100 -> 96.929825 | Q8: =K8/I8*100 -> 90.950226 | R8: =G8/K8 -> 0 | S8: =(I8-H8)/H8 -> -0.030701754 | T8: 662
A9: V4 | B9: 118197.48 | C9: =G9+J9+L9 -> 69355 | E9: =D9/B9*100 -> 0 | F9: =D9/K9 -> 0 | H9: 271 | I9: 263 | J9: =K9*T9 -> 44896 | K9: 244 | L9: =I9*93 -> 24459 | M9: =I9-K9-N9 -> 19 | O9: =IFERROR(M9/I9*100,0) -> 7.2243346 | P9: =I9/H9*100 -> 97.04797 | Q9: =K9/I9*100 -> 92.775665 | R9: =G9/K9 -> 0 | S9: =(I9-H9)/H9 -> -0.029520295 | T9: 184
A10: V4- P of 2 | B10: 20969.46 | C10: =G10+J10+L10 -> 10789 | E10: =D10/B10*100 -> 0 | F10: =D10/K10 -> 0 | H10: 26 | I10: 25 | J10: =K10*T10 -> 8464 | K10: 23 | L10: =I10*93 -> 2325 | M10: =I10-K10-N10 -> 2 | O10: =IFERROR(M10/I10*100,0) -> 8 | P10: =I10/H10*100 -> 96.153846 | Q10: =K10/I10*100 -> 92 | R10: =G10/K10 -> 0 | S10: =(I10-H10)/H10 -> -0.038461538 | T10: 368
A11: V4- P of 3 | B11: 0 | C11: =G11+J11+L11 -> 0 | E11: =D11/B11*100 -> #DIV/0! | F11: =D11/K11 -> #DIV/0! | H11: 0 | I11: 0 | J11: =K11*T11 -> 0 | K11: 0 | L11: =I11*93 -> 0 | M11: =I11-K11-N11 -> 0 | O11: =IFERROR(M11/I11*100,0) -> 0 | P11: =I11/H11*100 -> #DIV/0! | Q11: =K11/I11*100 -> #DIV/0! | R11: =G11/K11 -> #DIV/0! | S11: =(I11-H11)/H11 -> #DIV/0! | T11: 368
A12: V5 | B12: 0 | C12: 0 | E12: 0 | F12: 0 | H12: 0 | I12: 0 | J12: 0 | K12: 0 | L12: =I12*93 -> 0 | M12: =I12-K12-N12 -> 0 | O12: =IFERROR(M12/I12*100,0) -> 0 | P12: =I12/H12*100 -> #DIV/0! | Q12: =K12/I12*100 -> #DIV/0! | S12: =(I12-H12)/H12 -> #DIV/0! | T12: 206
A13: V6 | B13: 1243580.8 | C13: =G13+J13+L13 -> 490774 | E13: =D13/B13*100 -> 0 | F13: =D13/K13 -> 0 | H13: 1373 | I13: 1346 | J13: =K13*T13 -> 365596 | K13: 1187 | L13: =I13*93 -> 125178 | M13: =I13-K13-N13 -> 153 | N13: 6 | O13: =IFERROR(M13/I13*100,0) -> 11.367013 | P13: =I13/H13*100 -> 98.033503 | Q13: =K13/I13*100 -> 88.187221 | R13: =G13/K13 -> 0 | S13: =(I13-H13)/H13 -> -0.019664967 | T13: 308
A14: V6- P of 2 | B14: 44843.53 | C14: =G14+J14+L14 -> 17202 | E14: =D14/B14*100 -> 0 | F14: =D14/K14 -> 0 | H14: 26 | I14: 26 | J14: =K14*T14 -> 14784 | K14: 24 | L14: =I14*93 -> 2418 | M14: =I14-K14-N14 -> 2 | O14: =IFERROR(M14/I14*100,0) -> 7.6923077 | P14: =I14/H14*100 -> 100 | Q14: =K14/I14*100 -> 92.307692 | R14: =G14/K14 -> 0 | S14: =(I14-H14)/H14 -> 0 | T14: 616
A15: V7 | B15: 0 | C15: =G15+J15+L15 -> 0 | E15: =D15/B15*100 -> #DIV/0! | F15: =D15/K15 -> #DIV/0! | H15: 0 | I15: 0 | J15: =K15*T15 -> 0 | K15: 0 | L15: =I15*93 -> 0 | M15: =I15-K15-N15 -> 0 | O15: =IFERROR(M15/I15*100,0) -> 0 | P15: =I15/H15*100 -> #DIV/0! | Q15: =K15/I15*100 -> #DIV/0! | R15: =G15/K15 -> #DIV/0! | S15: =(I15-H15)/H15 -> #DIV/0! | T15: 435
A16: V8 | B16: 0 | C16: 0 | E16: =D16/B16*100 -> #DIV/0! | F16: 0 | H16: 0 | I16: 0 | J16: =K16*T16 -> 0 | K16: 0 | L16: =I16*93 -> 0 | M16: =I16-K16-N16 -> 0 | O16: =IFERROR(M16/I16*100,0) -> 0 | P16: =I16/H16*100 -> #DIV/0! | Q16: =K16/I16*100 -> #DIV/0! | S16: =(I16-H16)/H16 -> #DIV/0! | T16: 699
A17: V9 | B17: 1435132.9 | C17: =G17+J17+L17 -> 724087 | E17: =D17/B17*100 -> 0 | F17: =D17/K17 -> 0 | H17: 950 | I17: 901 | J17: =K17*T17 -> 640294 | K17: 823 | L17: =I17*93 -> 83793 | M17: =I17-K17-N17 -> 69 | N17: 9 | O17: =IFERROR(M17/I17*100,0) -> 7.6581576 | P17: =I17/H17*100 -> 94.842105 | Q17: =K17/I17*100 -> 91.342952 | R17: =G17/K17 -> 0 | S17: =(I17-H17)/H17 -> -0.051578947 | T17: 778
A18: V9 P of 2 | B18: 65297.75 | C18: =G18+J18+L18 -> 41225 | E18: =D18/B18*100 -> 0 | F18: =D18/K18 -> 0 | H18: 28 | I18: 25 | J18: =K18*T18 -> 38900 | K18: 25 | L18: =I18*93 -> 2325 | M18: =I18-K18-N18 -> 0 | O18: =IFERROR(M18/I18*100,0) -> 0 | P18: =I18/H18*100 -> 89.285714 | Q18: =K18/I18*100 -> 100 | R18: =G18/K18 -> 0 | S18: =(I18-H18)/H18 -> -0.10714286 | T18: 1556
A19: V10 | B19: 97406.06 | C19: =G19+J19+L19 -> 64102 | E19: =D19/B19*100 -> 0 | F19: =D19/K19 -> 0 | H19: 65 | I19: 60 | J19: =K19*T19 -> 58522 | K19: 58 | L19: =I19*93 -> 5580 | M19: =I19-K19-N19 -> 2 | O19: =IFERROR(M19/I19*100,0) -> 3.3333333 | P19: =I19/H19*100 -> 92.307692 | Q19: =K19/I19*100 -> 96.666667 | R19: =G19/K19 -> 0 | S19: =(I19-H19)/H19 -> -0.076923077 | T19: 1009
A20: Busy Book | B20: 0 | C20: 0 | E20: 0 | F20: 0 | H20: 0 | I20: 0 | J20: =K20*T20 -> 0 | K20: 0 | L20: =I20*93 -> 0 | M20: =I20-K20-N20 -> 0 | O20: =IFERROR(M20/I20*100,0) -> 0 | P20: 0 | Q20: 0 | R20: 0 | S20: =(I20-H20)/H20 -> #DIV/0! | T20: 250
A21: Busy Book Pink | B21: 182251.84 | C21: =G21+J21+L21 -> 89427 | E21: =D21/B21*100 -> 0 | F21: =D21/K21 -> 0 | H21: 256 | I21: 239 | J21: =K21*T21 -> 67200 | K21: 224 | L21: =I21*93 -> 22227 | M21: =I21-K21-N21 -> 15 | O21: =IFERROR(M21/I21*100,0) -> 6.2761506 | P21: =I21/H21*100 -> 93.359375 | Q21: =K21/I21*100 -> 93.723849 | R21: =G21/K21 -> 0 | S21: =(I21-H21)/H21 -> -0.06640625 | T21: 300
A22: Busy Book Blue | B22: 125830.43 | C22: =G22+J22+L22 -> 60573 | E22: =D22/B22*100 -> 0 | F22: =D22/K22 -> 0 | H22: 166 | I22: 161 | J22: =K22*T22 -> 45600 | K22: 152 | L22: =I22*93 -> 14973 | M22: =I22-K22-N22 -> 9 | O22: =IFERROR(M22/I22*100,0) -> 5.5900621 | P22: =I22/H22*100 -> 96.987952 | Q22: =K22/I22*100 -> 94.409938 | R22: =G22/K22 -> 0 | S22: =(I22-H22)/H22 -> -0.030120482 | T22: 300
A23: Human Book | B23: 0 | C23: =G23+J23+L23 -> 0 | E23: =D23/B23*100 -> #DIV/0! | F23: =D23/K23 -> #DIV/0! | H23: 0 | I23: 0 | J23: =K23*T23 -> 0 | K23: 0 | L23: =I23*93 -> 0 | M23: =I23-K23-N23 -> 0 | O23: =IFERROR(M23/I23*100,0) -> 0 | P23: =I23/H23*100 -> #DIV/0! | Q23: =K23/I23*100 -> #DIV/0! | R23: =G23/K23 -> #DIV/0! | S23: =(I23-H23)/H23 -> #DIV/0! | T23: 300
A24: V9-V3 Combo | B24: 110191.18 | C24: =G24+J24+L24 -> 59973 | E24: =D24/B24*100 -> 0 | F24: =D24/K24 -> 0 | H24: 43 | I24: 41 | J24: =K24*T24 -> 56160 | K24: 39 | L24: =I24*93 -> 3813 | M24: =I24-K24-N24 -> 2 | O24: =IFERROR(M24/I24*100,0) -> 4.8780488 | P24: =I24/H24*100 -> 95.348837 | Q24: =K24/I24*100 -> 95.121951 | R24: =G24/K24 -> 0 | S24: =(I24-H24)/H24 -> -0.046511628 | T24: 1440
A25: V9-V10 Combo | B25: 47560.67 | C25: =G25+J25+L25 -> 33840 | E25: =D25/B25*100 -> 0 | F25: =D25/K25 -> 0 | H25: 21 | I25: 18 | J25: =K25*T25 -> 32166 | K25: 18 | L25: =I25*93 -> 1674 | M25: =I25-K25-N25 -> 0 | O25: =IFERROR(M25/I25*100,0) -> 0 | P25: =I25/H25*100 -> 85.714286 | Q25: =K25/I25*100 -> 100 | R25: =G25/K25 -> 0 | S25: =(I25-H25)/H25 -> -0.14285714 | T25: 1787
A26: V7-V4 Combo | B26: 0 | C26: =G26+J26+L26 -> 0 | E26: =D26/B26*100 -> #DIV/0! | F26: =D26/K26 -> #DIV/0! | H26: 0 | I26: 0 | J26: =K26*T26 -> 0 | K26: 0 | L26: =I26*93 -> 0 | M26: =I26-K26-N26 -> 0 | O26: =IFERROR(M26/I26*100,0) -> 0 | P26: =I26/H26*100 -> #DIV/0! | Q26: =K26/I26*100 -> #DIV/0! | R26: =G26/K26 -> #DIV/0! | S26: =(I26-H26)/H26 -> #DIV/0! | T26: 619
A27: V1-V4 Combo | B27: 76537.95 | C27: =G27+J27+L27 -> 31404 | E27: =D27/B27*100 -> 0 | F27: =D27/K27 -> 0 | H27: 64 | I27: 64 | J27: =K27*T27 -> 25452 | K27: 63 | L27: =I27*93 -> 5952 | M27: =I27-K27-N27 -> 1 | O27: =IFERROR(M27/I27*100,0) -> 1.5625 | P27: =I27/H27*100 -> 100 | Q27: =K27/I27*100 -> 98.4375 | R27: =G27/K27 -> 0 | S27: =(I27-H27)/H27 -> 0 | T27: 404
A28: V1-V7 Combo | B28: 0 | C28: =G28+J28+L28 -> 0 | E28: =D28/B28*100 -> #DIV/0! | F28: =D28/K28 -> #DIV/0! | H28: 0 | I28: 0 | J28: =K28*T28 -> 0 | K28: 0 | L28: =I28*93 -> 0 | M28: =I28-K28-N28 -> 0 | O28: =IFERROR(M28/I28*100,0) -> 0 | P28: =I28/H28*100 -> #DIV/0! | Q28: =K28/I28*100 -> #DIV/0! | R28: =G28/K28 -> #DIV/0! | S28: =(I28-H28)/H28 -> #DIV/0! | T28: 655
A29: V6-V2 Combo | B29: 29862.97 | C29: =G29+J29+L29 -> 10575 | E29: =D29/B29*100 -> 0 | F29: =D29/K29 -> 0 | H29: 17 | I29: 15 | J29: =K29*T29 -> 9180 | K29: 15 | L29: =I29*93 -> 1395 | M29: =I29-K29-N29 -> 0 | O29: =IFERROR(M29/I29*100,0) -> 0 | P29: =I29/H29*100 -> 88.235294 | Q29: =K29/I29*100 -> 100 | R29: =G29/K29 -> 0 | S29: =(I29-H29)/H29 -> -0.11764706 | T29: 612
A30: V6-V7 Combo | B30: 0 | C30: =G30+J30+L30 -> 0 | E30: =D30/B30*100 -> #DIV/0! | F30: =D30/K30 -> #DIV/0! | H30: 0 | I30: 0 | J30: =K30*T30 -> 0 | K30: 0 | L30: =I30*93 -> 0 | M30: =I30-K30-N30 -> 0 | O30: =IFERROR(M30/I30*100,0) -> 0 | P30: =I30/H30*100 -> #DIV/0! | Q30: =K30/I30*100 -> #DIV/0! | R30: =G30/K30 -> #DIV/0! | S30: =(I30-H30)/H30 -> #DIV/0! | T30: 743
A31: V2-V7 Combo | B31: 0 | C31: =G31+J31+L31 -> 0 | E31: =D31/B31*100 -> #DIV/0! | F31: =D31/K31 -> #DIV/0! | H31: 0 | I31: 0 | J31: =K31*T31 -> 0 | K31: 0 | L31: =I31*93 -> 0 | M31: =I31-K31-N31 -> 0 | O31: =IFERROR(M31/I31*100,0) -> 0 | P31: =I31/H31*100 -> #DIV/0! | Q31: =K31/I31*100 -> #DIV/0! | R31: =G31/K31 -> #DIV/0! | S31: =(I31-H31)/H31 -> #DIV/0! | T31: 739
A32: V1-V2 Combo | B32: 74886.29 | C32: =G32+J32+L32 -> 24342 | E32: =D32/B32*100 -> 0 | F32: =D32/K32 -> 0 | H32: 43 | I32: 42 | J32: =K32*T32 -> 20436 | K32: 39 | L32: =I32*93 -> 3906 | M32: =I32-K32-N32 -> 3 | O32: =IFERROR(M32/I32*100,0) -> 7.1428571 | P32: =I32/H32*100 -> 97.674419 | Q32: =K32/I32*100 -> 92.857143 | R32: =G32/K32 -> 0 | S32: =(I32-H32)/H32 -> -0.023255814 | T32: 524
... A34: V2-V4 Combo | B34: 25304.72 | C34: =G34+J34+L34 -> 9877 | E34: =D34/B34*100 -> 0 | F34: =D34/K34 -> 0 | H34: 17 | I34: 17 | J34: =K34*T34 -> 8296 | K34: 17 | L34: =I34*93 -> 1581 | M34: =I34-K34-N34 -> 0 | O34: =IFERROR(M34/I34*100,0) -> 0 | P34: =I34/H34*100 -> 100 | Q34: =K34/I34*100 -> 100 | R34: =G34/K34 -> 0 | S34: =(I34-H34)/H34 -> 0 | T34: 488
A35: Total | B35: =sum(B4:B34)+80000 -> 6605422.4 | D35: =SUM(D4:D34) -> 0 | G35: 4231133 | H35: =SUM(H4:H34) -> 6528 | I35: =SUM(I4:I34) -> 6365 | J35: =SUM(J4:J34) -> 2268484 | K35: =SUM(K4:K34) -> 5829 | L35: =SUM(L4:L34) -> 591945 | M35: =SUM(M4:M34) -> 511 | N35: =SUM(N4:N34) -> 25 | O35: =M35/K35 -> 0.087665123 | P35: =I35/H35 -> 0.97503064 | Q35: =K35/H35 -> 0.89292279 | R35: =SUM(R4:R34) -> #DIV/0! | S35: =(I35-H35)/H35 -> -0.024969363
N37: =N35*1000 -> 25000 | O37: =N35/H35 -> 0.0038296569
D38: Blended
A39: Total Units Sold | B39: =K35 -> 5829
A40: Total Revenue | B40: =B35 -> 6605422.4 | D40: COGS | E40: =B41/B39 -> 389.17207 | F40: =E40/E43 -> 0.34342754 | I40: =B17/K17 -> 1743.7824
A41: COGS | B41: =J35 -> 2268484 | D41: CAC | E41: =G35/B39 -> 725.87631
A42: Logistics | B42: =L35 -> 591945 | D42: Logistics | E42: =B42/B39 -> 101.55172
A43: Marketing | B43: =G35 -> 4231133 | D43: AOV | E43: =B40/B39 -> 1133.1999
A44: P&L | B44: =B40-(B41+B42+B43) -> -486139.57
A45: P&L % | B45: =B44/B40 -> -0.073597045
A49: NOV | B49: Amazon
B51: Total revenue | C51: Total expense | D51: Total P/L | E51: Profit % | F51: P/pcs | G51: Total orders | H51: Product expense | I51: Delivered | J51: Return | K51: Amazon expense | L51: RTO% | M51: Only Ad spend | N51: Return GMV
A52: V1 | B52: =434949.67+167454.21+1899 -> 604302.88 | C52: =K52+H52+M52 -> 317168.69 | D52: =B52-C52 -> 287134.19 | E52: =D52/B52*100 -> 47.514946 | F52: =D52/I52 -> 493.35771 | G52: =512+130+1 -> 643 | H52: =220*I52 -> 128040 | I52: =453+129 -> 582 | J52: =G52-I52 -> 61 | K52: =(154009.79+30907.36+283.39 )-(98903.85) -> 86296.69 | L52: =J52/I52*100 -> 10.4811 | M52: 102832 | N52: =J52*999 -> 60939 | O52: =B52/M52 -> 5.8766034 | P52: =B52/#REF!*100 -> #REF!
A53: V2 | B53: =121716+156197.79 -> 277913.79 | C53: =K53+H53+M53 -> 173153.02 | D53: =B53-C53 -> 104760.77 | E53: =D53/B53*100 -> 37.69542 | F53: =D53/I53 -> 482.76853 | G53: =84+155 -> 239 | H53: =304*I53 -> 65968 | I53: =84+133 -> 217 | J53: =G53-I53 -> 22 | K53: =(21882.26+52072.52 )-14346.76 -> 59608.02 | L53: =J53/G53*100 -> 9.2050209 | M53: 47577 | N53: =J53*1119 -> 24618 | O53: =B53/M53 -> 5.8413475 | P53: =B53/#REF!*100 -> #REF!
A54: V3 | B54: =9565.24 -> 9565.24 | C54: =K54+H54+M54 -> 12642.1 | D54: =B54-C54 -> -3076.86 | E54: =D54/B54*100 -> -32.167097 | F54: =D54/I54 -> -512.81 | G54: =10 -> 10 | H54: =662*I54 -> 3972 | I54: =6 -> 6 | J54: =G54-I54 -> 4 | K54: =3439.1 -> 3439.1 | L54: =J54/G54*100 -> 40 | M54: 5231 | N54: =J54*1799 -> 7196 | O54: =B54/M54 -> 1.8285682 | P54: =B54/#REF!*100 -> #REF!
A55: V4 | B55: =36308.68+230929.11+899 -> 268136.79 | C55: =K55+H55+M55 -> 86722.48 | D55: =B55-C55 -> 181414.31 | E55: =D55/B55*100 -> 67.657374 | F55: =D55/I55 -> 307.48188 | G55: =56+565+1 -> 622 | H55: =9585.96 -> 9585.96 | I55: =56+533+1 -> 590 | J55: =G55-I55 -> 32 | K55: =(9585.96+63972.15+34)-(4848.98+26861.61) -> 41881.52 | L55: =J55/G55*100 -> 5.1446945 | M55: 35255 | N55: =J55*499 -> 15968 | O55: =B55/M55 -> 7.6056386 | P55: =B55/#REF!*100 -> #REF! | Q55: =36308.68+899+230929.11 -> 268136.79 | R55: =Z55+W55+AB55 -> 84861.88 | S55: =Q55-R55 -> 183274.91 | T55: =S55/Q55*100 -> 68.351273 | U55: =S55/X55 -> 181.28082 | V55: =56+1+565 -> 622 | W55: =9585.96 -> 9585.96 | X55: =56+1+421+533 -> 1011 | Y55: =V55-X55 -> -389 | Z55: =(9585.96+34+63972.15)-(6709.58+26861.61) -> 40020.92 | AA55: =Y55/V55*100 -> -62.540193 | AB55: 35255 | AC55: =Y55*499 -> -194111 | AD55: =Q55/AB55 -> 7.6056386 | AE55: =Q55/#REF!*100 -> #REF!
A56: V6 | B56: =151407.6+3174 -> 154581.6 | C56: =K56+H56+M56 -> 142391.54 | D56: =B56-C56 -> 12190.06 | E56: =D56/B56*100 -> 7.8858415 | F56: =D56/I56 -> 95.984724 | G56: =160+2 -> 162 | H56: =308*I56 -> 39116 | I56: =125+2 -> 127 | J56: =35 -> 35 | K56: =(87643.03+1256.56)-(46876.09+8.96) -> 42014.54 | L56: =J56/G56*100 -> 21.604938 | M56: 61261 | N56: =J56*1249 -> 43715 | O56: =B56/M56 -> 2.5233281 | P56: =B56/#REF!*100 -> #REF!
A57: V7 | B57: =62.53 -> 62.53 | C57: =K57+H57+M57 -> 4309.17 | D57: =B57-C57 -> -4246.64 | E57: =D57/B57*100 -> -6791.3641 | F57: =D57/I57 -> -1061.66 | G57: =3 -> 3 | H57: =435*I57 -> 1740 | I57: =4 -> 4 | J57: =G57-I57 -> -1 | K57: =(2539.28)-(1557.11) -> 982.17 | L57: =J57/G57*100 -> -33.333333 | M57: 1587 | N57: =J57*1349 -> -1349 | O57: =B57/M57 -> 0.039401386 | P57: =B57/#REF!*100 -> #REF!
A58: V9 | B58: =154204.94+9912.62 -> 164117.56 | C58: =K58+H58+M58 -> 123737.69 | D58: =B58-C58 -> 40379.87 | E58: =D58/B58*100 -> 24.604235 | F58: =D58/I58 -> 475.05729 | G58: =98+5 -> 103 | H58: =778*I58 -> 66130 | I58: =81+4 -> 85 | J58: =G58-I58 -> 18 | K58: =(45003.36)-(3491.67) -> 41511.69 | L58: =J58/G58*100 -> 17.475728 | M58: 16096 | N58: =J58*1999 -> 35982 | O58: =B58/M58 -> 10.19617 | P58: =B58/#REF!*100 -> #REF!
A59: V10 | B59: =9912.62 -> 9912.62 | C59: =K59+H59+M59 -> 9207.47 | D59: =B59-C59 -> 705.15 | E59: =D59/B59*100 -> 7.1136592 | F59: =D59/I59 -> 176.2875 | G59: =5 -> 5 | H59: =(900)*I59 -> 3600 | I59: =4 -> 4 | J59: =G59-I59 -> 1 | K59: =5607.47 -> 5607.47 | L59: =J59/G59*100 -> 20 | N59: =J59*999 -> 999 | O59: =B59/M59 -> #DIV/0! | P59: =B59/#REF!*100 -> #REF!
A60: BB | B60: =4792 -> 4792 | C60: =K60+H60+M60 -> 2669.52 | E60: =D60/B60*100 -> 0 | F60: =D60/I60 -> 0 | G60: =8 -> 8 | H60: =200*I60 -> 1600 | I60: =8 -> 8 | J60: =G60-I60 -> 0 | K60: =1069.52 -> 1069.52 | L60: =J60/G60*100 -> 0 | N60: =J60*599 -> 0 | O60: =B60/M60 -> #DIV/0! | P60: =B60/#REF!*100 -> #REF!
A61: V1V4 | C61: =K61+H61+M61 -> 0 | D61: =B61-C61 -> 0 | E61: =D61/B61*100 -> #DIV/0! | F61: =D61/I61 -> #DIV/0! | H61: =(270+220)*I61 -> 0 | J61: =G61-I61 -> 0 | L61: =J61/G61*100 -> #DIV/0! | O61: =B61/M61 -> #DIV/0! | P61: =B61/#REF!*100 -> #REF!
A62: V1V2 | C62: =K62+H62+M62 -> 0 | D62: =B62-C62 -> 0 | E62: =D62/B62*100 -> #DIV/0! | F62: =D62/I62 -> #DIV/0! | H62: =(220+304)*I62 -> 0 | J62: =G62-I62 -> 0 | L62: =J62/G62*100 -> #DIV/0! | N62: =J62*2199 -> 0 | O62: =B62/M62 -> #DIV/0! | P62: =B62/#REF!*100 -> #REF!
A63: V1V6 | C63: =K63+H63+M63 -> 0 | D63: =B63-C63 -> 0 | E63: =D63/B63*100 -> #DIV/0! | F63: =D63/I63 -> #DIV/0! | H63: =(220+308)*I63 -> 0 | J63: =G63-I63 -> 0 | L63: =J63/G63*100 -> #DIV/0! | N63: =J63*999 -> 0 | O63: =B63/M63 -> #DIV/0! | P63: =B63/#REF!*100 -> #REF!
A64: V2V4 | B64: =4797 -> 4797 | C64: =K64+H64+M64 -> 2280.67 | D64: =B64-C64 -> 2516.33 | E64: =D64/B64*100 -> 52.456327 | F64: =D64/I64 -> 838.77667 | G64: =3 -> 3 | H64: =(304+184)*I64 -> 1464 | I64: =3 -> 3 | J64: =G64-I64 -> 0 | K64: =816.67 -> 816.67 | L64: =J64/G64*100 -> 0 | N64: =J64*1499 -> 0 | O64: =B64/M64 -> #DIV/0! | P64: =B64/#REF!*100 -> #REF!
A65: V2V6 | B65: =4368.1 -> 4368.1 | C65: =K65+H65+M65 -> 0 | D65: =B65-C65 -> 4368.1 | E65: =D65/B65*100 -> 100 | F65: =D65/I65 -> #DIV/0! | H65: =(304+308)*I65 -> 0 | J65: =G65-I65 -> 0 | L65: =J65/G65*100 -> #DIV/0! | N65: =J65*999 -> 0 | O65: =B65/M65 -> #DIV/0! | P65: =B65/#REF!*100 -> #REF!
A66: V9V10 | C66: =K66+H66+M66 -> 0 | D66: =B66-C66 -> 0 | E66: =D66/B66*100 -> #DIV/0! | F66: =D66/I66 -> #DIV/0! | H66: =(1900)*I66 -> 0 | J66: =G66-I66 -> 0 | L66: =J66/G66*100 -> #DIV/0! | N66: =J66*999 -> 0 | O66: =B66/M66 -> #DIV/0! | P66: =B66/#REF!*100 -> #REF!
A67: BB's | B67: =28067.14+3598+1998+1799 -> 35462.14 | C67: =K67+H67+M67 -> 29956.91 | D67: =B67-C67 -> 5505.23 | E67: =D67/B67*100 -> 15.524246 | F67: =D67/I67 -> 161.91853 | G67: =1+31+2+2 -> 36 | H67: =(330)*I67 -> 11220 | I67: =1+29+2+2 -> 34 | J67: =G67-I67 -> 2 | K67: =5876.73+432.67+5876.73+578.78 -> 12764.91 | L67: =J67/G67*100 -> 5.5555556 | M67: =5816+156 -> 5972 | N67: =J67*999 -> 1998 | O67: =B67/M67 -> 5.9380676 | P67: =B67/#REF!*100 -> #REF!
A68: HBB | B68: =43477.83 -> 43477.83 | C68: =K68+H68+M68 -> 21392.26 | D68: =B68-C68 -> 22085.57 | E68: =D68/B68*100 -> 50.797314 | F68: =D68/I68 -> 408.99204 | G68: =57 -> 57 | H68: =(330)*I68 -> 17820 | I68: =54 -> 54 | J68: =G68-I68 -> 3 | K68: =41312.85 -37740.59 -> 3572.26 | L68: =J68/G68*100 -> 5.2631579 | N68: =J68*999 -> 2997 | O68: =B68/M68 -> #DIV/0!
A69: Total | B69: =SUM(B52:B68) -> 1581490.1 | C69: =SUM(C52:C68) -> 925631.52 | D69: =SUM(D52:D68) -> 653736.08 | G69: =SUM(G52:G68) -> 1891 | H69: =SUM(H52:H68) -> 350255.96 | I69: =SUM(I52:I68) -> 1714 | K69: =SUM(K52:K68) -> 299564.56 | M69: =SUM(M52:M68) -> 275811
A72: Total Revenue | B72: =B69 -> 1581490.1
A73: COGS | B73: =H69 -> 350255.96 | D73: Blended
A74: Amazon Ex | B74: 190954 | D74: COGS | E74: =B73/I69 -> 204.35003 | I74: =B75/I69 -> 62.281214
A75: Logi | B75: 106750
A76: Marketing | B76: =M69 -> 275811 | D76: CAC | E76: =B76/I69 -> 160.91657
A77: Net P&L | B77: =B72-SUM(B73:B76) -> 657719.12 | D77: Commisions | E77: =B74/I69 -> 111.4084 | H77: =B69/I69 -> 922.68966
A78: P&L % | B78: =B77/B72*100 -> 41.588571 | D78: AOV | E78: =B72/I69 -> 922.68966
A85: NOV | B85: Flipkart
B87: Total revenue | C87: Total expense | D87: Total P/L | E87: Profit % | F87: P/pcs | G87: Total orders | H87: Product expense | I87: Delivered | J87: Return | K87: Flipkart expenses | L87: RTO% | M87: Only Ad spend
A88: V1 | B88: =4364 -> 4364 | C88: =K88+H88 -> 2340 | D88: =B88-C88 -> 2024 | E88: =D88/B88*100 -> 46.379468 | F88: =D88/I88 -> 337.33333 | G88: =10 -> 10 | H88: =220*I88 -> 1320 | I88: =6 -> 6 | J88: =G88-I88 -> 4 | K88: =1020 -> 1020 | L88: =J88/G88*100 -> 40
A89: V2 | B89: =25705 -> 25705 | C89: =K89+H89 -> 12977 | D89: =B89-C89 -> 12728 | E89: =D89/B89*100 -> 49.515658 | F89: =D89/I89 -> 424.26667 | G89: =42 -> 42 | H89: =304*I89 -> 9120 | I89: =30 -> 30 | J89: =G89-I89 -> 12 | K89: 3857 | L89: =J89/G89*100 -> 28.571429
